Workbook
Name DATAFILNAVN: '[1]L Basis sokkel'!$C$2
Name DATAARK2: '[1]A Innh'!$P$7

Sheet SNKS
B3: 2007 | C3: 2008 | D3: 2009 | E3: 2010 | F3: 2011 | G3: 2012 | H3: 2013 | I3: 2014 | J3: 2015 | K3: 2016 | L3: 2017 | M3: 2018 | N3: 2019 | O3: 2020 | P3: 2021 | Q3: 2022 | R3: 2023 | S3: 2024 | T3: 2025 | U3: 2026 | V3: 2027 | W3: 2028 | X3: 2029 | Y3: 2030 | Z3: 2031 | AA3: 2032 | AB3: 2033 | AC3: 2034 | AD3: 2035 | AE3: 2036 | AF3: 2037 | AG3: 2038 | AH3: 2039 | AI3: 2040 | AJ3: 2041 | AK3: 2042 | AL3: 2043 | AM3: 2044 | AN3: 2045 | AO3: 2046 | AP3: 2047 | AQ3: 2048 | AR3: 2049 | AS3: 2050 | AT3: 2051 | AU3: 2052 | AV3: 2053 | AW3: 2054 | AX3: 2055 | AY3: 2056 | AZ3: 2057 | BA3: 2058 | BB3: 2059 | BC3: 2060 | BD3: 2061 | BE3: 2062 | BF3: 2063 | BG3: 2064 | BH3: 2065 | BI3: 2066 | BJ3: 2067 | BK3: 2068 | BL3: 2069 | BM3: 2070 | BN3: 2071 | BO3: 2072 | BP3: 2073 | BQ3: 2074 | BR3: 2075 | BS3: 2076 | BT3: 2077 | BU3: 2078 | BV3: 2079 | BW3: 2080 | BX3: 2081 | BY3: 2082 | BZ3: 2083 | CA3: 2084 | CB3: 2085 | CC3: 2086 | CD3: 2087 | CE3: 2088 | CF3: 2089 | CG3: 2090
A4: OEDs anslag på påløpte skatter og avgifter
A5: Ordinær inntektsskatt (Påløpt) | I5: 60138 | J5: 37796 | K5: 21816 | L5: 34261.815 | M5: 51315 | N5: 36861.546 | O5: 18353.446 | P5: 100738.24 | Q5: 278750.99 | R5: 148738.99 | S5: 123447.59 | T5: 113057.81 | U5: 79111.769 | V5: 61731.884 | W5: 53717.917 | X5: 48154.134 | Y5: 33976.939 | Z5: 34056.2 | AA5: 34943.587 | AB5: 35075.418 | AC5: 37388.296 | AD5: 39542.572 | AE5: 40283.955 | AF5: 38056.097 | AG5: 34508.552 | AH5: 32815.23 | AI5: 31607.413 | AJ5: 30416.088 | AK5: 27739.584 | AL5: 26647.806 | AM5: 24967.08 | AN5: 23170.601 | AO5: 21911.493 | AP5: 20928.576 | AQ5: 21671.312 | AR5: 21645.065 | AS5: 20456.332 | AT5: 20912.886 | AU5: 18907.424 | AV5: 17694.763 | AW5: 16332.818 | AX5: 15475.962 | AY5: 16093.912 | AZ5: 15911.787 | BA5: 13614.459 | BB5: 12898.107 | BC5: 11809.592
A6: Særskatt (Påløpt) | I6: 98701 | J6: 58513 | K6: 35058 | L6: 63762.704 | M6: 105445 | N6: 84676.523 | O6: -30102.969 | P6: 193549.05 | Q6: 659385.81 | R6: 319897.55 | S6: 260941.74 | T6: 242277.94 | U6: 185567.5 | V6: 164146.87 | W6: 164228.33 | X6: 151850.93 | Y6: 114611.77 | Z6: 110678.25 | AA6: 106452.01 | AB6: 101299.1 | AC6: 108538.28 | AD6: 115480.14 | AE6: 118072.07 | AF6: 113048.9 | AG6: 103083.11 | AH6: 95480.587 | AI6: 88453.795 | AJ6: 85172.445 | AK6: 77329.305 | AL6: 74578.952 | AM6: 70614.447 | AN6: 67073.079 | AO6: 65724.433 | AP6: 61674.244 | AQ6: 63705.011 | AR6: 63265.488 | AS6: 61603.7 | AT6: 63433.239 | AU6: 59597.941 | AV6: 56848.161 | AW6: 52090.024 | AX6: 50654.628 | AY6: 53350.643 | AZ6: 52052.158 | BA6: 44396.377 | BB6: 43820.687 | BC6: 40229.363
A7: Refusjon mot underskudd særskatt | I7: -3805 | J7: -4305 | K7: -2297 | L7: -1992.3761 | M7: -1197 | N7: -1334.5978 | O7: -133.39073 | P7: -2984.1693 | Q7: -2395.6757 | R7: -2702.9706 | S7: -3208.7847 | T7: -3323.468 | U7: -4708.1237 | V7: -3186.109 | W7: -7371.3867 | X7: -8976.0047 | Y7: -15239.473 | Z7: -6534.682 | AA7: -2464.9669 | AB7: -1935.8041 | AC7: -1093.75 | AD7: -1864.9611 | AE7: -2551.7804 | AF7: -2990.4797 | AG7: -3509.3018 | AH7: -2363.5832 | AI7: -1189.2626 | AJ7: -1860.6843 | AK7: -2077.9027 | AL7: -940.65841 | AM7: -950.87582 | AN7: -850.94092 | AO7: -167.95633 | AP7: -644.96991 | AQ7: -4021.3083 | AR7: -4932.3671 | AS7: -184.80182 | AT7: -548.34446 | AU7: -411.24236 | AV7: -482.9807 | AW7: -404.45942 | AX7: -269.99124 | AY7: -147.62065 | AZ7: -588.40853 | BA7: -2.7512848 | BB7: -258.59975 | BC7: -312.41288
A8: Refusjon ubenyttet friinntekt | I8: -7188 | J8: -8132 | K8: -4869 | L8: -5089.2217 | M8: -4332 | N8: -3445.0816 | O8: -161.50569 | P8: -1069.1184 | Q8: -216.96911 | R8: -80.724425 | S8: -66.774 | T8: -5396.2333 | U8: -4240.8334 | V8: -169.448 | W8: -18.668 | X8: 0 | Y8: 0 | Z8: 0 | AA8: 0 | AB8: 0 | AC8: 0 | AD8: 0 | AE8: 0 | AF8: 0 | AG8: 0 | AH8: 0 | AI8: 0 | AJ8: 0 | AK8: 0 | AL8: 0 | AM8: 0 | AN8: 0 | AO8: 0 | AP8: 0 | AQ8: 0 | AR8: 0 | AS8: 0 | AT8: 0 | AU8: 0 | AV8: 0 | AW8: 0 | AX8: 0 | AY8: 0 | AZ8: 0 | BA8: 0 | BB8: 0 | BC8: 0
A9: Produksjonsavgift | I9: 0 | J9: 0 | K9: 0 | L9: 0 | M9: 0 | N9: 0 | O9: 0 | P9: 0 | Q9: 0 | R9: 0 | S9: 0 | T9: 0 | U9: 0 | V9: 0 | W9: 0 | X9: 0 | Y9: 0 | Z9: 0 | AA9: 0 | AB9: 0 | AC9: 0 | AD9: 0 | AE9: 0 | AF9: 0 | AG9: 0 | AH9: 0 | AI9: 0 | AJ9: 0 | AK9: 0 | AL9: 0 | AM9: 0 | AN9: 0 | AO9: 0 | AP9: 0 | AQ9: 0 | AR9: 0 | AS9: 0
A10: Arealavgift | I10: 1766 | J10: 1636 | K10: 1500 | L10: 1359.4042 | M10: 1379.829 | N10: 1488.3013 | O10: 1508.6929 | P10: 1372.141 | Q10: 1209.3158 | R10: 1127.2039 | S10: 1382.3287 | T10: 1472.5541 | U10: 1624.6262 | V10: 1696.2214 | W10: 1879.5041 | X10: 1905.7279 | Y10: 1750.0413 | Z10: 1785.0421 | AA10: 1820.7429 | AB10: 1857.1578 | AC10: 1894.3009 | AD10: 1932.187 | AE10: 1970.8307 | AF10: 2010.2473 | AG10: 2050.4523 | AH10: 2091.4613 | AI10: 2133.2905 | AJ10: 2175.9563 | AK10: 2219.4755 | AL10: 2263.865 | AM10: 2309.1423 | AN10: 2355.3251 | AO10: 2402.4316 | AP10: 2450.4803 | AQ10: 2499.4899 | AR10: 2549.4797 | AS10: 2600.4693 | AT10: 2652.4786 | AU10: 2705.5282 | AV10: 2759.6388 | AW10: 2814.8315 | AX10: 2871.1282 | AY10: 2928.5507 | AZ10: 2987.1218 | BA10: 3046.8642 | BB10: 3107.8015 | BC10: 3169.9575
A11: NOx-avgift | I11: 0 | J11: 0 | K11: 0 | L11: 0 | M11: 0 | N11: 0 | O11: 0 | P11: 0 | Q11: 0 | R11: 0 | S11: 0 | T11: 0 | U11: 0 | V11: 0 | W11: 0 | X11: 0 | Y11: 0 | Z11: 0 | AA11: 0 | AB11: 0 | AC11: 0 | AD11: 0 | AE11: 0 | AF11: 0 | AG11: 0 | AH11: 0 | AI11: 0 | AJ11: 0 | AK11: 0 | AL11: 0 | AM11: 0 | AN11: 0 | AO11: 0 | AP11: 0 | AQ11: 0 | AR11: 0 | AS11: 0 | AT11: 0 | AU11: 0 | AV11: 0 | AW11: 0 | AX11: 0 | AY11: 0 | AZ11: 0 | BA11: 0 | BB11: 0 | BC11: 0
A12: CO2-avgift | I12: 4894 | J12: 5078 | K12: 5365 | L12: 5331.1906 | M12: 5650.0241 | N12: 5790.1281 | O12: 6031.9859 | P12: 5357.6102 | Q12: 7082.6807 | R12: 7586.9975 | S12: 7540.5543 | T12: 9253.362 | U12: 9597.2284 | V12: 9460.3313 | W12: 8459.0003 | X12: 7968.6141 | Y12: 11153.701 | Z12: 10592.486 | AA12: 9681.5216 | AB12: 9602.8419 | AC12: 9105.9987 | AD12: 8763.7091 | AE12: 8839.61 | AF12: 8771.796 | AG12: 8382.0078 | AH12: 8107.1451 | AI12: 7144.8301 | AJ12: 6382.6336 | AK12: 6387.2586 | AL12: 6123.787 | AM12: 5582.5922 | AN12: 4944.2153 | AO12: 4614.685 | AP12: 4447.84 | AQ12: 3953.3849 | AR12: 3678.6206 | AS12: 3399.1007 | AT12: 3351.4057 | AU12: 3563.7522 | AV12: 3616.8768 | AW12: 3324.1837 | AX12: 3331.772 | AY12: 3261.3247 | AZ12: 3293.9937 | BA12: 3396.8859 | BB12: 3229.877 | BC12: 3066.4823
A13: Totale skatter justert for refusjon | I13: =SUM(I5:I8) -> 147846 | J13: =SUM(J5:J8) -> 83872 | K13: =SUM(K5:K8) -> 49708 | L13: =SUM(L5:L8) -> 90942.921 | M13: =SUM(M5:M8) -> 151231 | N13: =SUM(N5:N8) -> 116758.39 | O13: =SUM(O5:O8) -> -12044.419 | P13: =SUM(P5:P8) -> 290234 | ... BC13: =SUM(BC5:BC8) -> 51726.542
A14: Totale avgifter | I14: =SUM(I9:I12) -> 6660 | J14: =SUM(J9:J12) -> 6714 | K14: =SUM(K9:K12) -> 6865 | L14: =SUM(L9:L12) -> 6690.5948 | M14: =SUM(M9:M12) -> 7029.8531 | N14: =SUM(N9:N12) -> 7278.4294 | O14: =SUM(O9:O12) -> 7540.6787 | P14: =SUM(P9:P12) -> 6729.7512 | ... BC14: =SUM(BC9:BC12) -> 6236.4398
A15: Sum skatter og avgifter | I15: =I13+I14 -> 154506 | J15: =J13+J14 -> 90586 | K15: =K13+K14 -> 56573 | L15: =L13+L14 -> 97633.516 | M15: =M13+M14 -> 158260.85 | N15: =N13+N14 -> 124036.82 | O15: =O13+O14 -> -4503.7405 | P15: =P13+P14 -> 296963.75 | ... BC15: =BC13+BC14 -> 57962.982
A18: FINs anslag på påløpte skatter og avgifter (Gul = Overprøving av OED)
A19: (avrundingsfaktor) | I19: 0 | J19: 0 | K19: 0 | L19: 0 | M19: 0 | N19: 0 | O19: 0 | P19: 0 | Q19: 0 | R19: 0 | S19: 0 | T19: 0 | U19: 0 | V19: 0 | W19: 0 | X19: 0 | Y19: 0 | Z19: 0 | AA19: 0 | AB19: 0 | AC19: 0 | AD19: 0 | AE19: 0 | AF19: 0 | AG19: 0 | AH19: 0 | AI19: 0 | AJ19: 0 | AK19: 0 | AL19: 0 | AM19: 0 | AN19: 0 | AO19: 0 | AP19: 0 | AQ19: 0 | AR19: 0 | AS19: 0 | AT19: 0 | AU19: 0 | AV19: 0 | AW19: 0 | AX19: 0 | AY19: 0 | AZ19: 0 | BA19: 0 | BB19: 0 | BC19: 0
A20: Income tax | I20: =I5 -> 60138 | J20: =J5 -> 37796 | K20: =K5 -> 21816 | L20: =L5 -> 34261.815 | M20: =M5 -> 51315 | N20: =N5 -> 36861.546 | O20: =O5 -> 18353.446 | P20: =P5 -> 100738.24 | ... S20: =S5 -> 123447.59 | T20: 107392 | U20: =U5 -> 79111.769 | V20: =V5 -> 61731.884 | W20: =W5 -> 53717.917 | X20: =X5 -> 48154.134 | Y20: =Y5 -> 33976.939 | Z20: =Z5 -> 34056.2 | AA20: =AA5 -> 34943.587 | AB20: =AB5 -> 35075.418 | ... BC20: =BC5 -> 11809.592
A21: Special petroleum tax | I21: =I6 -> 98701 | J21: =J6 -> 58513 | K21: =K6 -> 35058 | L21: =L6 -> 63762.704 | M21: =M6 -> 105445 | N21: =N6 -> 84676.523 | O21: =O6 -> -30102.969 | P21: =P6 -> 193549.05 | ... S21: =S6 -> 260941.74 | T21: 228208 | U21: =U6 -> 185567.5 | V21: =V6 -> 164146.87 | W21: =W6 -> 164228.33 | X21: =X6 -> 151850.93 | Y21: =Y6 -> 114611.77 | Z21: =Z6 -> 110678.25 | AA21: =AA6 -> 106452.01 | AB21: =AB6 -> 101299.1 | ... BC21: =BC6 -> 40229.363
A22: Refusjon mot underskudd særskatt | I22: =I7 -> -3805 | J22: =J7 -> -4305 | K22: =K7 -> -2297 | L22: =L7 -> -1992.3761 | M22: =M7 -> -1197 | N22: =N7 -> -1334.5978 | O22: =O7 -> -133.39073 | P22: =P7 -> -2984.1693 | ... BC22: =BC7 -> -312.41288
A23: Refusjon ubenyttet friinntekt | I23: =I8 -> -7188 | J23: =J8 -> -8132 | K23: =K8 -> -4869 | L23: =L8 -> -5089.2217 | M23: =M8 -> -4332 | N23: =N8 -> -3445.0816 | O23: =O8 -> -161.50569 | P23: =P8 -> -1069.1184 | ... BC23: =BC8 -> 0
A24: Produksjonsavgift | I24: =I9 -> 0 | J24: =J9 -> 0 | K24: =K9 -> 0 | L24: =L9 -> 0 | M24: =M9 -> 0 | N24: =N9 -> 0 | O24: =O9 -> 0 | P24: =P9 -> 0 | ... BC24: =BC9 -> 0
A25: Arealavgift | I25: =I10 -> 1766 | J25: =J10 -> 1636 | K25: =K10 -> 1500 | L25: =L10 -> 1359.4042 | M25: =M10 -> 1379.829 | N25: =N10 -> 1488.3013 | O25: =O10 -> 1508.6929 | P25: =P10 -> 1372.141 | ... BC25: =BC10 -> 3169.9575
A26: CO2-avgift | I26: =I12 -> 4894 | J26: =J12 -> 5078 | K26: =K12 -> 5365 | L26: =L12 -> 5331.1906 | M26: =M12 -> 5650.0241 | N26: =N12 -> 5790.1281 | O26: =O12 -> 6031.9859 | P26: =P12 -> 5357.6102 | ... BC26: =BC12 -> 3066.4823
A27: Nox-avgift | I27: =I11 -> 0 | J27: =J11 -> 0 | K27: =K11 -> 0 | L27: =L11 -> 0 | M27: =M11 -> 0 | N27: =N11 -> 0 | O27: =O11 -> 0 | P27: =P11 -> 0 | ... BC27: =BC11 -> 0
A30: Betalte skatter og avgifter
A31: Income tax | I31: 64212 | J31: 39476.659 | K31: 16034.226 | L31: 23688.095 | M31: 38539.517 | N31: 43011.141 | O31: 16724.759 | P31: 51982.827 | Q31: 212994.79 | R31: 188239.11 | S31: 132693.48 | T31: 121052.35 | U31: =(T20+U20)/2 -> 93251.884 | V31: =(U20+V20)/2 -> 70421.826 | W31: =(V20+W20)/2 -> 57724.9 | X31: =(W20+X20)/2 -> 50936.026 | Y31: =(X20+Y20)/2 -> 41065.537 | Z31: =(Y20+Z20)/2 -> 34016.569 | AA31: =(Z20+AA20)/2 -> 34499.893 | AB31: =(AA20+AB20)/2 -> 35009.502 | ... BC31: =(BB20+BC20)/2 -> 12353.85
A32: Special petroleum tax (adjusted for repayments) | I32: 105837 | J32: 64195.817 | K32: 25058.532 | L32: 41361 | M32: 71773.979 | N32: 90490.326 | O32: 11662.884 | P32: 33728.419 | Q32: 500626.49 | R32: 426187.36 | S32: 278773.96 | T32: 252819.61 | U32: =(T21+U21)/2+(T22+T23) -> 198168.05 | V32: =(U21+V21)/2+(U22+U23) -> 165908.23 | W32: =(V21+W21)/2+(V22+V23) -> 160832.04 | X32: =(W21+X21)/2+(W22+W23) -> 150649.57 | Y32: =(X21+Y21)/2+(X22+X23) -> 124255.34 | Z32: =(Y21+Z21)/2+(Y22+Y23) -> 97405.539 | AA32: =(Z21+AA21)/2+(Z22+Z23) -> 102030.45 | AB32: =(AA21+AB21)/2+(AA22+AA23) -> 101410.58 | ... BC32: =(BB21+BC21)/2+(BB22+BB23) -> 41766.425
A33: Produksjonsavgift | I33: =(1/12)*(H24)+(11/12)*(I24) -> 0 | J33: =(1/12)*(I24)+(11/12)*(J24) -> 0 | K33: =(1/12)*(J24)+(11/12)*(K24) -> 0 | L33: =(1/12)*(K24)+(11/12)*(L24) -> 0 | M33: =(1/12)*(L24)+(11/12)*(M24) -> 0 | N33: 0 | O33: =(1/12)*(N24)+(11/12)*(O24) -> 0 | P33: =(1/12)*(O24)+(11/12)*(P24) -> 0 | Q33: =(1/12)*(P24)+(11/12)*(Q24) -> 0 | R33: =(1/12)*(Q24)+(11/12)*(R24) -> 0 | S33: =(1/12)*(R24)+(11/12)*(S24) -> 0 | T33: =(1/12)*(S24)+(11/12)*(T24) -> 0 | U33: =(1/12)*(T24)+(11/12)*(U24) -> 0 | V33: =(1/12)*(U24)+(11/12)*(V24) -> 0 | ... BC33: =(1/12)*(BB24)+(11/12)*(BC24) -> 0
A34: Arealavgift | I34: 1535.8388 | J34: 1550.9334 | K34: 1403.3694 | L34: 939.15558 | M34: 1779.7733 | N34: 1504.9512 | O34: 1417.6332 | P34: 939.59585 | Q34: 1049.9071 | R34: 1319.4878 | S34: 1179.8897 | T34: =T25 -> 1472.5541 | U34: =U25 -> 1624.6262 | V34: =V25 -> 1696.2214 | W34: =W25 -> 1879.5041 | X34: =X25 -> 1905.7279 | Y34: =Y25 -> 1750.0413 | Z34: =Z25 -> 1785.0421 | AA34: =AA25 -> 1820.7429 | ... BC34: =BC25 -> 3169.9575
A35: CO2-avgift | I35: 4516.1052 | J35: 4959.4259 | K35: 5107.5202 | L35: 5181.9697 | M35: 5192.6893 | N35: 5370.9069 | O35: 5601.6462 | P35: 5197.2109 | Q35: 6258.3328 | R35: 7495.8174 | S35: 7694.7028 | T35: =(S26+T26)/2 -> 8396.9581 | U35: =(T26+U26)/2 -> 9425.2952 | V35: =(U26+V26)/2 -> 9528.7799 | W35: =(V26+W26)/2 -> 8959.6658 | X35: =(W26+X26)/2 -> 8213.8072 | Y35: =(X26+Y26)/2 -> 9561.1578 | Z35: =(Y26+Z26)/2 -> 10873.094 | AA35: =(Z26+AA26)/2 -> 10137.004 | ... BC35: =(BB26+BC26)/2 -> 3148.1796
A36: Nox-avgift | I36: 61.899116 | J36: -25.682537 | K36: 2.199846 | L36: 6.554682 | M36: 1.030437 | N36: 1.715724 | O36: 0.952288 | P36: 0.728023 | Q36: 1.447237 | R36: 3.649008 | S36: -2.624272 | T36: 1 | U36: 1 | V36: =0.25*U27+0.75*V27 -> 0 | W36: =0.25*V27+0.75*W27 -> 0 | X36: =0.25*W27+0.75*X27 -> 0 | Y36: =0.25*X27+0.75*Y27 -> 0 | Z36: =0.25*Y27+0.75*Z27 -> 0 | AA36: =0.25*Z27+0.75*AA27 -> 0 | AB36: =0.25*AA27+0.75*AB27 -> 0 | AC36: =0.25*AB27+0.75*AC27 -> 0 | ... BC36: =0.25*BB27+0.75*BC27 -> 0
A37: Sum skatter | I37: =I31+I32 -> 170049 | J37: =J31+J32 -> 103672.48 | K37: =K31+K32 -> 41092.758 | L37: =L31+L32 -> 65049.095 | M37: =M31+M32 -> 110313.5 | N37: =N31+N32 -> 133501.47 | O37: =O31+O32 -> 28387.643 | P37: =P31+P32 -> 85711.246 | ... BC37: =BC31+BC32 -> 54120.275
A38: Sum avgifter | I38: =I33+I34+I35+I36 -> 6113.8431 | J38: =J33+J34+J35+J36 -> 6484.6767 | K38: =K33+K34+K35+K36 -> 6513.0895 | L38: =L33+L34+L35+L36 -> 6127.6799 | M38: =M33+M34+M35+M36 -> 6973.4931 | N38: =N33+N34+N35+N36 -> 6877.5739 | O38: =O33+O34+O35+O36 -> 7020.2317 | P38: =P33+P34+P35+P36 -> 6137.5348 | ... BC38: =BC33+BC34+BC35+BC36 -> 6318.1372
A39: Sum skatter og avgifter | I39: =I37+I38 -> 176162.84 | J39: =J37+J38 -> 110157.15 | K39: =K37+K38 -> 47605.847 | L39: =L37+L38 -> 71176.775 | M39: =M37+M38 -> 117286.99 | N39: =N37+N38 -> 140379.04 | O39: =O37+O38 -> 35407.874 | P39: =P37+P38 -> 91848.781 | ... BC39: =BC37+BC38 -> 60438.412
A42: Provenyvirkning
A43: Særskatt (Påløpt) | I43: 0 | J43: 0 | K43: 0 | L43: 0 | M43: 0 | N43: 0 | O43: 0 | P43: 0 | Q43: 0 | R43: 0 | S43: 0 | T43: 0 | U43: 0 | V43: 0 | W43: 0
A44: Særskatt (Betalt) | I44: 0 | J44: 0 | K44: 0 | L44: 0 | M44: 0 | N44: 0 | O44: 0 | P44: 0 | Q44: 0 | R44: 0 | S44: 0 | T44: 0 | U44: 0 | V44: 0 | W44: 0
A51: Oppsummering av inntektsanslag fra petroleumssektoren
A53: Påløpte skatter og avgifter, avrundet, mill. kr.
A54: Income tax | I54: =I20+I22 -> 56333 | J54: =J20+J22 -> 33491 | K54: =K20+K22 -> 19519 | L54: =L20+L22 -> 32269.439 | M54: =M20+M22 -> 50118 | N54: =N20+N22 -> 35526.948 | O54: =O20+O22 -> 18220.055 | P54: =P20+P22 -> 97754.066 | ... S54: =S20+S22 -> 120238.8 | T54: =ROUND((T20)/100,T$66)*100 -> 107400 | U54: =ROUND((U20)/100,U$66)*100 -> 79100 | V54: =ROUND((V20)/100,V$66)*100 -> 61700 | W54: =ROUND((W20)/100,W$66)*100 -> 53700 | X54: =ROUND((X20)/100,X$66)*100 -> 48200 | Y54: =ROUND((Y20)/100,Y$66)*100 -> 34000 | Z54: =ROUND((Z20)/100,Z$66)*100 -> 34100 | AA54: =ROUND((AA20)/100,AA$66)*100 -> 34900 | ... BC54: =ROUND((BC20)/100,BC$66)*100 -> 11800
A55: Special petroleum tax (adjusted for repayments) | I55: =I21+I23 -> 91513 | J55: =J21+J23 -> 50381 | K55: =K21+K23 -> 30189 | L55: =L21+L23 -> 58673.482 | M55: =M21+M23 -> 101113 | N55: =N21+N23 -> 81231.442 | O55: =O21+O23 -> -30264.474 | P55: =P21+P23 -> 192479.94 | ... S55: =S21+S23 -> 260874.97 | T55: =ROUND((T21+T22+T23+T43)/100,T$66)*100 -> 219500 | U55: =ROUND((U21+U22+U23+U43)/100,U$66)*100 -> 176600 | V55: =ROUND((V21+V22+V23+V43)/100,V$66)*100 -> 160800 | W55: =ROUND((W21+W22+W23+W43)/100,W$66)*100 -> 156800 | X55: =ROUND((X21+X22+X23)/100,X$66)*100 -> 142900 | Y55: =ROUND((Y21+Y22+Y23)/100,Y$66)*100 -> 99400 | Z55: =ROUND((Z21+Z22+Z23)/100,Z$66)*100 -> 104100 | AA55: =ROUND((AA21+AA22+AA23)/100,AA$66)*100 -> 104000 | AB55: =ROUND((AB21+AB22+AB23)/100,AB$66)*100 -> 99400 | AC55: =ROUND((AC21+AC22+AC23)/100,AC$66)*100 -> 107400 | AD55: =ROUND((AD21+AD22+AD23)/100,AD$66)*100 -> 113600 | AE55: =ROUND((AE21+AE22+AE23)/100,AE$66)*100 -> 115500 | ... BC55: =ROUND((BC21+BC22+BC23)/100,BC$66)*100 -> 39900
A56: Produksjonsavgift | I56: =I24 -> 0 | J56: =J24 -> 0 | K56: =K24 -> 0 | L56: =L24 -> 0 | M56: =M24 -> 0 | N56: =N24 -> 0 | O56: =O24 -> 0 | P56: =P24 -> 0 | ... S56: =S24 -> 0 | T56: =ROUND(T24/100,T$66)*100 -> 0 | U56: =ROUND(U24/100,U$66)*100 -> 0 | V56: =ROUND(V24/100,V$66)*100 -> 0 | W56: =ROUND(W24/100,W$66)*100 -> 0 | X56: =ROUND(X24/100,X$66)*100 -> 0 | Y56: =ROUND(Y24/100,Y$66)*100 -> 0 | Z56: =ROUND(Z24/100,Z$66)*100 -> 0 | AA56: =ROUND(AA24/100,AA$66)*100 -> 0 | ... BC56: =ROUND(BC24/100,BC$66)*100 -> 0
A57: Arealavgift | I57: =I25 -> 1766 | J57: =J25 -> 1636 | K57: =K25 -> 1500 | L57: =L25 -> 1359.4042 | M57: =M25 -> 1379.829 | N57: =N25 -> 1488.3013 | O57: =O25 -> 1508.6929 | P57: =P25 -> 1372.141 | ... S57: =S25 -> 1382.3287 | T57: =ROUND(T25/100,T$66)*100 -> 1500 | U57: =ROUND(U25/100,U$66)*100 -> 1600 | V57: =ROUND(V25/100,V$66)*100 -> 1700 | W57: =ROUND(W25/100,W$66)*100 -> 1900 | X57: =ROUND(X25/100,X$66)*100 -> 1900 | Y57: =ROUND(Y25/100,Y$66)*100 -> 1800 | Z57: =ROUND(Z25/100,Z$66)*100 -> 1800 | AA57: =ROUND(AA25/100,AA$66)*100 -> 1800 | ... BC57: =ROUND(BC25/100,BC$66)*100 -> 3200
A58: CO2-avgift | I58: =I26 -> 4894 | J58: =J26 -> 5078 | K58: =K26 -> 5365 | L58: =L26 -> 5331.1906 | M58: =M26 -> 5650.0241 | N58: =N26 -> 5790.1281 | O58: =O26 -> 6031.9859 | P58: =P26 -> 5357.6102 | ... S58: =S26 -> 7540.5543 | T58: =ROUND(T26/100,T$66)*100 -> 9300 | U58: =ROUND(U26/100,U$66)*100 -> 9600 | V58: =ROUND(V26/100,V$66)*100 -> 9500 | W58: =ROUND(W26/100,W$66)*100 -> 8500 | X58: =ROUND(X26/100,X$66)*100 -> 8000 | Y58: =ROUND(Y26/100,Y$66)*100 -> 11200 | Z58: =ROUND(Z26/100,Z$66)*100 -> 10600 | AA58: =ROUND(AA26/100,AA$66)*100 -> 9700 | ... BC58: =ROUND(BC26/100,BC$66)*100 -> 3100
A59: Nox-avgift | I59: =I27 -> 0 | J59: =J27 -> 0 | K59: =K27 -> 0 | L59: =L27 -> 0 | M59: =M27 -> 0 | N59: =N27 -> 0 | O59: =O27 -> 0 | P59: =P27 -> 0 | ... S59: =S27 -> 0 | T59: =ROUND(T27/100,T$66)*100 -> 0 | U59: =ROUND(U27/100,U$66)*100 -> 0 | V59: =ROUND(V27/100,V$66)*100 -> 0 | W59: =ROUND(W27/100,W$66)*100 -> 0 | X59: =ROUND(X27/100,X$66)*100 -> 0 | Y59: =ROUND(Y27/100,Y$66)*100 -> 0 | Z59: =ROUND(Z27/100,Z$66)*100 -> 0 | AA59: =ROUND(AA27/100,AA$66)*100 -> 0 | ... BC59: =ROUND(BC27/100,BC$66)*100 -> 0
A60: Sum skatter | I60: =I54+I55 -> 147846 | J60: =J54+J55 -> 83872 | K60: =K54+K55 -> 49708 | L60: =L54+L55 -> 90942.921 | M60: =M54+M55 -> 151231 | N60: =N54+N55 -> 116758.39 | O60: =O54+O55 -> -12044.419 | P60: =P54+P55 -> 290234 | ... BC60: =BC54+BC55 -> 51700
A61: Sum avgifter | I61: =SUM(I56:I59) -> 6660 | J61: =SUM(J56:J59) -> 6714 | K61: =SUM(K56:K59) -> 6865 | L61: =SUM(L56:L59) -> 6690.5948 | M61: =SUM(M56:M59) -> 7029.8531 | N61: =SUM(N56:N59) -> 7278.4294 | O61: =SUM(O56:O59) -> 7540.6787 | P61: =SUM(P56:P59) -> 6729.7512 | ... BC61: =SUM(BC56:BC59) -> 6300
A62: Sum skatter og avgifter | I62: =I60+I61 -> 154506 | J62: =J60+J61 -> 90586 | K62: =K60+K61 -> 56573 | L62: =L60+L61 -> 97633.516 | M62: =M60+M61 -> 158260.85 | N62: =N60+N61 -> 124036.82 | O62: =O60+O61 -> -4503.7405 | P62: =P60+P61 -> 296963.75 | ... BC62: =BC60+BC61 -> 58000 | BD62: =Formue!BK69 -> 56697.114 | BE62: =Formue!BL69 -> 55328.546 | BF62: =Formue!BM69 -> 53892.676 | BG62: =Formue!BN69 -> 52387.867 | BH62: =Formue!BO69 -> 50812.469 | BI62: =Formue!BP69 -> 49164.815 | BJ62: =Formue!BQ69 -> 47443.23 | BK62: =Formue!BR69 -> 45646.025 | ... CG62: =Formue!CN69 -> -16449.891
A65: Betalte skatter og avgifter, avrundet, mill. kr.
A66: Avrundingsfaktor | I66: 0 | J66: 0 | K66: 0 | L66: 0 | M66: 0 | N66: 0 | O66: 0 | P66: 0 | Q66: 0 | R66: 0 | S66: 0 | T66: 0 | U66: 0 | V66: 0 | W66: 0 | X66: 0 | Y66: 0 | Z66: 0 | AA66: 0 | AB66: 0 | AC66: 0 | AD66: 0 | AE66: 0 | AF66: 0 | AG66: 0 | AH66: 0 | AI66: 0 | AJ66: 0 | AK66: 0 | AL66: 0 | AM66: 0 | AN66: 0 | AO66: 0 | AP66: 0 | AQ66: 0 | AR66: 0 | AS66: 0
A67: Income tax | I67: =I31 -> 64212 | J67: =J31 -> 39476.659 | K67: =K31 -> 16034.226 | L67: =L31 -> 23688.095 | M67: =M31 -> 38539.517 | N67: =N31 -> 43011.141 | O67: =O31 -> 16724.759 | P67: =P31 -> 51982.827 | ... S67: =S31 -> 132693.48 | T67: =ROUND(T31/100,T$66)*100 -> 121100 | U67: =ROUND(U31/100,U$66)*100 -> 93300 | V67: =ROUND(V31/100,V$66)*100 -> 70400 | W67: =ROUND(W31/100,W$66)*100 -> 57700 | X67: =ROUND(X31/100,X$66)*100 -> 50900 | Y67: =ROUND(Y31/100,Y$66)*100 -> 41100 | Z67: =ROUND(Z31/100,Z$66)*100 -> 34000 | AA67: =ROUND(AA31/100,AA$66)*100 -> 34500 | ... BC67: =ROUND(BC31/100,BC$66)*100 -> 12400
A68: Special petroleum tax (adjusted for repayments) | I68: =I32 -> 105837 | J68: =J32 -> 64195.817 | K68: =K32 -> 25058.532 | L68: =L32 -> 41361 | M68: =M32 -> 71773.979 | N68: =N32 -> 90490.326 | O68: =O32 -> 11662.884 | P68: =P32 -> 33728.419 | ... S68: =S32 -> 278773.96 | T68: =(ROUND(T32/100,T$66)*100)+T44 -> 252800 | U68: =(ROUND(U32/100,U$66)*100)+U44 -> 198200 | V68: =(ROUND(V32/100,V$66)*100)+V44 -> 165900 | W68: =(ROUND(W32/100,W$66)*100)+W44 -> 160800 | X68: =ROUND(X32/100,X$66)*100 -> 150600 | Y68: =ROUND(Y32/100,Y$66)*100 -> 124300 | Z68: =ROUND(Z32/100,Z$66)*100 -> 97400 | AA68: =ROUND(AA32/100,AA$66)*100 -> 102000 | AB68: =ROUND(AB32/100,AB$66)*100 -> 101400 | AC68: =ROUND(AC32/100,AC$66)*100 -> 103000 | AD68: =ROUND(AD32/100,AD$66)*100 -> 110900 | AE68: =ROUND(AE32/100,AE$66)*100 -> 114900 | ... BC68: =ROUND(BC32/100,BC$66)*100 -> 41800
A69: Produksjonsavgift | I69: =I33 -> 0 | J69: =J33 -> 0 | K69: =K33 -> 0 | L69: =L33 -> 0 | M69: =M33 -> 0 | N69: =N33 -> 0 | O69: =O33 -> 0 | P69: =P33 -> 0 | ... S69: =S33 -> 0 | T69: =ROUND(T33/100,T$66)*100 -> 0 | U69: =ROUND(U33/100,U$66)*100 -> 0 | V69: =ROUND(V33/100,V$66)*100 -> 0 | W69: =ROUND(W33/100,W$66)*100 -> 0 | X69: =ROUND(X33/100,X$66)*100 -> 0 | Y69: =ROUND(Y33/100,Y$66)*100 -> 0 | Z69: =ROUND(Z33/100,Z$66)*100 -> 0 | AA69: =ROUND(AA33/100,AA$66)*100 -> 0 | ... BC69: =ROUND(BC33/100,BC$66)*100 -> 0
A70: Arealavgift | I70: =I34 -> 1535.8388 | J70: =J34 -> 1550.9334 | K70: =K34 -> 1403.3694 | L70: =L34 -> 939.15558 | M70: =M34 -> 1779.7733 | N70: =N34 -> 1504.9512 | O70: =O34 -> 1417.6332 | P70: =P34 -> 939.59585 | ... S70: =S34 -> 1179.8897 | T70: =ROUND(T34/100,T$66)*100 -> 1500 | U70: =ROUND(U34/100,U$66)*100 -> 1600 | V70: =ROUND(V34/100,V$66)*100 -> 1700 | W70: =ROUND(W34/100,W$66)*100 -> 1900 | X70: =ROUND(X34/100,X$66)*100 -> 1900 | Y70: =ROUND(Y34/100,Y$66)*100 -> 1800 | Z70: =ROUND(Z34/100,Z$66)*100 -> 1800 | AA70: =ROUND(AA34/100,AA$66)*100 -> 1800 | ... BC70: =ROUND(BC34/100,BC$66)*100 -> 3200
A71: CO2-avgift | I71: =I35 -> 4516.1052 | J71: =J35 -> 4959.4259 | K71: =K35 -> 5107.5202 | L71: =L35 -> 5181.9697 | M71: =M35 -> 5192.6893 | N71: =N35 -> 5370.9069 | O71: =O35 -> 5601.6462 | P71: =P35 -> 5197.2109 | ... S71: =S35 -> 7694.7028 | T71: =ROUND(T35/100,T$66)*100 -> 8400 | U71: =ROUND(U35/100,U$66)*100 -> 9400 | V71: =ROUND(V35/100,V$66)*100 -> 9500 | W71: =ROUND(W35/100,W$66)*100 -> 9000 | X71: =ROUND(X35/100,X$66)*100 -> 8200 | Y71: =ROUND(Y35/100,Y$66)*100 -> 9600 | Z71: =ROUND(Z35/100,Z$66)*100 -> 10900 | AA71: =ROUND(AA35/100,AA$66)*100 -> 10100 | ... BC71: =ROUND(BC35/100,BC$66)*100 -> 3100
A72: Nox-avgift | I72: =I36 -> 61.899116 | J72: =J36 -> -25.682537 | K72: =K36 -> 2.199846 | L72: =L36 -> 6.554682 | M72: =M36 -> 1.030437 | N72: =N36 -> 1.715724 | O72: =O36 -> 0.952288 | P72: =P36 -> 0.728023 | ... BC72: =BC36 -> 0
A73: Sum skatter | I73: =SUM(I67:I68) -> 170049 | J73: =SUM(J67:J68) -> 103672.48 | K73: =SUM(K67:K68) -> 41092.758 | L73: =SUM(L67:L68) -> 65049.095 | M73: =SUM(M67:M68) -> 110313.5 | N73: =SUM(N67:N68) -> 133501.47 | O73: =SUM(O67:O68) -> 28387.643 | P73: =SUM(P67:P68) -> 85711.246 | ... BC73: =SUM(BC67:BC68) -> 54200
A74: Sum avgifter | I74: =SUM(I69:I72) -> 6113.8431 | J74: =SUM(J69:J72) -> 6484.6767 | K74: =SUM(K69:K72) -> 6513.0895 | L74: =SUM(L69:L72) -> 6127.6799 | M74: =SUM(M69:M72) -> 6973.4931 | N74: =SUM(N69:N72) -> 6877.5739 | O74: =SUM(O69:O72) -> 7020.2317 | P74: =SUM(P69:P72) -> 6137.5348 | ... BC74: =SUM(BC69:BC72) -> 6300
A75: Sum skatter og avgifter | I75: =I73+I74 -> 176162.84 | J75: =J73+J74 -> 110157.15 | K75: =K73+K74 -> 47605.847 | L75: =L73+L74 -> 71176.775 | M75: =M73+M74 -> 117286.99 | N75: =N73+N74 -> 140379.04 | O75: =O73+O74 -> 35407.874 | P75: =P73+P74 -> 91848.781 | ... BC75: =BC73+BC74 -> 60500 | BD75: =Formue!BK70 -> 59140.955 | BE75: =Formue!BL70 -> 57713.397 | BF75: =Formue!BM70 -> 56215.636 | BG75: =Formue!BN70 -> 54645.965 | BH75: =Formue!BO70 -> 53002.661 | BI75: =Formue!BP70 -> 51283.988 | BJ75: =Formue!BQ70 -> 49488.196 | BK75: =Formue!BR70 -> 47613.526 | ... CG75: =Formue!CN70 -> -17158.938
A78: Netto innbetalinger SDØE, mill. kr
A79: Innbetalinger | I79: =Petoro!T50 -> 185514 | J79: =Petoro!U50 -> 158512.8 | K79: =Petoro!V50 -> 127908.6 | L79: =Petoro!W50 -> 145043.04 | M79: =Petoro!X50 -> 175454.21 | N79: =Petoro!Y50 -> 155059.3 | O79: =Petoro!Z50 -> 113793.97 | P79: =Petoro!AA50 -> 249674.3 | ... BC79: =Petoro!BN50 -> 60253.732
A80: Utbetalinger | I80: =Petoro!T51 -> 72655.085 | J80: =Petoro!U51 -> 65796.32 | K80: =Petoro!V51 -> 61453.295 | L80: =Petoro!W51 -> 56771.007 | M80: =Petoro!X51 -> 56766.515 | N80: =Petoro!Y51 -> 58571.661 | O80: =Petoro!Z51 -> 57407.276 | P80: =Petoro!AA51 -> 64504.232 | ... BC80: =Petoro!BN51 -> 49302.824
A81: Netto inntekt SDØE | I81: =Petoro!T52 -> 112858.92 | J81: =Petoro!U52 -> 92716.478 | K81: =Petoro!V52 -> 66455.308 | L81: =Petoro!W52 -> 88272.034 | M81: =Petoro!X52 -> 118687.69 | N81: =Petoro!Y52 -> 96487.643 | O81: =Petoro!Z52 -> 56386.696 | P81: =Petoro!AA52 -> 185170.07 | ... BC81: =Petoro!BN52 -> 10950.908 | BD81: =Formue!BK71 -> 10704.912 | BE81: =Formue!BL71 -> 10446.514 | BF81: =Formue!BM71 -> 10175.41 | BG81: =Formue!BN71 -> 9891.2885 | BH81: =Formue!BO71 -> 9593.8394 | BI81: =Formue!BP71 -> 9282.748 | BJ81: =Formue!BQ71 -> 8957.6976 | BK81: =Formue!BR71 -> 8618.3696 | ... CG81: =Formue!CN71 -> -3105.8836
A84: Aksjeutbytte Statoil, mill. kr.
A85: Dividend - Old technical method | B85: 14005.699 | C85: 16940.158 | D85: 15489 | E85: 12818 | F85: 13352.46 | G85: 13886.558 | H85: 14420.657 | I85: 22646 | J85: 15382 | K85: 10717.498 | L85: 8397.82 | M85: 14984.124 | N85: 20056.967 | O85: 15029.919 | P85: 10493.748 | Q85: 35258.259 | R85: 76600 | S85: =R85*(KVARTS!AB5/KVARTS!AA5) -> 69834.069 | T85: =S85*(KVARTS!AC5/KVARTS!AB5) -> 68948.055 | U85: =T85*(KVARTS!AD5/KVARTS!AC5) -> 58316.975 | V85: =U85*(KVARTS!AE5/KVARTS!AD5) -> 54328.43 | W85: =V85*(KVARTS!AF5/KVARTS!AE5) -> 54285.663 | X85: =W85*(KVARTS!AG5/KVARTS!AF5) -> 54590.464 | Y85: =X85*(KVARTS!AH5/KVARTS!AG5) -> 54840.956 | Z85: =Y85*(KVARTS!AI5/KVARTS!AH5) -> 54876.935 | ... BC85: =BB85*(KVARTS!BL5/KVARTS!BK5) -> 110605.9
A86: Dividend - New technical method | B86: 14005.699 | C86: 16940.158 | D86: 15489 | E86: 12818 | F86: 13352.46 | G86: 13886.558 | H86: 14420.657 | I86: 22646 | J86: 15382 | K86: 10717.498 | L86: 8397.82 | M86: 14984.124 | N86: 20056.967 | O86: 15029.919 | P86: 10493.748 | Q86: 35258.259 | R86: 78309 | S86: 62578 | T86: 37768.1 | U86: 25804.6 | V86: =KVARTS!AF5/0.049 -> 13754.374 | W86: =KVARTS!AG5/0.049 -> 13831.601 | X86: =KVARTS!AH5/0.049 -> 13895.068 | Y86: =KVARTS!AI5/0.049 -> 13904.184 | Z86: =KVARTS!AJ5/0.049 -> 14565.091 | AA86: =KVARTS!AK5/0.049 -> 15246.873 | AB86: =KVARTS!AL5/0.049 -> 15950.099 | AC86: =KVARTS!AM5/0.049 -> 16675.356 | ... BC86: =KVARTS!BM5/0.049 -> 28584.732 | BD86: =Formue!BK72 -> 27942.617 | BE86: =Formue!BL72 -> 27268.132 | BF86: =Formue!BM72 -> 26560.477 | BG86: =Formue!BN72 -> 25818.847 | BH86: =Formue!BO72 -> 25042.427 | BI86: =Formue!BP72 -> 24230.397 | BJ86: =Formue!BQ72 -> 23381.931 | BK86: =Formue!BR72 -> 22496.196 | ... CG86: =Formue!CN72 -> -8107.1675
A89: Kontroll:
A90: Årlig endring i aksjeutbytte | F90: =(F86/E86-1)*100 -> 4.1696052 | G90: =(G86/F86-1)*100 -> 3.999998 | H90: =(H86/G86-1)*100 -> 3.8461538 | I90: =(I86/H86-1)*100 -> 57.03862 | J90: =(J86/I86-1)*100 -> -32.076305 | K90: =(K86/J86-1)*100 -> -30.324418 | L90: =(L86/K86-1)*100 -> -21.643839 | M90: =(M86/L86-1)*100 -> 78.428735 | ... BC90: =(BC86/BB86-1)*100 -> 2
A91: Årlig endring i nominell oljepris | F91: =(KVARTS!P5/KVARTS!O5-1)*100 -> 28.247423 | G91: =(KVARTS!Q5/KVARTS!P5-1)*100 -> 4.5016077 | H91: =(KVARTS!R5/KVARTS!Q5-1)*100 -> -1.6923077 | I91: =(KVARTS!S5/KVARTS!R5-1)*100 -> -1.8779343 | J91: =(KVARTS!T5/KVARTS!S5-1)*100 -> -31.259968 | K91: =(KVARTS!U5/KVARTS!T5-1)*100 -> -12.064965 | L91: =(KVARTS!V5/KVARTS!U5-1)*100 -> 19.261214 | M91: =(KVARTS!W5/KVARTS!V5-1)*100 -> 28.982301 | ... BC91: =(KVARTS!BM5/KVARTS!BL5-1)*100 -> 2
A92: Dividend/ SNKS previous year | C92: =C86/B99 -> 0.05354212 | D92: =D86/C99 -> 0.037245159 | E92: =E86/D99 -> 0.045812293 | F92: =F86/E99 -> 0.048385954 | G92: =G86/F99 -> 0.039585005 | H92: =H86/G99 -> 0.036463426 | I92: =I86/H99 -> 0.0656118 | J92: =J86/I99 -> 0.049354155 | ... CG92: =CG86/CF99 -> 0.3740618
A95: Netto andre inntekter, mill. kr.
A96: Netto andre inntekter, mill. kr. | B96: =Petoro!M79 -> -4.58 | C96: =Petoro!N79 -> 0 | D96: =Petoro!O79 -> 0 | E96: =Petoro!P79 -> -81.5 | F96: =Petoro!Q79 -> -2 | G96: =Petoro!R79 -> -0.027193 | H96: =Petoro!S79 -> -1 | I96: =Petoro!T79 -> -2 | ... CG96: =Petoro!CR79 -> 0
A99: Statens netto kontantstrøm, mill. kr | B99: 316389.37 | C99: 415866.13 | D99: 279793.9 | E99: 275957.36 | F99: 350803.5 | G99: 395482.76 | H99: 345151.33 | I99: =I75+I81+I86+I96 -> 311665.76 | J99: =J75+J81+J86+J96 -> 218255.63 | K99: =K75+K81+K86+K96 -> 124778.65 | L99: =L75+L81+L86+L96 -> 167846.63 | M99: =M75+M81+M86+M96 -> 250958.8 | N99: =N75+N81+N86+N96 -> 256923.65 | O99: =O75+O81+O86+O96 -> 106824.49 | P99: =P75+P81+P86+P96 -> 287512.6 | ... BC99: =BC75+BC81+BC86+BC96 -> 100035.64 | BD99: =Formue!BK74 -> 97788.484 | BE99: =Formue!BL74 -> 95428.043 | BF99: =Formue!BM74 -> 92951.523 | BG99: =Formue!BN74 -> 90356.101 | BH99: =Formue!BO74 -> 87638.928 | BI99: =Formue!BP74 -> 84797.133 | BJ99: =Formue!BQ74 -> 81827.825 | BK99: =Formue!BR74 -> 78728.092 | ... CG99: =Formue!CN74 -> -28371.989
A103: Comparison with previous utsending
A104: NB26b | I104: 311665.76 | J104: 218255.63 | K104: 124778.65 | L104: 167846.63 | M104: 250958.8 | N104: 256923.65 | O104: 106824.49 | P104: 287512.6 | Q104: 1285223 | R104: 978064.87 | S104: 702159.39 | T104: 661601 | U104: 526908.2 | V104: 407654.37 | W104: 380031.6 | X104: 340095.07 | Y104: 279907.86 | Z104: 241434.71 | AA104: 240877.07 | AB104: 240207.64 | AC104: 243004.96 | AD104: 253485.96 | AE104: 254640.19 | AF104: 249473.3 | AG104: 229935.57 | AH104: 209224.22 | AI104: 195906.54 | AJ104: 183556.19 | AK104: 178137.26 | AL104: 164620.78 | AM104: 161561.28 | AN104: 152065.09 | AO104: 147006.5 | AP104: 140314.6 | AQ104: 137796.21 | AR104: 133349.56 | AS104: 126817.75 | AT104: 129073.79 | AU104: 126418.4 | AV104: 118683.2 | AW104: 111774.16 | AX104: 107715.43 | AY104: 109415.49 | AZ104: 110259.82 | BA104: 107836.66 | BB104: 102763.83 | BC104: 100035.64 | BD104: 97788.484 | BE104: 95428.043 | BF104: 92951.523 | BG104: 90356.101 | BH104: 87638.928 | BI104: 84797.133 | BJ104: 81827.825 | BK104: 78728.092 | BL104: 75495.006 | BM104: 72125.629 | BN104: 68617.007 | BO104: 64966.182 | BP104: 61170.192 | BQ104: 57226.074 | BR104: 53130.867 | BS104: 48881.622 | BT104: 44475.397 | BU104: 39909.271 | BV104: 35180.342 | BW104: 30285.739 | BX104: 25222.622 | BY104: 19988.189 | BZ104: 14579.688 | CA104: 8994.4178 | CB104: 3229.7367 | CC104: -2716.9271 | CD104: -8848.0696 | CE104: -15166.101 | CF104: -21673.337 | CG104: -28371.989
A105: Difference | I105: =I99-I104 -> 0 | J105: =J99-J104 -> 0 | K105: =K99-K104 -> 0 | L105: =L99-L104 -> 0 | M105: =M99-M104 -> 0 | N105: =N99-N104 -> 0 | O105: =O99-O104 -> 0 | P105: =P99-P104 -> 0 | ... CG105: =CG99-CG104 -> 0
A107: Comparison with previous budget round
A108: RNB25e | I108: 311665.76 | J108: 218255.63 | K108: 124778.65 | L108: 167846.63 | M108: 250958.8 | N108: 256923.65 | O108: 106824.49 | P108: 287512.6 | Q108: 1285223 | R108: 978064.87 | S108: 702159.39 | T108: 697701 | U108: 594407.2 | V108: 474104.72 | W108: 433036.29 | X108: 387988.54 | Y108: 320712.38 | Z108: 271695.03 | AA108: 267711.73 | AB108: 268489.78 | AC108: 273230.88 | AD108: 283299.43 | AE108: 284811.85 | AF108: 278630.97 | AG108: 258946.47 | AH108: 238012.26 | AI108: 224024.54 | AJ108: 210303.42 | AK108: 204233.94 | AL108: 190315.16 | AM108: 186573.28 | AN108: 176806.06 | AO108: 171177.01 | AP108: 163585.74 | AQ108: 160329.08 | AR108: 156267.32 | AS108: 149063.21 | AT108: 149897.22 | AU108: 147174.1 | AV108: 139138.09 | AW108: 132339.57 | AX108: 128182.63 | AY108: 129929.59 | AZ108: 130040.17 | BA108: 127430.51 | BB108: 121777.62 | BC108: 118961.21 | BD108: 117055.68 | BE108: 115045.08 | BF108: 112926.87 | BG108: 110698.51 | BH108: 108357.43 | BI108: 105901.06 | BJ108: 103326.81 | BK108: 100632.08 | BL108: 97814.279 | BM108: 94870.807 | BN108: 91799.068 | BO108: 88596.468 | BP108: 85260.428 | BQ108: 81788.378 | BR108: 78177.771 | BS108: 74426.079 | BT108: 70530.805 | BU108: 66489.485 | BV108: 62299.692 | BW108: 57959.048 | BX108: 53465.225 | BY108: 48815.952 | BZ108: 44009.028 | CA108: 39042.321 | CB108: 33913.785 | CC108: 28621.463 | CD108: 23163.496 | CE108: 17538.137 | CF108: 11743.758 | CG108: 5778.8604
A109: Difference | I109: =I99-I108 -> 0 | J109: =J99-J108 -> 0 | K109: =K99-K108 -> 0 | L109: =L99-L108 -> 0 | M109: =M99-M108 -> 0 | N109: =N99-N108 -> 0 | O109: =O99-O108 -> 0 | P109: =P99-P108 -> 0 | ... CG109: =CG99-CG108 -> -34150.849
A115: Shares | I115: skatt og avgift | K115: =K75/K99 -> 0.38152237 | L115: =L75/L99 -> 0.42405841 | M115: =M75/M99 -> 0.46735555 | N115: =N75/N99 -> 0.54638427 | O115: =O75/O99 -> 0.3314584 | P115: =P75/P99 -> 0.31946002 | Q115: =Q75/Q99 -> 0.5609384 | R115: =R75/R99 -> 0.63722299 | ... T115: =T75/T99 -> 0.57834842
I116: netto sdøe | K116: =K81/K99 -> 0.53258555 | L116: =L81/L99 -> 0.52590889 | M116: =M81/M99 -> 0.47293695 | N116: =N81/N99 -> 0.37554987 | O116: =O81/O99 -> 0.52784428 | P116: =P81/P99 -> 0.64404158 | Q116: =Q81/Q99 -> 0.41162802 | R116: =R81/R99 -> 0.28271177 | ... T116: =T81/T99 -> 0.36473896
I117: utbytte | K117: =K86/K99 -> 0.085892079 | L117: =L86/L99 -> 0.0500327 | M117: =M86/M99 -> 0.059707505 | N117: =N86/N99 -> 0.078065865 | O117: =O86/O99 -> 0.14069732 | P117: =P86/P99 -> 0.036498395 | Q117: =Q86/Q99 -> 0.027433572 | R117: =R86/R99 -> 0.080065241 | ... T117: =T86/T99 -> 0.056912621
A120: Average 2026-2050
A121: Taxes | I121: =AVERAGE(U73:AS73) -> 137500
A122: Avgifter | I122: =AVERAGE(U74:AS74) -> 9620.04
A123: Net SDFI | I123: =AVERAGE(U81:AS81) -> 66640.969
A124: Dividend | I124: =AVERAGE(U86:AS86) -> 18735.387
A125: Sum | I125: =SUM(I121:I124) -> 232496.4
A127: Control: SNKS | I127: =AVERAGE(U99:AS99) -> 232496.4
A129: Control: Avvik | I129: =AVERAGE(U109:AS109) -> -32613.857

Sheet Petoro
A1: Data SDØE - rapportert fra Olje- og energidepartementet
A3: (Ikke avrundede tall)
A4: Kap. 2441 | B4: Teknologiutv. | C4: 1997 | D4: 1998 | E4: 1999 | F4: 2000 | G4: 2001 | H4: 2002 | I4: 2003 | J4: 2004 | K4: 2005 | L4: 2006 | M4: 2007 | N4: 2008 | O4: 2009 | P4: 2010 | Q4: 2011 | R4: 2012 | S4: 2013 | T4: 2014 | U4: 2015 | V4: 2016 | W4: 2017 | X4: 2018 | Y4: 2019 | Z4: 2020 | AA4: 2021 | AB4: 2022 | AC4: 2023 | AD4: 2024 | AE4: 2025 | AF4: 2026 | AG4: 2027 | AH4: 2028 | AI4: 2029 | AJ4: 2030 | AK4: 2031 | AL4: 2032 | AM4: 2033 | AN4: 2034 | AO4: 2035 | AP4: 2036 | AQ4: 2037 | AR4: 2038 | AS4: 2039 | AT4: 2040 | AU4: 2041 | AV4: 2042 | AW4: 2043 | AX4: 2044 | AY4: 2045 | AZ4: 2046 | BA4: 2047 | BB4: 2048 | BC4: 2049 | BD4: 2050 | BE4: 2051 | BF4: 2052 | BG4: 2053 | BH4: 2054 | BI4: 2055 | BJ4: 2056 | BK4: 2057 | BL4: 2058 | BM4: 2059 | BN4: 2060
A5: Post 50 | B5: Prosj. rettet tekn. utv. | C5: 0.258 | D5: 0 | E5: 0 | F5: 0
A6: Sum kap 2441 | C6: =C5 -> 0.258 | D6: =D5 -> 0 | E6: =E5 -> 0 | F6: =F5 -> 0 | G6: =G5 -> 0 | H6: =H5 -> 0 | I6: =I5 -> 0 | J6: =J5 -> 0 | ... BN6: =BN5 -> 0
A8: Kap. 2442 | B8: Disponering
A9: Post 21 | B9: Spes. dr. utg. | C9: 0.258 | D9: 1.766613 | E9: 3.493977 | F9: 3 | G9: 0 | H9: 0 | P9: 81.5 | Q9: 2 | R9: 0.027193 | S9: 0.62214487 | T9: 2 | U9: 0 | V9: 0 | W9: 0
A10: Post 70 | B10: Tilskudd | C10: 93.471 | D10: 69.887841 | E10: 15.374209 | F10: 0 | G10: 5.962 | H10: 47.715 | I10: 113.492 | J10: 125.261 | K10: 14.177 | L10: 0 | M10: 0 | N10: 0 | O10: 0 | P10: 0 | Q10: 0 | R10: 0 | S10: 0 | T10: 0 | U10: 0 | V10: 0 | W10: 0 | X10: 0 | Y10: 0 | Z10: 0 | AA10: 0 | AB10: 0 | AC10: 0 | AD10: 0 | AE10: 0 | AF10: 0 | AG10: 0 | AH10: 0 | AI10: 0 | AJ10: 0 | AK10: 0 | AL10: 0 | AM10: 0 | AN10: 0 | AO10: 0 | AP10: 0 | AQ10: 0 | AR10: 0 | AS10: 0 | AT10: 0 | AU10: 0 | AV10: 0 | AW10: 0 | AX10: 0 | AY10: 0 | AZ10: 0 | BA10: 0 | BB10: 0 | BC10: 0 | BD10: 0 | BE10: 0 | BF10: 0 | BG10: 0 | BH10: 0 | BI10: 0 | BJ10: 0 | BK10: 0 | BL10: 0 | BM10: 0 | BN10: 0
A11: Sum kap 2442 | C11: =C9+C10 -> 93.729 | D11: =D9+D10 -> 71.654454 | E11: =E9+E10 -> 18.868186 | F11: =F9+F10 -> 3 | G11: =G9+G10 -> 5.962 | H11: =H9+H10 -> 47.715 | I11: =I9+I10 -> 113.492 | J11: =J9+J10 -> 125.261 | ... BN11: =BN9+BN10 -> 0
A13: Kap. 2443 | B13: Petoro AS
A14: Post 70 | B14: Administrasjon | C14: 0.258 | D14: 0 | E14: 5.3 | F14: 0 | G14: 50 | H14: 250 | I14: 220 | J14: 0 | K14: =J14*(1+KVARTS!$H$12/100) -> 0 | L14: =K14*(1+KVARTS!$H$12/100) -> 0 | M14: =L14*(1+KVARTS!$H$12/100) -> 0 | N14: =M14*(1+KVARTS!$H$12/100) -> 0 | O14: =N14*(1+KVARTS!$H$12/100) -> 0 | P14: =O14*(1+KVARTS!$H$12/100) -> 0 | Q14: =P14*(1+KVARTS!$H$12/100) -> 0 | R14: =Q14*(1+KVARTS!$H$12/100) -> 0 | ... BN14: =BM14*(1+KVARTS!$H$12/100) -> 0
A15: Sum kap 2443 | C15: =C14 -> 0.258 | D15: =D14 -> 0 | E15: =E14 -> 5.3 | F15: =F14 -> 0 | G15: =G14 -> 50 | H15: =H14 -> 250 | I15: =I14 -> 220 | J15: =J14 -> 0 | ... BN15: =BN14 -> 0
A17: Kap. 5442 | B17: Disp. innretninger
A18: Post 80 | B18: Tilbakef. av tilskudd | C18: 0.258 | D18: 0 | E18: 5.316 | F18: 0 | G18: 0 | J18: 1.955
A19: Sum kap 5442 | C19: =C18 -> 0.258 | D19: =D18 -> 0 | E19: =E18 -> 5.316 | F19: =F18 -> 0 | G19: =G18 -> 0 | H19: =H18 -> 0 | I19: =I18 -> 0 | J19: =J18 -> 1.955 | ... BN19: =BN18 -> 0
A23: FBU+FUV
A24: Kap. 2440 | B24: SDØE
A25: Post 22 | B25: Fjerningsutg. | C25: 0 | D25: 0 | E25: 20.001241 | F25: 7.840046 | G25: 0 | H25: 86.578 | I25: 2.875 | J25: -0.015
A26: Post 25 | B26: Pro & contra oppgjør | G26: 8448.989 | H26: 1977.575 | I26: 208.905 | J26: 98.462248 | K26: 0.686004 | L26: 15.877961
A27: Post 30 | B27: Inv. | C27: 20341.944 | D27: 27250.755 | E27: 30336.998 | F27: 22647.354 | G27: 16569.099 | H27: 12807.833 | I27: 16038.211 | J27: 17323.845 | K27: 20701.299 | L27: 19967.276 | M27: 19950.561 | N27: 19997.732 | O27: 23596.66 | P27: 18470 | Q27: 21436.794 | R27: 25610.149 | S27: 33584.653 | T27: 35371 | U27: 29254.281 | V27: 27815.084 | W27: 26564.055 | X27: 22554.906 | Y27: 26330.658 | Z27: 27601 | AA27: 24732 | AB27: 28378 | AC27: 30396 | AD27: 35397 | AE27: 33400 | AF27: 36100 | AG27: 39600 | AH27: 39500 | AI27: 38600 | AJ27: 35048.05 | AK27: 32360.927 | AL27: 32650.254 | AM27: 30847.499 | AN27: 28551.896 | AO27: 24528.448 | AP27: 23302.028 | AQ27: 23380.023 | AR27: 23438.618 | AS27: 23397.07 | AT27: 22719.652 | AU27: 22315.609 | AV27: 20571.908 | AW27: 20636.644 | AX27: 20451.345 | AY27: 19310.67 | AZ27: 18982.422 | BA27: 18230.886 | BB27: 17821.604 | BC27: 17459.919 | BD27: 17065.078 | BE27: 16750.289 | BF27: 16322.349 | BG27: 15931.369 | BH27: 15764.283 | BI27: 15405.506 | BJ27: 14895.096 | BK27: 14420.287 | BL27: 13970.175 | BM27: 13528.569 | BN27: 13319.757
A28: Post 31 | B28: Kjøp av andelar | AD28: 13129 | AE28: -2046.441
A29: Post 50 | B29: Til p.f.fond | C29: 600 | D29: 285.984 | E29: 586 | F29: 592 | G29: =592 -> 592 | H29: 905 | I29: 980.6 | J29: 1113 | K29: 731 | L29: 1199 | M29: 1101 | N29: 1841 | O29: 1122 | P29: 1594 | Q29: 0 | R29: 0 | S29: 0 | T29: 0 | U29: 0 | V29: 0 | W29: 0 | X29: 0 | Y29: 0 | Z29: 0 | AA29: 0 | AB29: 0 | AC29: 0 | AD29: 0 | AE29: 0 | AF29: 0 | AG29: 0 | AH29: 0 | AI29: 0 | AJ29: 0 | AK29: 0 | AL29: 0 | AM29: 0 | AN29: 0 | AO29: 0 | AP29: 0 | AQ29: 0 | AR29: 0 | AS29: 0 | AT29: 0 | AU29: 0 | AV29: 0 | AW29: 0 | AX29: 0 | AY29: 0 | AZ29: 0 | BA29: 0 | BB29: 0 | BC29: 0 | BD29: 0 | BE29: 0 | BF29: 0 | BG29: 0 | BH29: 0 | BI29: 0 | BJ29: 0 | BK29: 0 | BL29: 0 | BM29: 0 | BN29: 0
A30: Sum Kap. 2440 | C30: =SUM(C25:C29) -> 20941.944 | D30: =SUM(D25:D29) -> 27536.739 | E30: =SUM(E25:E29) -> 30942.999 | F30: =SUM(F25:F29) -> 23247.195 | G30: =SUM(G25:G29) -> 25610.088 | H30: =SUM(H25:H29) -> 15776.986 | I30: =SUM(I25:I29) -> 17230.591 | J30: =SUM(J25:J29) -> 18535.292 | ... BN30: =SUM(BN25:BN29) -> 13319.757
A32: Kap. 5440 | B32: SDØE
A33: 01 | B33: Pro & contra oppgjør | H33: 347.881 | I33: 51.006 | J33: 118.98633 | K33: 233.073
A34: 24.01 | B34: Driftsinnt. | C34: 76899.51 | D34: 60262.914 | E34: 74581.097 | F34: 142264.77 | G34: 128589.42 | H34: 99935.367 | I34: 101184.7 | J34: 120331.7 | K34: 144181.51 | L34: 176443.19 | M34: 162924.99 | N34: 216722.17 | O34: 156123.52 | P34: 156745.94 | Q34: 183982.11 | R34: 213166.28 | S34: 197639.91 | T34: 185514 | U34: 158512.8 | V34: 127908.6 | W34: 145043.04 | X34: 175454.21 | Y34: 155059.3 | Z34: 113793.97 | AA34: 249674.3 | AB34: 634025.31 | AC34: 363492.33 | AD34: 313874 | AE34: 318700 | AF34: 274200 | AG34: 229300 | AH34: 219800 | AI34: 201100 | AJ34: 171905.25 | AK34: 163056.49 | AL34: 158113.64 | AM34: 154788.14 | AN34: 153597.5 | AO34: 148878.39 | AP34: 143381.39 | AQ34: 139496.81 | AR34: 132433.22 | AS34: 124366.15 | AT34: 118857.91 | AU34: 110263.41 | AV34: 110983.31 | AW34: 107681.55 | AX34: 104287 | AY34: 100931.62 | AZ34: 97694.897 | BA34: 94342.061 | BB34: 91099.772 | BC34: 86722.044 | BD34: 79477.73 | BE34: 76662.145 | BF34: 73824.363 | BG34: 70277.54 | BH34: 67712.022 | BI34: 66157.813 | BJ34: 62891.003 | BK34: 62182.572 | BL34: 61313.045 | BM34: 60387.93 | BN34: 60253.732
A35: 24.02 | B35: Driftsutg. | C35: -13473 | D35: -15563.819 | E35: -16849.842 | F35: -19584.97 | G35: -16765.714 | H35: -17763.887 | I35: -17362.291 | J35: -21696.296 | K35: -24289.046 | L35: -29077.688 | M35: -30350.799 | N35: -39869.835 | O35: -33709.84 | P35: -32477.388 | Q35: -32764.717 | R35: -36808.814 | S35: -36559.772 | T35: -34665 | U35: -34601.627 | V35: -31160.202 | W35: -28774.709 | X35: -32036.103 | Y35: -29995.982 | Z35: -28063.437 | AA35: -38308.416 | AB35: -74657.536 | AC35: -55109.741 | AD35: -43198.659 | AE35: -43200 | AF35: -43000 | AG35: -41500 | AH35: -41700 | AI35: -46100 | AJ35: -44881.815 | AK35: -45071.269 | AL35: -45394.803 | AM35: -44740.963 | AN35: -46336.245 | AO35: -45599.64 | AP35: -45920.683 | AQ35: -44880.826 | AR35: -46756.72 | AS35: -47595.268 | AT35: -48189.831 | AU35: -46779.257 | AV35: -46497.804 | AW35: -49682.279 | AX35: -45946.176 | AY35: -47587.088 | AZ35: -45603.835 | BA35: -46868.134 | BB35: -45036.947 | BC35: -43358.653 | BD35: -40745.753 | BE35: -40977.829 | BF35: -39644.165 | BG35: -40052.734 | BH35: -39801.142 | BI35: -38910.991 | BJ35: -35510.008 | BK35: -36096.649 | BL35: -32374.282 | BM35: -32546.957 | BN35: -32542.794
A36: 24.03 | B36: Leteutg. | C36: -2331.463 | D36: -2726.163 | E36: -1516.1244 | F36: -1879.4917 | G36: -1538.855 | H36: -1011.696 | I36: -642.541 | J36: -543.359 | K36: -978.364 | L36: -1122.226 | M36: -1423.993 | N36: -1962.8019 | O36: -2391.12 | P36: -1764.538 | Q36: -2005.3135 | R36: -1858.0599 | S36: -3199.8096 | T36: -2619.0849 | U36: -1940.4115 | V36: -2478.0089 | W36: -1432.2438 | X36: -2175.5065 | Y36: -2245.0205 | Z36: -1742.839 | AA36: -1463.8162 | AB36: -1955.951 | AC36: -1476.141 | AD36: -2907.356 | AE36: -2100 | AF36: -2100 | AG36: -1800 | AH36: -1800 | AI36: -1800 | AJ36: -2771.7101 | AK36: -2854.6718 | AL36: -2838.3866 | AM36: -2842.1338 | AN36: -2879.755 | AO36: -2887.6152 | AP36: -2890.2315 | AQ36: -2889.8383 | AR36: -2892.0349 | AS36: -2809.1141 | AT36: -2778.5878 | AU36: -2833.7854 | AV36: -2890.2066 | AW36: -2855.9949 | AX36: -2850.6323 | AY36: -2907.6449 | AZ36: -2965.7978 | BA36: -2925.3724 | BB36: -2983.8798 | BC36: -3043.5574 | BD36: -2998.5822 | BE36: -2878.6658 | BF36: -2936.2391 | BG36: -2994.9639 | BH36: -3054.8632 | BI36: -3115.9604 | BJ36: -3178.2796 | BK36: -3241.8452 | BL36: -3306.6821 | BM36: -3372.8158 | BN36: -3440.2721
A37: 24.04 | B37: Avskrivn. | C37: -14092.148 | D37: -14443.221 | E37: -15343.33 | F37: -17006.37 | G37: -17892.241 | H37: -14571.337 | I37: -14092.013 | J37: -14609.777 | K37: -12914.084 | L37: -14537.729 | M37: -15403.963 | N37: -15741.102 | O37: -15268.079 | P37: -15719.89 | Q37: -16861.847 | R37: -19500.976 | S37: -20261.842 | T37: -21837 | U37: -23721.755 | V37: -23276.648 | W37: -24648.044 | X37: -23636.285 | Y37: -22673.976 | Z37: -22438.631 | AA37: -25633.967 | AB37: -26314.13 | AC37: -27206.412 | AD37: 29599.681 | AE37: -33500 | AF37: -39300 | AG37: -40000 | AH37: -45700 | AI37: -32300
A38: 24.05 | B38: Renter | C38: -8983.521 | D38: -8535.8508 | E38: -8419.9428 | F38: -8397.8829 | G38: -7487.597 | H38: -6362.82 | I38: -6392.093 | J38: -6677.383 | K38: -6670.289 | L38: -6844.4532 | M38: -6929.15 | N38: -6572.8041 | O38: -6469 | P38: -6526.391 | Q38: -6529.898 | R38: -6552.8533 | S38: -6014.3654 | T38: -4944 | U38: -4104.0022 | V38: -3805.8039 | W38: -3567.9702 | X38: -3096.414 | Y38: -2768.2806 | Z38: -2474.387 | AA38: -2331.3975 | AB38: -2377.552 | AC38: -2696.659 | AD38: -4015.564 | AE38: -5000 | AF38: -5000 | AG38: -6900 | AH38: -8300 | AI38: -9300
A39: SUM 24 | B39: Driftsresultat | C39: =SUM(C34:C38) -> 38019.378 | D39: =SUM(D34:D38) -> 18993.86 | E39: =SUM(E34:E38) -> 32451.859 | F39: =SUM(F34:F38) -> 95396.056 | G39: =SUM(G34:G38) -> 84905.014 | H39: =SUM(H34:H38) -> 60225.627 | I39: =SUM(I34:I38) -> 62695.761 | J39: =SUM(J34:J38) -> 76804.886 | ... BN39: =SUM(BN34:BN38) -> 24270.666
A40: Post 30 | B40: Avskrivn. | C40: =-C37 -> 14092.148 | D40: =-D37 -> 14443.221 | E40: =-E37 -> 15343.33 | F40: =-F37 -> 17006.37 | G40: =-G37 -> 17892.241 | H40: =-H37 -> 14571.337 | I40: =-I37 -> 14092.013 | J40: =-J37 -> 14609.777 | ... BN40: =-BN37 -> 0
A41: Post 31 | B41: Salg andeler | G41: =38979.889 -> 38979.889 | H41: 8521
A42: Post 50 | B42: Fra p.f.fond | C42: 118.084 | D42: 182.29755 | E42: 517.0861 | F42: 652.57364 | G42: 565.862 | H42: 284.885 | I42: 1482.152 | J42: 490.36801 | K42: 887.569 | L42: 462.18282 | M42: 1136.551 | N42: 707.82981 | O42: 35 | P42: 737.849
A43: Post 80 | B43: Renter av statens kapital (Renter fast kapital) | C43: =-C38 -> 8983.521 | D43: =-D38 -> 8535.8508 | E43: =-E38 -> 8419.9428 | F43: =-F38 -> 8397.8829 | G43: =-G38 -> 7487.597 | H43: =-H38 -> 6362.82 | I43: 6390.077 | J43: 6666.301 | K43: 6646.122 | L43: 6820.1768 | M43: 6918.46 | N43: 6559.904 | O43: 6456 | P43: 6527.677 | Q43: 6540.51 | R43: 6574.6875 | S43: 6041.2852 | T43: 4968 | U43: 4127.036 | V43: 3819.8187 | W43: 3580.822 | X43: 3113.578 | Y43: 2791.025 | Z43: 2483.311 | AA43: 2331.386 | AB43: 2382.093 | AC43: 2707.84 | AD43: 4026.08 | AE43: 5000 | AF43: 5000 | AG43: 6900 | AH43: 8300 | AI43: 9300 | AJ43: =-AJ38 -> 0 | AK43: =-AK38 -> 0 | AL43: =-AL38 -> 0 | AM43: =-AM38 -> 0 | AN43: =-AN38 -> 0 | AO43: =-AO38 -> 0 | AP43: =-AP38 -> 0 | AQ43: =-AQ38 -> 0 | ... BN43: =-BN38 -> 0
A44: Post 81 | B44: Renter, salg av SDØE-andeler | G44: 1247.806 | H44: 248.773
A45: Post 85 | B45: Renter på mellomregnskapet | C45: 132.085 | D45: -46.554115 | E45: -19.79787 | F45: 13.007133 | G45: =-29.229 -> -29.229 | I45: 2.016 | J45: 11.081 | K45: 24.167 | L45: 24.276424 | M45: 10.69 | N45: 12.319158 | O45: 13 | P45: -1.2863051 | Q45: -10.672243 | R45: -21.834221 | S45: -26.919735 | T45: -23 | U45: 0 | V45: -14.014774 | W45: -12.852 | X45: -17.164 | Y45: -31.793 | Z45: -8.9242093 | AA45: 0.012 | AB45: -5.351 | AC45: -11.181 | AD45: -10.516 | AE45: 0 | AF45: 0 | AG45: 0 | AH45: 0 | AI45: 0
A46: Post 84 | B46: E. oppgjør
P47: 875
A48: Sum Kap. 5440 | C48: =SUM(C39:C46) -> 61345.216 | D48: =SUM(D39:D46) -> 42108.675 | E48: =SUM(E39:E46) -> 56712.419 | F48: =SUM(F39:F46) -> 121465.89 | G48: =SUM(G39:G46) -> 151049.18 | H48: =SUM(H39:H46)+H33 -> 90562.323 | I48: =SUM(I39:I46)+I33 -> 84713.025 | J48: =SUM(J39:J46)+J33 -> 98701.399 | K48: =SUM(K39:K46)+K33 -> 120034.75 | L48: =SUM(L39:L46) -> 146705.46 | M48: =SUM(M39:M46) -> 132286.75 | N48: =SUM(N39:N47) -> 175596.78 | O48: =SUM(O39:O47) -> 120057.56 | P48: =SUM(P39:P47) -> 124116.86 | Q48: =SUM(Q39:Q46) -> 149212.02 | R48: =SUM(R39:R46) -> 174499.4 | S48: =SUM(S39:S46) -> 157880.33 | T48: =SUM(T39:T46) -> 148230.92 | U48: =SUM(U39:U46) -> 121993.79 | V48: =SUM(V39:V46) -> 94270.392 | W48: =SUM(W39:W46) -> 114836.09 | X48: =SUM(X39:X46) -> 141242.6 | ... BN48: =SUM(BN39:BN46) -> 24270.666
A50: Innbetalinger | C50: =C34+C41+C42+C44+IF(C45>0,C45,0) -> 77149.679 | D50: =D34+D41+D42+D44+IF(D45>0,D45,0) -> 60445.212 | E50: =E34+E41+E42+E44+IF(E45>0,E45,0)+E18 -> 75103.499 | F50: =F34+F41+F42+F44+IF(F45>0,F45,0) -> 142930.35 | G50: =G34+G41+G42+G44+IF(G45>0,G45,0) -> 169382.98 | H50: =H33+H34+H41+H42+H44+IF(H45>0,H45,0) -> 109337.91 | I50: =I33+I34+I41+I42+I44 -> 102717.86 | J50: =J33+J34+J41+J42+J44 -> 120941.06 | K50: =K33+K34+K41+K42+K44 -> 145302.16 | L50: =L33+L34+L41+L42+L44 -> 176905.37 | M50: =M33+M34+M41+M42+M44 -> 164061.54 | N50: =N33+N34+N41+N42+N44 -> 217430 | O50: =O33+O34+O41+O42+O44 -> 156158.52 | P50: =P33+P34+P41+P42+P44+P47 -> 158358.78 | Q50: =Q33+Q34+Q41+Q42+Q44 -> 183982.11 | R50: =R33+R34+R41+R42+R44 -> 213166.28 | S50: =S33+S34+S41+S42+S44 -> 197639.91 | T50: =T33+T34+T41+T42+T44 -> 185514 | U50: =U33+U34+U41+U42+U44 -> 158512.8 | V50: =V33+V34+V41+V42+V44 -> 127908.6 | W50: =W33+W34+W41+W42+W44 -> 145043.04 | X50: =X33+X34+X41+X42+X44 -> 175454.21 | ... BN50: =BN33+BN34+BN41+BN42+BN44 -> 60253.732
A51: Utbetalinger | C51: =C25+C26+C27+C28+C29-C35-C36 -> 36746.407 | D51: =D25+D26+D27+D28+D29-D35-D36 -> 45826.721 | E51: =E25+E26+E27+E28+E29-E35-E36 -> 49308.965 | F51: =F25+F26+F27+F28+F29-F35-F36 -> 44711.656 | G51: =G25+G26+G27+G28+G29-G35-G36 -> 43914.657 | H51: =H25+H26+H27+H28+H29-H35-H36 -> 34552.569 | I51: =I25+I26+I27+I28+I29-I35-I36 -> 35235.423 | J51: =J25+J26+J27+J28+J29-J35-J36 -> 40774.947 | ... BN51: =BN25+BN26+BN27+BN28+BN29-BN35-BN36 -> 49302.824
A52: Netto inntekt | C52: =(C50-C51) -> 40403.272 | D52: =(D50-D51) -> 14618.49 | E52: =(E50-E51) -> 25794.534 | F52: =(F50-F51) -> 98218.696 | G52: =(G50-G51) -> 125468.32 | H52: =(H50-H51) -> 74785.337 | I52: =(I50-I51) -> 67482.434 | J52: =(J50-J51) -> 80166.108 | ... BN52: =(BN50-BN51) -> 10950.908
A53: Netto inntekt | B53: Kontroll | C53: =(C48-C30)-C52 -> 0 | D53: =(D48-D30)-D52 -> -46.554115 | E53: =(E48+E18-E30)-E52 -> -19.79787 | F53: =(F48-F30)-F52 -> 0 | G53: =(G48-G30)-G52 -> -29.229 | H53: =(H48-H30)-H52 -> 0 | I53: =(I48-I30)-I52 -> 0 | J53: =(J48-J30)-J52 -> -0.00099999999 | K53: =(K48-K30)-K52 -> 0 | L53: =(L48-L30)-L52 -> 0 | M53: =(M48-M30)-M52 -> 0 | ... BN53: =(BN48-BN30)-BN52 -> 0
A55: Investeringer | C55: =C27 -> 20341.944 | D55: =D27 -> 27250.755 | E55: =E27 -> 30336.998 | F55: =F27 -> 22647.354 | G55: =G27 -> 16569.099 | H55: =H27 -> 12807.833 | I55: =I27 -> 16038.211 | J55: =J27 -> 17323.845 | ... BN55: =BN27 -> 13319.757
A56: - Avskrivninger | C56: =-C37 -> 14092.148 | D56: =-D37 -> 14443.221 | E56: =-E37 -> 15343.33 | F56: =-F37 -> 17006.37 | G56: =-G37 -> 17892.241 | H56: =-H37 -> 14571.337 | I56: =-I37 -> 14092.013 | J56: =-J37 -> 14609.777 | ... BN56: =-BN37 -> 0
A57: =Kapitalinnskudd | C57: =C55-C56 -> 6249.796 | D57: =D55-D56 -> 12807.534 | E57: =E55-E56 -> 14993.669 | F57: =F55-F56 -> 5640.9841 | G57: =G55-G56 -> -1323.142 | H57: =H55-H56 -> -1763.504 | I57: =I55-I56 -> 1946.198 | J57: =J55-J56 -> 2714.068 | ... BN57: =BN55-BN56 -> 13319.757
A59: Avrunding | C59: 0 | D59: 0 | E59: 0 | F59: 0 | G59: 0 | H59: 0 | I59: 0 | J59: 0 | K59: 0 | L59: 0 | M59: 0 | N59: 0 | O59: 0 | P59: 0 | Q59: 0 | R59: 0 | S59: 0 | T59: 0 | U59: 0 | V59: 0 | W59: 0 | X59: 0 | Y59: 0 | Z59: 0 | AA59: 0 | AB59: 0 | AC59: 0 | AD59: 0 | AE59: 0 | AF59: 0 | AG59: 0 | AH59: 0 | AI59: 0 | AJ59: 0 | AK59: 0 | AL59: 0 | AM59: 0 | AN59: 0 | AO59: 0 | AP59: 0 | AQ59: 0 | AR59: 0 | AS59: 0 | AT59: 0 | AU59: 0 | AV59: 0 | AW59: 0 | AX59: 0 | AY59: 0 | AZ59: 0 | BA59: 0 | BB59: 0 | BC59: 0 | BD59: 0 | BE59: 0 | BF59: 0 | BG59: 0 | BH59: 0 | BI59: 0 | BJ59: 0 | BK59: 0 | BL59: 0 | BM59: 0 | BN59: 0
A61: Kap. 2441 | B61: Teknologiutv.
A62: Post 50 | B62: Prosj. rettet tekn. utv. | C62: =ROUND(C5,C59) -> 0 | D62: =ROUND(D5,D59) -> 0 | E62: =ROUND(E5,E59) -> 0 | F62: =ROUND(F5,F59) -> 0 | G62: =ROUND(G5,G59) -> 0 | H62: =ROUND(H5,H59) -> 0 | I62: =ROUND(I5,I59) -> 0 | J62: =ROUND(J5,J59) -> 0 | ... M62: =ROUND(M5,M59) -> 0 | N62: =N5 -> 0 | O62: =O5 -> 0 | P62: =P5 -> 0 | Q62: =Q5 -> 0 | R62: =R5 -> 0 | S62: =ROUND(S5,S59) -> 0 | T62: =ROUND(T5,T59) -> 0 | U62: =ROUND(U5,U59) -> 0 | V62: =ROUND(V5,V59) -> 0 | W62: =ROUND(W5,W59) -> 0 | X62: =ROUND(X5,X59) -> 0 | Y62: =ROUND(Y5,Y59) -> 0 | Z62: =ROUND(Z5,Z59) -> 0 | ... BN62: =ROUND(BN5,BN59) -> 0
A63: Sum kap 2441 | C63: =SUM(C62) -> 0 | D63: =SUM(D62) -> 0 | E63: =SUM(E62) -> 0 | F63: =SUM(F62) -> 0 | G63: =SUM(G62) -> 0 | H63: =SUM(H62) -> 0 | I63: =SUM(I62) -> 0 | J63: =SUM(J62) -> 0 | ... BN63: =SUM(BN62) -> 0
A65: Kap. 2442 | B65: Disponering
A66: Post 21 | B66: Spes. dr. utg. | C66: =ROUND(C9,C$59) -> 0 | D66: =ROUND(D9,D$59) -> 2 | E66: =ROUND(E9,E$59) -> 3 | F66: =ROUND(F9,F$59) -> 3 | G66: =ROUND(G9,G$59) -> 0 | H66: =ROUND(H9,H$59) -> 0 | I66: =ROUND(I9,I$59) -> 0 | J66: =ROUND(J9,J$59) -> 0 | ... M66: =ROUND(M9,M$59) -> 0 | N66: =N9 -> 0 | O66: =O9 -> 0 | P66: =P9 -> 81.5 | Q66: =Q9 -> 2 | R66: =R9 -> 0.027193 | S66: =ROUND(S9,S$59) -> 1 | T66: =ROUND(T9,T$59) -> 2 | U66: =ROUND(U9,U$59) -> 0 | V66: =ROUND(V9,V$59) -> 0 | W66: =ROUND(W9,W$59) -> 0 | X66: =ROUND(X9,X$59) -> 0 | Y66: =ROUND(Y9,Y$59) -> 0 | Z66: =ROUND(Z9,Z$59) -> 0 | ... BN66: =ROUND(BN9,BN$59) -> 0
A67: Post 70 | B67: Tilskudd | C67: =ROUND(C10,C$59) -> 93 | D67: =ROUND(D10,D$59) -> 70 | E67: =ROUND(E10,E$59) -> 15 | F67: =ROUND(F10,F$59) -> 0 | G67: =ROUND(G10,G$59) -> 6 | H67: =ROUND(H10,H$59) -> 48 | I67: =ROUND(I10,I$59) -> 113 | J67: =ROUND(J10,J$59) -> 125 | ... L67: =ROUND(L10,L$59) -> 0 | M67: 4.58 | N67: =N10 -> 0 | O67: =O10 -> 0 | P67: =P10 -> 0 | Q67: =Q10 -> 0 | R67: =R10 -> 0 | S67: =ROUND(S10,S$59) -> 0 | T67: =ROUND(T10,T$59) -> 0 | U67: =ROUND(U10,U$59) -> 0 | V67: =ROUND(V10,V$59) -> 0 | W67: =ROUND(W10,W$59) -> 0 | X67: =ROUND(X10,X$59) -> 0 | Y67: =ROUND(Y10,Y$59) -> 0 | Z67: =ROUND(Z10,Z$59) -> 0 | ... BN67: =ROUND(BN10,BN$59) -> 0
A68: Sum kap 2442 | C68: =SUM(C66:C67) -> 93 | D68: =SUM(D66:D67) -> 72 | E68: =SUM(E66:E67) -> 18 | F68: =SUM(F66:F67) -> 3 | G68: =SUM(G66:G67) -> 6 | H68: =SUM(H66:H67) -> 48 | I68: =SUM(I66:I67) -> 113 | J68: =SUM(J66:J67) -> 125 | ... BN68: =SUM(BN66:BN67) -> 0
A70: Kap. 2443 | B70: Petoro AS
A71: Post 70 | B71: Administrasjon | C71: =ROUND(C14,C$59) -> 0 | D71: =ROUND(D14,D$59) -> 0 | E71: =ROUND(E14,E$59) -> 5 | F71: =ROUND(F14,F$59) -> 0 | G71: =ROUND(G14,G$59) -> 50 | H71: =ROUND(H14,H$59) -> 250 | I71: =ROUND(I14,I$59) -> 220 | J71: =ROUND(J14,J$59) -> 0 | ... M71: =ROUND(M14,M$59) -> 0 | N71: =N14 -> 0 | O71: =O14 -> 0 | P71: =P14 -> 0 | Q71: =Q14 -> 0 | R71: =R14 -> 0 | S71: =ROUND(S14,S$59) -> 0 | T71: =ROUND(T14,T$59) -> 0 | U71: =ROUND(U14,U$59) -> 0 | V71: =ROUND(V14,V$59) -> 0 | W71: =ROUND(W14,W$59) -> 0 | X71: =ROUND(X14,X$59) -> 0 | Y71: =ROUND(Y14,Y$59) -> 0 | Z71: =ROUND(Z14,Z$59) -> 0 | ... BN71: =ROUND(BN14,BN$59) -> 0
A72: Sum kap 2443 | C72: =SUM(C71) -> 0 | D72: =SUM(D71) -> 0 | E72: =SUM(E71) -> 5 | F72: =SUM(F71) -> 0 | G72: =SUM(G71) -> 50 | H72: =SUM(H71) -> 250 | I72: =SUM(I71) -> 220 | J72: =SUM(J71) -> 0 | ... BN72: =SUM(BN71) -> 0
A74: Kap. 5442 | B74: Disp. innretninger
A75: Post 80 | B75: Tilbakef. av tilskudd | C75: =ROUND(C18,C59) -> 0 | D75: =ROUND(D18,D59) -> 0 | E75: =ROUND(E18,E59) -> 5 | F75: =ROUND(F18,F59) -> 0 | G75: =ROUND(G18,G59) -> 0 | H75: =ROUND(H18,H59) -> 0 | I75: =ROUND(I18,I59) -> 0 | J75: =ROUND(J18,J59) -> 2 | ... M75: =ROUND(M18,M59) -> 0 | N75: =N18 -> 0 | O75: =O18 -> 0 | P75: =P18 -> 0 | Q75: =Q18 -> 0 | R75: =R18 -> 0 | S75: =ROUND(S18,S59) -> 0 | T75: =ROUND(T18,T59) -> 0 | U75: =ROUND(U18,U59) -> 0 | V75: =ROUND(V18,V59) -> 0 | W75: =ROUND(W18,W59) -> 0 | X75: =ROUND(X18,X59) -> 0 | Y75: =ROUND(Y18,Y59) -> 0 | Z75: =ROUND(Z18,Z59) -> 0 | ... BN75: =ROUND(BN18,BN59) -> 0
A76: Sum kap 5442 | C76: =SUM(C75) -> 0 | D76: =SUM(D75) -> 0 | E76: =SUM(E75) -> 5 | F76: =SUM(F75) -> 0 | G76: =SUM(G75) -> 0 | H76: =SUM(H75) -> 0 | I76: =SUM(I75) -> 0 | J76: =SUM(J75) -> 2 | ... BN76: =SUM(BN75) -> 0
A79: Netto andre inntekter | C79: =-C63-C68-C72+C76 -> -93 | D79: =-D63-D68-D72+D76 -> -72 | E79: =-E63-E68-E72+E76 -> -18 | F79: =-F63-F68-F72+F76 -> -3 | G79: =-G63-G68-G72+G76 -> -56 | H79: =-H63-H68-H72+H76 -> -298 | I79: =-I63-I68-I72+I76 -> -333 | J79: =-J63-J68-J72+J76 -> -123 | ... BN79: =-BN63-BN68-BN72+BN76 -> 0
B86: SDØE-produksjon
B87: Oljeproduksjon m Sm3 oe | C87: 70.9 | D87: 67.89 | E87: 72.5 | F87: 71.54 | G87: 65 | H87: 56 | I87: 50.24 | J87: 48.98 | K87: 42.86 | L87: 37.6 | M87: 33.6 | N87: 30.2 | O87: 27.23 | P87: 23.2 | Q87: 21.4 | R87: 19.7 | S87: 18.8 | T87: 18.6 | U87: 19.2 | V87: 18.8 | W87: 17.6 | X87: 16.6 | Y87: 15.179794 | Z87: 17.441832 | AA87: 18.861712 | AB87: 17.866655 | AC87: 17.565511 | AD87: 15.779605 | AE87: 17.715409 | AF87: 17.948733 | AG87: 16.406327 | AH87: 14.997435 | AI87: 12.958051 | AJ87: 12.04554 | AK87: 10.966561 | AL87: 10.500992 | AM87: 10.300487 | AN87: 10.286427 | AO87: 9.6791286 | AP87: 9.4496687 | AQ87: 9.1122837 | AR87: 8.7858505 | AS87: 8.4638827 | AT87: 8.0808394 | AU87: 7.3143004 | AV87: 6.8727205 | AW87: 6.4922563 | AX87: 6.126149 | AY87: 5.7027728 | AZ87: 5.4401775 | BA87: 5.1073584 | BB87: 4.8729088 | BC87: 4.9045719 | BD87: 4.7034301 | BE87: 4.2268975 | BF87: 4.1163055 | BG87: 3.93501 | BH87: 3.8411151 | BI87: 3.6831265 | BJ87: 3.5752509 | BK87: 3.4459034 | BL87: 3.3301616 | BM87: 3.2155924 | BN87: 3.1099787
B88: Gassproduksjon m Sm3 oe | C88: 14.3 | D88: 16.259398 | E88: 20.839506 | F88: 21.514851 | G88: 22 | H88: 22 | I88: 24 | J88: 24.96 | K88: 28.1 | L88: 33.8 | M88: 32.5 | N88: 34.7 | O88: 35.37 | P88: 39.5 | Q88: 32.9 | R88: 36 | S88: 36.1 | T88: 35.4 | U88: 36 | V88: 39 | W88: 37.7 | X88: 37.6 | Y88: 36.539207 | Z88: 35.360923 | AA88: 36.625264 | AB88: 38.886194 | AC88: 36.426429 | AD88: 38.018384 | AE88: 37.86259 | AF88: 39.161307 | AG88: 39.333856 | AH88: 38.577352 | AI88: 36.484966 | AJ88: 34.633923 | AK88: 32.916982 | AL88: 31.654232 | AM88: 30.142182 | AN88: 28.68906 | AO88: 26.402399 | AP88: 24.866197 | AQ88: 23.105524 | AR88: 20.847349 | AS88: 18.505079 | AT88: 17.050676 | AU88: 15.111865 | AV88: 14.030591 | AW88: 12.876076 | AX88: 11.846375 | AY88: 10.642386 | AZ88: 9.4441903 | BA88: 8.4529571 | BB88: 7.5951747 | BC88: 6.7412078 | BD88: 5.7171619 | BE88: 4.7713374 | BF88: 4.2277513 | BG88: 3.9432181 | BH88: 3.8133478 | BI88: 3.73691 | BJ88: 3.6320704 | BK88: 3.5309487 | BL88: 3.4052873 | BM88: 3.309145 | BN88: 3.2076143
B89: NGL-produksjon m Sm3 oe | C89: 1.7 | D89: 2.63 | E89: 1.2 | F89: 4.87 | G89: 3.8 | H89: 3.9 | I89: 4.39 | J89: 4.22 | K89: 4.49 | L89: 5.4 | M89: 4 | N89: 4 | O89: 4.732 | P89: 4.6 | Q89: 4.8 | R89: 5.4 | S89: 4.8 | T89: 5.6 | U89: 5.2 | V89: 5.2 | W89: 4.8 | X89: 4.9 | Y89: 4.5944199 | Z89: 4.2099224 | AA89: 3.4439169 | AB89: 2.8218265 | AC89: 2.9497016 | AD89: 3.0887218 | AE89: 2.6109751 | AF89: 2.6784611 | AG89: 2.5572486 | AH89: 2.2439141 | AI89: 2.1310551 | AJ89: 2.0306216 | AK89: 2.0811138 | AL89: 2.1202977 | AM89: 1.8935166 | AN89: 1.5587773 | AO89: 1.2889944 | AP89: 1.2527744 | AQ89: 1.2042177 | AR89: 1.1308099 | AS89: 1.0535176 | AT89: 0.99043306 | AU89: 0.95617353 | AV89: 0.93486635 | AW89: 0.89191726 | AX89: 0.83623857 | AY89: 0.79189874 | AZ89: 0.74843053 | BA89: 0.68171575 | BB89: 0.64024245 | BC89: 0.58420278 | BD89: 0.4983163 | BE89: 0.4353539 | BF89: 0.39573998 | BG89: 0.34309183 | BH89: 0.29034668 | BI89: 0.24636464 | BJ89: 0.1855037 | BK89: 0.13620385 | BL89: 0.079059315 | BM89: 0.02580792 | BN89: 1.9557774e-09
B90: Sum produksjon m Sm3 oe | C90: =SUM(C87:C89) -> 86.9 | D90: =SUM(D87:D89) -> 86.779398 | E90: =SUM(E87:E89) -> 94.539506 | F90: =SUM(F87:F89) -> 97.924851 | G90: =SUM(G87:G89) -> 90.8 | H90: =SUM(H87:H89) -> 81.9 | I90: =SUM(I87:I89) -> 78.63 | J90: =SUM(J87:J89) -> 78.16 | ... BN90: =SUM(BN87:BN89) -> 6.317593
B91: Kilde: OED
B93: Markedsverdi SDØE Mill. kr.
B94: Olje | C94: =KVARTS!B33*C87 -> 60471.527 | D94: =KVARTS!C33*D87 -> 41229.058 | E94: =KVARTS!D33*E87 -> 61408.18 | F94: =KVARTS!E33*F87 -> 112943.22 | G94: =KVARTS!F33*G87 -> 91170.796 | H94: =KVARTS!G33*H87 -> 69741.413 | I94: =KVARTS!H33*I87 -> 63516.011 | J94: =KVARTS!I33*J87 -> 78559.098 | ... BN94: =KVARTS!BM33*BN87 -> 27398.396
B95: Gass | C95: =KVARTS!B34*C88 -> 9295 | D95: =KVARTS!C34*D88 -> 10406.015 | E95: =KVARTS!D34*E88 -> 11461.728 | F95: =KVARTS!E34*F88 -> 21299.703 | G95: =KVARTS!F34*G88 -> 26620 | H95: =KVARTS!G34*H88 -> 20240 | I95: =KVARTS!H34*I88 -> 21120 | J95: =KVARTS!I34*J88 -> 24211.2 | ... BN95: =KVARTS!BM34*BN88 -> 13827.317
B96: NGL | C96: =KVARTS!B8*C89 -> 1689.171 | D96: =KVARTS!C8*D89 -> 1618.0549 | E96: =KVARTS!D8*E89 -> 1221.564 | F96: =KVARTS!E8*F89 -> 8363.1049 | G96: =KVARTS!F8*G89 -> 5800.206 | H96: =KVARTS!G8*H89 -> 5370.69 | I96: =KVARTS!H8*I89 -> 4799.0114 | J96: =KVARTS!I8*J89 -> 5621.58 | ... BN96: =KVARTS!BM8*BN89 -> 9.9968812e-06
B97: Sum | C97: =SUM(C94:C96) -> 71455.698 | D97: =SUM(D94:D96) -> 53253.128 | E97: =SUM(E94:E96) -> 74091.472 | F97: =SUM(F94:F96) -> 142606.03 | G97: =SUM(G94:G96) -> 123591 | H97: =SUM(H94:H96) -> 95352.103 | I97: =SUM(I94:I96) -> 89435.022 | J97: =SUM(J94:J96) -> 108391.88 | ... BN97: =SUM(BN94:BN96) -> 41225.713

Sheet Formue
B1: 2000 | C1: 2001 | D1: 2002 | E1: 2003 | F1: 2004 | G1: 2005 | H1: 2006 | I1: 2007 | J1: 2008 | K1: 2009 | L1: 2010 | M1: 2011 | N1: 2012 | O1: 2013 | P1: 2014 | Q1: 2015 | R1: 2016 | S1: 2017 | T1: 2018 | U1: 2019 | V1: 2020 | W1: 2021 | X1: 2022 | Y1: 2023 | Z1: 2024 | AA1: 2025 | AB1: 2026 | AC1: 2027 | AD1: 2028 | AE1: 2029 | AF1: 2030 | AG1: 2031 | AH1: 2032 | AI1: 2033 | AJ1: 2034 | AK1: 2035 | AL1: 2036 | AM1: 2037 | AN1: 2038 | AO1: 2039 | AP1: 2040 | AQ1: 2041 | AR1: 2042 | AS1: 2043 | AT1: 2044 | AU1: 2045 | AV1: 2046 | AW1: 2047 | AX1: 2048 | AY1: 2049 | AZ1: 2050 | BA1: 2051 | BB1: 2052 | BC1: 2053 | BD1: 2054 | BE1: 2055 | BF1: 2056 | BG1: 2057 | BH1: 2058 | BI1: 2059 | BJ1: 2060 | BK1: 2061 | BL1: 2062 | BM1: 2063 | BN1: 2064 | BO1: 2065 | BP1: 2066 | BQ1: 2067 | BR1: 2068 | BS1: 2069 | BT1: 2070 | BU1: 2071 | BV1: 2072 | BW1: 2073 | BX1: 2074 | BY1: 2075 | BZ1: 2076 | CA1: 2077 | CB1: 2078 | CC1: 2079 | CD1: 2080 | CE1: 2081 | CF1: 2082 | CG1: 2083 | CH1: 2084 | CI1: 2085 | CJ1: 2086 | CK1: 2087 | CL1: 2088 | CM1: 2089 | CN1: 2090
H3: 2031-2050 | J3: 2036-2050 | L3: 2040-2050 | N3: Faktor som anvendes
A4: Vekstrater | B4: 2031-2050 | C4: 2051-2090 | F4: Totalproduksjon | H4: =(AZ34/AG34)^(1/20) -> 0.96246528 | J4: =(AZ34/AL34)^(1/20) -> 0.9701335 | L4: =(AZ34/AQ34)^(1/20) -> 0.98213128
A6: Prisvekst | F6: Påløpte driftsutgifter (faste) | H6: =(AZ54/AG54)^(1/20) -> 0.98238415 | J6: =(AZ54/AL54)^(1/20) -> 0.98472439 | L6: =(AZ54/AQ54)^(1/20) -> 0.98968385
F7: Faktor | H7: =H6/H4 -> 1.0206957 | J7: =J6/J4 -> 1.0150401 | L7: =L6/L4 -> 1.00769 | N7: 1.016 | P7: Samme faktor i NB20 og RNB20
A8: Oljeproduksjon mill. Sm3 oe | B8: -335544.32 | C8: 0.023767071
A9: Gassproduksjon mill. Sm3 oe | C9: 0.008938545 | F9: Investeringsutgifter, faste priser | H9: =(AZ57/AG57)^(1/20) -> 0.97505411 | J9: =(AZ57/AL57)^(1/20) -> 0.98471592 | L9: =(AZ57/AQ57)^(1/20) -> 0.98800527
A10: NGL-produksjon mill. Sm3 oe | C10: 1.1885227 | F10: Faktor | H10: =H9/H4 -> 1.0130798 | J10: =J9/J4 -> 1.0150314 | L10: =L9/L4 -> 1.0059809 | N10: 1.005 | P10: Samme faktor i NB20 og RNB20
A12: Påløpte driftsutgifter | C12: -0.01
A13: Påløpte fjerningsutgifter | C13: 0.03
A14: Påløpte investeringsutgifter | C14: -0.05
A16: Startverdi 2031 | C16: 0.9
B19: Produksjon | C19: ODs anslag | D19: Andel av | E19: Gjenværende
B20: i beregnings- | C20: på gjenværende | D20: ressursene | E20: ressurser
B21: perioden | C21: ressurser | D21: som blir
C22: pr. 31.12.2022 | D22: produsert
A23: Samlet oljeproduksjon | B23: =SUM(Y30:CN30) -> 3120.7826 | C23: 3520 | D23: =B23/C23 -> 0.88658598 | E23: =C23-B23 -> 399.21735
A24: Samlet gassproduksjon | B24: =SUM(Y31:CN31) -> 3587.8259 | C24: 3684 | D24: =B24/C24 -> 0.97389412 | E24: =C24-B24 -> 96.174062
A25: Samlet NGL-produksjon | B25: =SUM(Y32:CN32) -> 227.4449 | C25: 316 | D25: =B25/C25 -> 0.71976235 | E25: =C25-B25 -> 88.555098
A26: Samlet | B26: =SUM(B23:B25) -> 6936.0535 | C26: =SUM(C23:C25) -> 7520 | D26: =B26/C26 -> 0.92234754 | E26: =C26-B26 -> 583.94651
A27: Formlene oppdatert
A29: Produksjon Mill. Sm3
A30: Produksjon av råolje | I30: =KVARTS!L62 -> 128.28 | J30: =KVARTS!M62 -> 122.66 | K30: =KVARTS!N62 -> 114.94 | L30: =KVARTS!O62 -> 104.39 | M30: =KVARTS!P62 -> 97.46 | N30: =KVARTS!Q62 -> 89.2 | O30: =KVARTS!R62 -> 84.94 | P30: =KVARTS!S62 -> 87.7 | ... BJ30: =KVARTS!BM62 -> 28.071747 | BK30: =BJ30 -> 28.071747 | BL30: =BK30 -> 28.071747 | BM30: =BL30 -> 28.071747 | BN30: =BM30 -> 28.071747 | BO30: =BN30 -> 28.071747 | BP30: =BO30 -> 28.071747 | BQ30: =BP30 -> 28.071747 | BR30: =BQ30 -> 28.071747 | ... CN30: =CM30 -> 28.071747
A31: Produksjon av naturgass | I31: =KVARTS!L63 -> 89.51 | J31: =KVARTS!M63 -> 99.46 | K31: =KVARTS!N63 -> 103.68 | L31: =KVARTS!O63 -> 106.53 | M31: =KVARTS!P63 -> 100.3 | N31: =KVARTS!Q63 -> 113.06 | O31: =KVARTS!R63 -> 107.05 | P31: =KVARTS!S63 -> 106.8 | ... BJ31: =KVARTS!BM63 -> 32.602377 | BK31: =BJ31 -> 32.602377 | BL31: =BK31 -> 32.602377 | BM31: =BL31 -> 32.602377 | BN31: =BM31 -> 32.602377 | BO31: =BN31 -> 32.602377 | BP31: =BO31 -> 32.602377 | BQ31: =BP31 -> 32.602377 | BR31: =BQ31 -> 32.602377 | ... CN31: =CM31 -> 32.602377
A32: Produksjon av NGL | I32: =KVARTS!L64 -> 19.76 | J32: =KVARTS!M64 -> 20.86 | K32: =KVARTS!N64 -> 21.4 | L32: =KVARTS!O64 -> 19.72 | M32: =KVARTS!P64 -> 20.89 | N32: =KVARTS!Q64 -> 22.38 | O32: =KVARTS!R64 -> 21.71 | P32: =KVARTS!S64 -> 21.86 | ... BJ32: =KVARTS!BM64 -> 0.046981571 | BK32: =BJ32 -> 0.046981571 | BL32: =BK32 -> 0.046981571 | BM32: =BL32 -> 0.046981571 | BN32: =BM32 -> 0.046981571 | BO32: =BN32 -> 0.046981571 | BP32: =BO32 -> 0.046981571 | BQ32: =BP32 -> 0.046981571 | BR32: =BQ32 -> 0.046981571 | ... CN32: =CM32 -> 0.046981571
A33: Råolje og NGL | I33: =I30+I32 -> 148.04 | J33: =J30+J32 -> 143.52 | K33: =K30+K32 -> 136.34 | L33: =L30+L32 -> 124.11 | M33: =M30+M32 -> 118.35 | N33: =N30+N32 -> 111.58 | O33: =O30+O32 -> 106.65 | P33: =P30+P32 -> 109.56 | ... CN33: =CN30+CN32 -> 28.118729
A34: Total produksjon | I34: =I30+I31+I32 -> 237.55 | J34: =J30+J31+J32 -> 242.98 | K34: =K30+K31+K32 -> 240.02 | L34: =L30+L31+L32 -> 230.64 | M34: =M30+M31+M32 -> 218.65 | N34: =N30+N31+N32 -> 224.64 | O34: =O30+O31+O32 -> 213.7 | P34: =P30+P31+P32 -> 216.36 | ... CN34: =CN30+CN31+CN32 -> 60.721106
A37: Priser
A38: Oljepris NOK/Sm3 o.e. | I38: =KVARTS!L33*(1+Skiftberegning!H25) -> 2673.1692 | J38: =KVARTS!M33*(1+Skiftberegning!I25) -> 3497.1344 | K38: =KVARTS!N33*(1+Skiftberegning!J25) -> 2459.3157 | L38: =KVARTS!O33*(1+Skiftberegning!K25) -> 3050.5579 | M38: =KVARTS!P33*(1+Skiftberegning!L25) -> 3912.2618 | N38: =KVARTS!Q33*(1+Skiftberegning!M25) -> 4088.3765 | O38: =KVARTS!R33*(1+Skiftberegning!N25) -> 4019.1886 | P38: =KVARTS!S33*(1+Skiftberegning!O25) -> 3943.7109 | ... BJ38: =KVARTS!BM33*(1+Skiftberegning!BI25) -> 8809.834 | BK38: =Skiftberegning!BJ2*Skiftberegning!BJ15*(1+Skiftberegning!BJ25) -> 8986.0307 | BL38: =Skiftberegning!BK2*Skiftberegning!BK15*(1+Skiftberegning!BK25) -> 9165.7513 | BM38: =Skiftberegning!BL2*Skiftberegning!BL15*(1+Skiftberegning!BL25) -> 9349.0663 | BN38: =Skiftberegning!BM2*Skiftberegning!BM15*(1+Skiftberegning!BM25) -> 9536.0476 | BO38: =Skiftberegning!BN2*Skiftberegning!BN15*(1+Skiftberegning!BN25) -> 9726.7686 | BP38: =Skiftberegning!BO2*Skiftberegning!BO15*(1+Skiftberegning!BO25) -> 9921.3039 | BQ38: =Skiftberegning!BP2*Skiftberegning!BP15*(1+Skiftberegning!BP25) -> 10119.73 | BR38: =Skiftberegning!BQ2*Skiftberegning!BQ15*(1+Skiftberegning!BQ25) -> 10322.125 | ... CN38: =Skiftberegning!CM2*Skiftberegning!CM15*(1+Skiftberegning!CM25) -> 15957.795
A39: Gasspris NOK/Sm3 o.e. | I39: =KVARTS!L34*(1+Skiftberegning!H26) -> 1570 | J39: =KVARTS!M34*(1+Skiftberegning!I26) -> 2220 | K39: =KVARTS!N34*(1+Skiftberegning!J26) -> 1670 | L39: =KVARTS!O34*(1+Skiftberegning!K26) -> 1590 | M39: =KVARTS!P34*(1+Skiftberegning!L26) -> 2000 | N39: =KVARTS!Q34*(1+Skiftberegning!M26) -> 2210 | O39: =KVARTS!R34*(1+Skiftberegning!N26) -> 2310 | P39: =KVARTS!S34*(1+Skiftberegning!O26) -> 2050 | ... BJ39: =KVARTS!BM34*(1+Skiftberegning!BI26) -> 4310.7792 | BK39: =Skiftberegning!BJ5*Skiftberegning!BJ16*(1+Skiftberegning!BJ26) -> 4396.9948 | BL39: =Skiftberegning!BK5*Skiftberegning!BK16*(1+Skiftberegning!BK26) -> 4484.9347 | BM39: =Skiftberegning!BL5*Skiftberegning!BL16*(1+Skiftberegning!BL26) -> 4574.6334 | BN39: =Skiftberegning!BM5*Skiftberegning!BM16*(1+Skiftberegning!BM26) -> 4666.1261 | BO39: =Skiftberegning!BN5*Skiftberegning!BN16*(1+Skiftberegning!BN26) -> 4759.4486 | BP39: =Skiftberegning!BO5*Skiftberegning!BO16*(1+Skiftberegning!BO26) -> 4854.6376 | BQ39: =Skiftberegning!BP5*Skiftberegning!BP16*(1+Skiftberegning!BP26) -> 4951.7303 | BR39: =Skiftberegning!BQ5*Skiftberegning!BQ16*(1+Skiftberegning!BQ26) -> 5050.7649 | ... CN39: =Skiftberegning!CM5*Skiftberegning!CM16*(1+Skiftberegning!CM26) -> 7808.3799
A40: NGL-pris kr/Sm3 o.e. | I40: =KVARTS!L8*(1+Skiftberegning!H25) -> 1814.6526 | J40: =KVARTS!M8*(1+Skiftberegning!I25) -> 2521.0891 | K40: =KVARTS!N8*(1+Skiftberegning!J25) -> 1763.5173 | L40: =KVARTS!O8*(1+Skiftberegning!K25) -> 2199.1357 | M40: =KVARTS!P8*(1+Skiftberegning!L25) -> 2796 | N40: =KVARTS!Q8*(1+Skiftberegning!M25) -> 2896 | O40: =KVARTS!R8*(1+Skiftberegning!N25) -> 2814.8571 | P40: =KVARTS!S8*(1+Skiftberegning!O25) -> 2352.3148 | ... BJ40: =KVARTS!BM8*(1+Skiftberegning!BI25) -> 5111.4616 | BK40: =Skiftberegning!BJ6*(1+Skiftberegning!BJ25) -> 5213.6909 | BL40: =Skiftberegning!BK6*(1+Skiftberegning!BK25) -> 5317.9647 | BM40: =Skiftberegning!BL6*(1+Skiftberegning!BL25) -> 5424.324 | BN40: =Skiftberegning!BM6*(1+Skiftberegning!BM25) -> 5532.8104 | BO40: =Skiftberegning!BN6*(1+Skiftberegning!BN25) -> 5643.4667 | BP40: =Skiftberegning!BO6*(1+Skiftberegning!BO25) -> 5756.336 | BQ40: =Skiftberegning!BP6*(1+Skiftberegning!BP25) -> 5871.4627 | BR40: =Skiftberegning!BQ6*(1+Skiftberegning!BQ25) -> 5988.892 | ... CN40: =Skiftberegning!CM6*(1+Skiftberegning!CM25) -> 9258.7052
A41: Oljepris 2015-NOK pr. fat | I41: =KVARTS!L24 -> 686.78097 | J41: =KVARTS!M24 -> 865.25317 | K41: =KVARTS!N24 -> 610.64954 | L41: =KVARTS!O24 -> 745.23316 | M41: =KVARTS!P24 -> 926.49437 | N41: =KVARTS!Q24 -> 948.57235 | O41: =KVARTS!R24 -> 919.05694 | P41: =KVARTS!S24 -> 887.40201 | ... BJ41: =KVARTS!BM24 -> 712.27491 | BK41: =BJ41 -> 712.27491 | BL41: =BK41 -> 712.27491 | BM41: =BL41 -> 712.27491 | BN41: =BM41 -> 712.27491 | BO41: =BN41 -> 712.27491 | BP41: =BO41 -> 712.27491 | BQ41: =BP41 -> 712.27491 | BR41: =BQ41 -> 712.27491 | ... CN41: =CM41 -> 712.27491
A43: Prisvekst | B43: =KVARTS!E12 -> 3.3768573 | C43: =KVARTS!F12 -> 2.8261711 | D43: =KVARTS!G12 -> 1.5860316 | E43: =KVARTS!H12 -> 2.270095 | F43: =KVARTS!I12 -> 2.6772367 | G43: =KVARTS!J12 -> 3.3927468 | H43: =KVARTS!K12 -> 3.2259441 | I43: =KVARTS!L12 -> 2.8526725 | ... BJ43: =KVARTS!BM12 -> 2 | BK43: =BJ43 -> 2 | BL43: =BK43 -> 2 | BM43: =BL43 -> 2 | BN43: =BM43 -> 2 | BO43: =BN43 -> 2 | BP43: =BO43 -> 2 | BQ43: =BP43 -> 2 | BR43: =BQ43 -> 2 | ... CN43: =CM43 -> 2
A44: Deflator | B44: =KVARTS!E13 -> 0.51394384 | C44: =KVARTS!F13 -> 0.52846878 | D44: =KVARTS!G13 -> 0.53685046 | E44: =KVARTS!H13 -> 0.54903747 | F44: =KVARTS!I13 -> 0.56373651 | G44: =KVARTS!J13 -> 0.58286266 | H44: =KVARTS!K13 -> 0.60166548 | I44: =KVARTS!L13 -> 0.61882903 | ... BJ44: =KVARTS!BM13 -> 1.9664484 | BK44: =BJ44*(1+BK43/100) -> 2.0057773 | BL44: =BK44*(1+BL43/100) -> 2.0458929 | BM44: =BL44*(1+BM43/100) -> 2.0868108 | BN44: =BM44*(1+BN43/100) -> 2.128547 | BO44: =BN44*(1+BO43/100) -> 2.1711179 | BP44: =BO44*(1+BP43/100) -> 2.2145403 | BQ44: =BP44*(1+BQ43/100) -> 2.2588311 | BR44: =BQ44*(1+BR43/100) -> 2.3040077 | ... CN44: =CM44*(1+CN43/100) -> 3.5619491
A46: Markedsverdi Mill. kr
A47: Olje | I47: =KVARTS!L80+Skiftberegning!H55 -> 342914.15 | J47: =KVARTS!M80+Skiftberegning!I55 -> 428958.5 | K47: =KVARTS!N80+Skiftberegning!J55 -> 282673.75 | L47: =KVARTS!O80+Skiftberegning!K55 -> 318447.73 | M47: =KVARTS!P80+Skiftberegning!L55 -> 381289.04 | N47: =KVARTS!Q80+Skiftberegning!M55 -> 364683.18 | O47: =KVARTS!R80+Skiftberegning!N55 -> 341389.88 | P47: =KVARTS!S80+Skiftberegning!O55 -> 345863.44 | ... BJ47: =KVARTS!BM80+Skiftberegning!BI55 -> 247307.43 | BK47: =BK30*BK38 -> 252253.58 | BL47: =BL30*BL38 -> 257298.65 | BM47: =BM30*BM38 -> 262444.62 | BN47: =BN30*BN38 -> 267693.52 | BO47: =BO30*BO38 -> 273047.39 | BP47: =BP30*BP38 -> 278508.33 | BQ47: =BQ30*BQ38 -> 284078.5 | BR47: =BR30*BR38 -> 289760.07 | ... CN47: =CN30*CN38 -> 447963.18
A48: Gass | I48: =KVARTS!L81+Skiftberegning!H58 -> 140530.7 | J48: =KVARTS!M81+Skiftberegning!I58 -> 220801.2 | K48: =KVARTS!N81+Skiftberegning!J58 -> 173145.6 | L48: =KVARTS!O81+Skiftberegning!K58 -> 169382.7 | M48: =KVARTS!P81+Skiftberegning!L58 -> 200600 | N48: =KVARTS!Q81+Skiftberegning!M58 -> 249862.6 | O48: =KVARTS!R81+Skiftberegning!N58 -> 247285.5 | P48: =KVARTS!S81+Skiftberegning!O58 -> 218940 | ... BJ48: =KVARTS!BM81+Skiftberegning!BI58 -> 140541.65 | BK48: =BK31*BK39 -> 143352.48 | BL48: =BL31*BL39 -> 146219.53 | BM48: =BM31*BM39 -> 149143.92 | BN48: =BN31*BN39 -> 152126.8 | BO48: =BO31*BO39 -> 155169.34 | BP48: =BP31*BP39 -> 158272.73 | BQ48: =BQ31*BQ39 -> 161438.18 | BR48: =BR31*BR39 -> 164666.94 | ... CN48: =CN31*CN39 -> 254571.75
A49: NGL | I49: =KVARTS!L82+Skiftberegning!H56 -> 35857.535 | J49: =KVARTS!M82+Skiftberegning!I56 -> 52589.919 | K49: =KVARTS!N82+Skiftberegning!J56 -> 37739.27 | L49: =KVARTS!O82+Skiftberegning!K56 -> 43366.957 | M49: =KVARTS!P82+Skiftberegning!L56 -> 58408.44 | N49: =KVARTS!Q82+Skiftberegning!M56 -> 64812.48 | O49: =KVARTS!R82+Skiftberegning!N56 -> 61110.549 | P49: =KVARTS!S82+Skiftberegning!O56 -> 51421.602 | ... BJ49: =KVARTS!BM82+Skiftberegning!BI56 -> 240.1445 | BK49: =BK32*BK40 -> 244.94739 | BL49: =BL32*BL40 -> 249.84633 | BM49: =BM32*BM40 -> 254.84326 | BN49: =BN32*BN40 -> 259.94013 | BO49: =BO32*BO40 -> 265.13893 | BP49: =BP32*BP40 -> 270.44171 | BQ49: =BQ32*BQ40 -> 275.85054 | BR49: =BR32*BR40 -> 281.36755 | ... CN49: =CN32*CN40 -> 434.98852
A50: Sum | I50: =KVARTS!L83+Skiftberegning!H59 -> 519302.39 | J50: =KVARTS!M83+Skiftberegning!I59 -> 702349.62 | K50: =KVARTS!N83+Skiftberegning!J59 -> 493558.62 | L50: =KVARTS!O83+Skiftberegning!K59 -> 531197.39 | M50: =KVARTS!P83+Skiftberegning!L59 -> 640297.48 | N50: =KVARTS!Q83+Skiftberegning!M59 -> 679358.26 | O50: =KVARTS!R83+Skiftberegning!N59 -> 649785.93 | P50: =KVARTS!S83+Skiftberegning!O59 -> 616225.05 | ... BJ50: =KVARTS!BM83+Skiftberegning!BI59 -> 388089.23 | BK50: =SUM(BK47:BK49) -> 395851.01 | BL50: =SUM(BL47:BL49) -> 403768.03 | BM50: =SUM(BM47:BM49) -> 411843.39 | BN50: =SUM(BN47:BN49) -> 420080.26 | BO50: =SUM(BO47:BO49) -> 428481.86 | BP50: =SUM(BP47:BP49) -> 437051.5 | BQ50: =SUM(BQ47:BQ49) -> 445792.53 | BR50: =SUM(BR47:BR49) -> 454708.38 | ... CN50: =SUM(CN47:CN49) -> 702969.91
A53: Utgifter
A54: Påløpte driftsutgifter (faste priser) | I54: =I55/KVARTS!L15 -> 101161.57 | J54: =J55/KVARTS!M15 -> 108457.01 | K54: =K55/KVARTS!N15 -> 107717.28 | L54: =L55/KVARTS!O15 -> 108694.71 | M54: =M55/KVARTS!P15 -> 112080.25 | N54: =N55/KVARTS!Q15 -> 118364.5 | O54: =O55/KVARTS!R15 -> 122784.99 | P54: =P55/KVARTS!S15 -> 120509.45 | ... BJ54: =BJ55/KVARTS!BM15 -> 48532.877 | BK54: =BJ54*BK34/BJ34*$N$7 -> 49309.403 | BL54: =BK54*BL34/BK34*$N$7 -> 50098.353 | BM54: =BL54*BM34/BL34*$N$7 -> 50899.927 | BN54: =BM54*BN34/BM34*$N$7 -> 51714.326 | BO54: =BN54*BO34/BN34*$N$7 -> 52541.755 | BP54: =BO54*BP34/BO34*$N$7 -> 53382.423 | BQ54: =BP54*BQ34/BP34*$N$7 -> 54236.542 | BR54: =BQ54*BR34/BQ34*$N$7 -> 55104.327 | ... CN54: =CM54*CN34/CM34*$N$7 -> 78135.298
A55: Påløpte driftsutgifter | I55: 69756 | J55: 80246 | K55: 84640 | L55: 87287 | M55: 93966 | N55: 101517 | O55: 107941 | P55: 110496 | Q55: 109512 | R55: 101128 | S55: 69958.704 | T55: 78639.943 | U55: 81608.968 | V55: 72763.489 | W55: 81731.617 | X55: 104517.51 | Y55: 110246.06 | Z55: 111903.13 | AA55: 119155.98 | AB55: 128119.84 | AC55: 132964.13 | AD55: 134863.58 | AE55: 135112.52 | AF55: 127554.46 | AG55: 129491.09 | AH55: 133767.01 | AI55: 136149.43 | AJ55: 138314.61 | AK55: 139839.07 | AL55: 137414.16 | AM55: 137538.02 | AN55: 137766.47 | AO55: 135372.3 | AP55: 136063.86 | AQ55: 137430.47 | AR55: 138849.86 | AS55: 138989.89 | AT55: 139621.98 | AU55: 141629.31 | AV55: 139018.68 | AW55: 143034.33 | AX55: 140660.42 | AY55: 138057.44 | AZ55: 133479.39 | BA55: 132009.17 | BB55: 130442.64 | BC55: 132057.87 | BD55: 134705.03 | BE55: 131320.92 | BF55: 122164.58 | BG55: 122782.11 | BH55: 123765.6 | BI55: 121720.11 | BJ55: 121581.52 | BK55: =BK54*KVARTS!BN15 -> 125997.36 | BL55: =BL54*KVARTS!BO15 -> 130573.58 | BM55: =BM54*KVARTS!BP15 -> 135316.02 | BN55: =BN54*KVARTS!BQ15 -> 140230.69 | BO55: =BO54*KVARTS!BR15 -> 145323.87 | BP55: =BP54*KVARTS!BS15 -> 150602.04 | BQ55: =BQ54*KVARTS!BT15 -> 156071.9 | BR55: =BR54*KVARTS!BU15 -> 161740.43 | ... CN55: =CN54*KVARTS!CQ15 -> 354555.28
A56: Påløpte fjerningsutgifter (tatt med i investeringene) | I56: =KVARTS!L58 -> 0 | J56: =KVARTS!M58 -> 0 | K56: =KVARTS!N58 -> 0 | L56: =KVARTS!O58 -> 0 | M56: =KVARTS!P58 -> 0 | N56: =KVARTS!Q58 -> 0 | O56: =KVARTS!R58 -> 0 | P56: =KVARTS!S58 -> 0 | ... BJ56: =KVARTS!BM58 -> 0 | BK56: =BJ56*(1+$C13) -> 0 | BL56: =BK56*(1+$C13) -> 0 | BM56: =BL56*(1+$C13) -> 0 | BN56: =BM56*(1+$C13) -> 0 | BO56: =BN56*(1+$C13) -> 0 | BP56: =BO56*(1+$C13) -> 0 | BQ56: =BP56*(1+$C13) -> 0 | BR56: =BQ56*(1+$C13) -> 0 | ... CN56: =CM56*(1+$C13) -> 0
A57: Påløpte investeringsutgifter (faste priser) | I57: =+I58/KVARTS!L15 -> 165310.61 | J57: =+J58/KVARTS!M15 -> 174253.49 | K57: =+K58/KVARTS!N15 -> 179222.52 | L57: =+L58/KVARTS!O15 -> 164881.93 | M57: =+M58/KVARTS!P15 -> 183738.56 | N57: =+N58/KVARTS!Q15 -> 210468.15 | O57: =+O58/KVARTS!R15 -> 249094.01 | P57: =+P58/KVARTS!S15 -> 241904.48 | ... BJ57: =+BJ58/KVARTS!BM15 -> 72290.783 | BK57: =+BJ57*(BK34/BJ34)*$N$10 -> 72652.237 | BL57: =+BK57*(BL34/BK34)*$N$10 -> 73015.498 | BM57: =+BL57*(BM34/BL34)*$N$10 -> 73380.575 | BN57: =+BM57*(BN34/BM34)*$N$10 -> 73747.478 | BO57: =+BN57*(BO34/BN34)*$N$10 -> 74116.216 | BP57: =+BO57*(BP34/BO34)*$N$10 -> 74486.797 | BQ57: =+BP57*(BQ34/BP34)*$N$10 -> 74859.231 | BR57: =+BQ57*(BR34/BQ34)*$N$10 -> 75233.527 | ... CN57: =+CM57*(CN34/CM34)*$N$10 -> 83958.521
A58: Påløpte investeringsutgifter | I58: 113990 | J58: 128928 | K58: 140826 | L58: 132408 | M58: 154043 | N58: 180511 | O58: 218980 | P58: 221804 | Q58: 201658 | R58: 164890.27 | S58: 152162.69 | T58: 158646.11 | U58: 186147.1 | V58: 180691.13 | W58: 185647.25 | X58: 187065.92 | Y58: 226738.46 | Z58: 262546.46 | AA58: 292760.33 | AB58: 282216.81 | AC58: 255067.26 | AD58: 237923.82 | AE58: 238655.66 | AF58: 236692 | AG58: 226631.98 | AH58: 221368.27 | AI58: 222651.9 | AJ58: 216033.17 | AK58: 209372.99 | AL58: 207078.43 | AM58: 208281.18 | AN58: 212270.36 | AO58: 212384.47 | AP58: 212290.33 | AQ58: 214218.1 | AR58: 214173.79 | AS58: 214093.96 | AT58: 211584.55 | AU58: 209977.88 | AV58: 207717.59 | AW58: 206169.03 | AX58: 204554.09 | AY58: 204623.89 | AZ58: 201114.29 | BA58: 195607.28 | BB58: 195274 | BC58: 194835.76 | BD58: 194661.72 | BE58: 192836.78 | BF58: 190452.67 | BG58: 187348.79 | BH58: 186573.94 | BI58: 183274.44 | BJ58: 181098.33 | BK58: =+BK57*KVARTS!BN15 -> 185643.9 | BL58: =+BL57*KVARTS!BO15 -> 190303.56 | BM58: =+BM57*KVARTS!BP15 -> 195080.18 | BN58: =+BN57*KVARTS!BQ15 -> 199976.7 | BO58: =+BO57*KVARTS!BR15 -> 204996.11 | BP58: =+BP57*KVARTS!BS15 -> 210141.51 | BQ58: =+BQ57*KVARTS!BT15 -> 215416.07 | BR58: =+BR57*KVARTS!BU15 -> 220823.01 | ... CN58: =+CN57*KVARTS!CQ15 -> 380979.37
A59: Samlede utgifter | I59: =SUM(I55:I58)-I57 -> 183746 | J59: =SUM(J55:J58)-J57 -> 209174 | K59: =SUM(K55:K58)-K57 -> 225466 | L59: =SUM(L55:L58)-L57 -> 219695 | M59: =SUM(M55:M58)-M57 -> 248009 | N59: =SUM(N55:N58)-N57 -> 282028 | O59: =SUM(O55:O58)-O57 -> 326921 | P59: =SUM(P55:P58)-P57 -> 332300 | ... CN59: =SUM(CN55:CN58)-CN57 -> 735534.65
N60: =+N58/N50 -> 0.26570811 | O60: =+O58/O50 -> 0.3370033 | P60: =+P58/P50 -> 0.35993993 | Q60: =+Q58/Q50 -> 0.40099622 | R60: =+R58/R50 -> 0.3952874 | S60: =+S58/S50 -> 0.30040123 | T60: =+T58/T50 -> 0.25272903 | U60: =+U58/U50 -> 0.3627037 | ... CN60: =+CN58/CN50 -> 0.54195686
A62: Sokkelens netto kontantstrøm | I62: =I50-I59 -> 335556.39 | J62: =J50-J59 -> 493175.62 | K62: =K50-K59 -> 268092.62 | L62: =L50-L59 -> 311502.39 | M62: =M50-M59 -> 392288.48 | N62: =N50-N59 -> 397330.26 | O62: =O50-O59 -> 322864.93 | P62: =P50-P59 -> 283925.05 | ... CN62: =CN50-CN59 -> -32564.732
A63: Sokkelens netto kontantstrøm i faste priser | I63: =I62/I44 -> 542244.1 | J63: =J62/J44 -> 767485.19 | K63: =K62/K44 -> 418697.27 | L63: =L62/L44 -> 478643.12 | M63: =M62/M44 -> 584329.68 | N63: =N62/N44 -> 579840.77 | O63: =O62/O44 -> 464368.16 | P63: =P62/P44 -> 401843.15 | ... CN63: =CN62/CN44 -> -9142.3914
A67: Statens netto kontantstrøm
A68: Løpende priser
A69: Påløpte skatter og avgifter | I69: =SNKS!B62 -> 0 | J69: =SNKS!C62 -> 0 | K69: =SNKS!D62 -> 0 | L69: =SNKS!E62 -> 0 | M69: =SNKS!F62 -> 0 | N69: =SNKS!G62 -> 0 | O69: =SNKS!H62 -> 0 | P69: =SNKS!I62 -> 154506 | ... BJ69: =SNKS!BC62 -> 58000 | BK69: =(BJ69/BJ74)*BK74 -> 56697.114 | BL69: =(BK69/BK74)*BL74 -> 55328.546 | BM69: =(BL69/BL74)*BM74 -> 53892.676 | BN69: =(BM69/BM74)*BN74 -> 52387.867 | BO69: =(BN69/BN74)*BO74 -> 50812.469 | BP69: =(BO69/BO74)*BP74 -> 49164.815 | BQ69: =(BP69/BP74)*BQ74 -> 47443.23 | BR69: =(BQ69/BQ74)*BR74 -> 45646.025 | ... CN69: =(CM69/CM74)*CN74 -> -16449.891
A70: Betalte skatter og avgifter | I70: =SNKS!B75 -> 0 | J70: =SNKS!C75 -> 0 | K70: =SNKS!D75 -> 0 | L70: =SNKS!E75 -> 0 | M70: =SNKS!F75 -> 0 | N70: =SNKS!G75 -> 0 | O70: =SNKS!H75 -> 0 | P70: =SNKS!I75 -> 176162.84 | ... BJ70: =SNKS!BC75 -> 60500 | BK70: =(BJ70/BJ74)*BK74 -> 59140.955 | BL70: =(BK70/BK74)*BL74 -> 57713.397 | BM70: =(BL70/BL74)*BM74 -> 56215.636 | BN70: =(BM70/BM74)*BN74 -> 54645.965 | BO70: =(BN70/BN74)*BO74 -> 53002.661 | BP70: =(BO70/BO74)*BP74 -> 51283.988 | BQ70: =(BP70/BP74)*BQ74 -> 49488.196 | BR70: =(BQ70/BQ74)*BR74 -> 47613.526 | ... CN70: =(CM70/CM74)*CN74 -> -17158.938
A71: Netto innbetaling SDØE | I71: =SNKS!B81 -> 0 | J71: =SNKS!C81 -> 0 | K71: =SNKS!D81 -> 0 | L71: =SNKS!E81 -> 0 | M71: =SNKS!F81 -> 0 | N71: =SNKS!G81 -> 0 | O71: =SNKS!H81 -> 0 | P71: =SNKS!I81 -> 112858.92 | ... BJ71: =SNKS!BC81 -> 10950.908 | BK71: =(BJ71/BJ74)*BK74 -> 10704.912 | BL71: =(BK71/BK74)*BL74 -> 10446.514 | BM71: =(BL71/BL74)*BM74 -> 10175.41 | BN71: =(BM71/BM74)*BN74 -> 9891.2885 | BO71: =(BN71/BN74)*BO74 -> 9593.8394 | BP71: =(BO71/BO74)*BP74 -> 9282.748 | BQ71: =(BP71/BP74)*BQ74 -> 8957.6976 | BR71: =(BQ71/BQ74)*BR74 -> 8618.3696 | ... CN71: =(CM71/CM74)*CN74 -> -3105.8836
A72: Aksjeutbytte Statoil | I72: =SNKS!B86 -> 14005.699 | J72: =SNKS!C86 -> 16940.158 | K72: =SNKS!D86 -> 15489 | L72: =SNKS!E86 -> 12818 | M72: =SNKS!F86 -> 13352.46 | N72: =SNKS!G86 -> 13886.558 | O72: =SNKS!H86 -> 14420.657 | P72: =SNKS!I86 -> 22646 | ... BJ72: =SNKS!BC86 -> 28584.732 | BK72: =(BJ72/BJ74)*BK74 -> 27942.617 | BL72: =(BK72/BK74)*BL74 -> 27268.132 | BM72: =(BL72/BL74)*BM74 -> 26560.477 | BN72: =(BM72/BM74)*BN74 -> 25818.847 | BO72: =(BN72/BN74)*BO74 -> 25042.427 | BP72: =(BO72/BO74)*BP74 -> 24230.397 | BQ72: =(BP72/BP74)*BQ74 -> 23381.931 | BR72: =(BQ72/BQ74)*BR74 -> 22496.196 | ... CN72: =(CM72/CM74)*CN74 -> -8107.1675
A73: Netto andre inntekter | I73: =SNKS!B96 -> -4.58 | J73: =SNKS!C96 -> 0 | K73: =SNKS!D96 -> 0 | L73: =SNKS!E96 -> -81.5 | M73: =SNKS!F96 -> -2 | N73: =SNKS!G96 -> -0.027193 | O73: =SNKS!H96 -> -1 | P73: =SNKS!I96 -> -2 | ... BJ73: =SNKS!BC96 -> 0
A74: SNKS | B74: 161374.7 | C74: 243292.09 | D74: 169531.32 | E74: 173996.92 | F74: 203530.11 | G74: 275558.76 | H74: 355377.37 | I74: 316389.39 | J74: 415866.28 | K74: 279793.9 | L74: 275957.5 | M74: 350801.04 | N74: 395483 | O74: 345152 | P74: =SUM(P70:P73) -> 311665.76 | Q74: =SUM(Q70:Q73) -> 218255.63 | R74: =SUM(R70:R73) -> 124778.65 | S74: =SUM(S70:S73) -> 167846.63 | T74: =SUM(T70:T73) -> 250958.8 | U74: =SUM(U70:U73) -> 256923.65 | V74: =SUM(V70:V73) -> 106824.49 | W74: =SUM(W70:W73) -> 287512.6 | ... BJ74: =SUM(BJ70:BJ73) -> 100035.64 | BK74: =(BK62*BK86) -> 97788.484 | BL74: =(BL62*BL86) -> 95428.043 | BM74: =(BM62*BM86) -> 92951.523 | BN74: =(BN62*BN86) -> 90356.101 | BO74: =(BO62*BO86) -> 87638.928 | BP74: =(BP62*BP86) -> 84797.133 | BQ74: =(BQ62*BQ86) -> 81827.825 | BR74: =(BR62*BR86) -> 78728.092 | ... CN74: =(CN62*CN86) -> -28371.989
A76: Kontroll | I76: =SNKS!B99-I74 -> -0.022 | J76: =SNKS!C99-J74 -> -0.15666281 | K76: =SNKS!D99-K74 -> 0 | L76: =SNKS!E99-L74 -> -0.141 | M76: =SNKS!F99-M74 -> 2.462 | N76: =SNKS!G99-N74 -> -0.23672833 | O76: =SNKS!H99-O74 -> -0.67017209 | P76: =SNKS!I99-P74 -> 0 | ... BJ76: =SNKS!BC99-BJ74 -> 0 | BK76: =Skiftberegning!BJ76 -> 0 | BL76: =Skiftberegning!BK76 -> 0 | BM76: =Skiftberegning!BL76 -> 0 | BN76: =Skiftberegning!BM76 -> 0 | BO76: =Skiftberegning!BN76 -> 0 | BP76: =Skiftberegning!BO76 -> 0 | BQ76: =Skiftberegning!BP76 -> 0 | BR76: =Skiftberegning!BQ76 -> 0 | ... CN76: =Skiftberegning!CM76 -> 0
A78: Faste priser
A79: Påløpte skatter og avgifter | I79: =I69/I$44 -> 0 | J79: =J69/J$44 -> 0 | K79: =K69/K$44 -> 0 | L79: =L69/L$44 -> 0 | M79: =M69/M$44 -> 0 | N79: =N69/N$44 -> 0 | O79: =O69/O$44 -> 0 | P79: =P69/P$44 -> 218674.54 | ... AF79: =AF69/AF$44 -> 134853.95
A80: Betalte skatter og avgifter | I80: =I70/I$44 -> 0 | J80: =J70/J$44 -> 0 | K80: =K70/K$44 -> 0 | L80: =L70/L$44 -> 0 | M80: =M70/M$44 -> 0 | N80: =N70/N$44 -> 0 | O80: =O70/O$44 -> 0 | P80: =P70/P$44 -> 249325.78 | ... CN80: =CN70/CN$44 -> -4817.2889
A81: Netto innbetaling SDØE | I81: =I71/I$44 -> 0 | J81: =J71/J$44 -> 0 | K81: =K71/K$44 -> 0 | L81: =L71/L$44 -> 0 | M81: =M71/M$44 -> 0 | N81: =N71/N$44 -> 0 | O81: =O71/O$44 -> 0 | P81: =P71/P$44 -> 159730.83 | ... CN81: =CN71/CN$44 -> -871.96182
A82: Aksjeutbytte Statoil | I82: =I72/I$44 -> 22632.583 | J82: =J72/J$44 -> 26362.455 | K82: =K72/K$44 -> 24190.155 | L82: =L72/L$44 -> 19695.667 | M82: =M72/M$44 -> 19889.034 | N82: =N72/N$44 -> 20265.239 | O82: =O72/O$44 -> 20740.852 | P82: =P72/P$44 -> 32051.206 | ... CN82: =CN72/CN$44 -> -2276.0481
A83: Netto andre inntekter | I83: =I73/I$44 -> -7.4010749 | J83: =J73/J$44 -> 0 | K83: =K73/K$44 -> 0 | L83: =L73/L$44 -> -125.2299 | M83: =M73/M$44 -> -2.9790816 | N83: =N73/N$44 -> -0.039683889 | O83: =O73/O$44 -> -1.4382738 | P83: =P73/P$44 -> -2.8306284 | ... CN83: =CN73/CN$44 -> 0
A84: SNKS | B84: =B74/B$44 -> 313992.86 | C84: =C74/C$44 -> 460371.74 | D84: =D74/D$44 -> 315788.72 | E84: =E74/E$44 -> 316912.65 | F84: =F74/F$44 -> 361037.66 | G84: =G74/G$44 -> 472767.91 | H84: =H74/H$44 -> 590656.08 | I84: =I74/I$44 -> 511271.09 | ... CN84: =CN74/CN$44 -> -7965.2989
P85: =AVERAGE(P86:V86) -> 0.86367391 | V85: =AVERAGE(V86:AZ86) -> 0.90606236
A86: Statens andel av sokkelens kontantstrøm | I86: =I74/I62 -> 0.94287996 | J86: =J74/J62 -> 0.84324177 | K86: =K74/K62 -> 1.0436464 | L86: =L74/L62 -> 0.88589208 | M86: =M74/M62 -> 0.89424252 | N86: =N74/N62 -> 0.99535081 | O86: =O74/O62 -> 1.0690291 | P86: =P74/P62 -> 1.0977044 | ... BJ86: =BJ74/BJ62 -> 1.171249 | BK86: =IF(BJ86-0.01>0.8,BJ86-0.01,0.8) -> 1.161249 | BL86: =IF(BK86-0.01>0.8,BK86-0.01,0.8) -> 1.151249 | BM86: =IF(BL86-0.01>0.8,BL86-0.01,0.8) -> 1.141249 | BN86: =IF(BM86-0.01>0.8,BM86-0.01,0.8) -> 1.131249 | BO86: =IF(BN86-0.01>0.8,BN86-0.01,0.8) -> 1.121249 | BP86: =IF(BO86-0.01>0.8,BO86-0.01,0.8) -> 1.111249 | BQ86: =IF(BP86-0.01>0.8,BP86-0.01,0.8) -> 1.101249 | BR86: =IF(BQ86-0.01>0.8,BQ86-0.01,0.8) -> 1.091249 | ... CN86: =IF(CM86-0.01>0.8,CM86-0.01,0.8) -> 0.87124895
I87: =SUM(I86:I86)/5 -> 0.18857599 | J87: =J70/J62 -> 0 | K87: =K70/K62 -> 0 | L87: =L70/L62 -> 0 | M87: =M70/M62 -> 0 | N87: =N70/N62 -> 0 | O87: =O70/O62 -> 0 | P87: =P70/P62 -> 0.62045545 | Q87: =Q70/Q62 -> 0.57456554 | ... BJ87: =BJ70/BJ62 -> 0.70835316
A88: Husk at skiftberegningen påvirker formuesanslagene | J88: =J71/J62 -> 0 | K88: =K71/K62 -> 0 | L88: =L71/L62 -> 0 | M88: =M71/M62 -> 0 | N88: =N71/N62 -> 0 | O88: =O71/O62 -> 0 | P88: =P71/P62 -> 0.39749545 | Q88: =Q71/Q62 -> 0.48359722 | ... BJ88: =BJ71/BJ62 -> 0.1282167
A89: Husk å oppdatere startår i formuesberegningen | K89: =AVERAGE(I86:K86) -> 0.94325605
A90: =IF(Skiftberegning!BT25=0,"Skiftberegning ikke i bruk","SKIFTBEREGNING I BRUK!") -> Skiftberegning ikke i bruk
A91: Startår: | M91: =M62*0.85 -> 333445.21 | N91: =N62*0.85 -> 337730.72 | O91: =O62*0.85 -> 274435.19 | P91: =P62*0.85 -> 241336.29 | Q91: =Q62*0.85 -> 162964.14 | R91: =R62*0.85 -> 128453.65 | S91: =S62*0.85 -> 241748.61 | T91: =T62*0.85 -> 331879.08 | ... BJ91: =BJ62*0.85 -> 72597.968
A92: Formlene oppdatert:
A93: FORMUESBEREGNINGER, MRD. 2025-KRONER
A94: Diskonteringsrente | B94: 0.03
A95: Petroleumsformuen (NV av sokkelens netto KS) | B95: =NPV($B$94,AA63:CN63)/1000 -> 5055.375
A96: Betalte skatter og avgifter | B96: =NPV($B$94,AA80:CN80)/1000 -> 2926.4931
A97: Netto innbetaling SDØE | B97: =NPV($B$94,AA81:CN81)/1000 -> 1404.3853
A98: Aksjeutbytte Statoil | B98: =NPV($B$94,AA82:CN82)/1000 -> 390.20258
A99: Netto andre inntekter | B99: =NPV($B$94,AA83:CN83)/1000 -> 0
A100: Statens del av formuen (SNKS) | B100: =NPV($B$94,AA84:CN84)/1000 -> 4721.081
A101: "Avkastningskrav" til formuen | B101: 0.03
A102: Permanentinntekt av petroleumsformuen | B102: =B95*B101 -> 151.66125
A103: Permanentinntekt av statens del av formuen | B103: =B100*B101 -> 141.63243
A107: SNKS, faste priser i mrd. kroner | P107: =P84/1000 -> 441.10498 | Q107: =Q84/1000 -> 308.53429 | R107: =R84/1000 -> 174.19415 | S107: =S84/1000 -> 229.431 | T107: =T84/1000 -> 334.85854 | U107: =U84/1000 -> 336.71555 | V107: =V84/1000 -> 138.29462 | W107: =W84/1000 -> 355.51141 | ... CN107: =CN84/1000 -> -7.9652989
A110: Hjelpeberegninger til Charts
A111: Påløpte driftsutgifter (faste priser) / Total produksjon | Y111: =(Y54/Y34) -> 428.31035 | Z111: =(Z54/Z34) -> 394.9349 | AA111: =(AA54/AA34) -> 411.9084 | AB111: =(AB54/AB34) -> 437.43237 | AC111: =(AC54/AC34) -> 448.22894 | AD111: =(AD54/AD34) -> 469.5521 | AE111: =(AE54/AE34) -> 492.90096 | AF111: =(AF54/AF34) -> 482.89258 | ... CN111: =(CN54/CN34) -> 1286.7898
A112: Påløpte investeringsutgifter (faste priser) / Total produksjon | Y112: =Y57/Y34 -> 880.88801 | Z112: =Z57/Z34 -> 926.59395 | AA112: =AA57/AA34 -> 1012.0385 | AB112: =AB57/AB34 -> 963.55698 | AC112: =AC57/AC34 -> 859.84493 | AD112: =AD57/AD34 -> 828.3751 | AE112: =AE57/AE34 -> 870.63439 | AF112: =AF57/AF34 -> 896.0628 | ... CN112: =CN57/CN34 -> 1382.6909

Sheet FAME Persistence2
A1: 27 | B1: SNKS
A2: KVARTS | B2: $C$219 | C2: A1:AA1 | D2: 506539.09 | E2: 45737.457 | F2: TRUE | G2: rnb25a13'X6667 | H2: 1998 | I2: 2024 | J2: 0 | K2: Annual | L2: TRUE | M2: FALSE | N2: FALSE
A3: KVARTS | B3: $C$227 | C3: A1:AA1 | D3: 0.9578125 | E3: 45737.457 | F3: TRUE | G3: rnb25a13'PA69 | H3: 1998 | I3: 2024 | J3: 0 | K3: Annual | L3: TRUE | M3: FALSE | N3: FALSE
A4: KVARTS | B4: $C$220 | C4: A1:AA1 | D4: 13625.811 | E4: 45737.457 | F4: TRUE | G4: rnb25a13'X6682 | H4: 1998 | I4: 2024 | J4: 0 | K4: Annual | L4: TRUE | M4: FALSE | N4: FALSE
A5: KVARTS | B5: $C$230 | C5: A1:AA1 | D5: 32911 | E5: 45737.457 | F5: TRUE | G5: rnb25a13'vh66+rnb25a13'vh68 | H5: 1998 | I5: 2024 | J5: 0 | K5: Annual | L5: TRUE | M5: FALSE | N5: FALSE
A6: KVARTS | B6: $C$217 | C6: A1:AA1 | D6: 37762.196 | E6: 45737.457 | F6: TRUE | G6: rnb25a13'X6631 | H6: 1998 | I6: 2024 | J6: 0 | K6: Annual | L6: TRUE | M6: FALSE | N6: FALSE
A7: KVARTS | B7: $C$218 | C7: A1:AA1 | D7: 978645.62 | E7: 45737.457 | F7: TRUE | G7: rnb25a13'X6666 | H7: 1998 | I7: 2024 | J7: 0 | K7: Annual | L7: TRUE | M7: FALSE | N7: FALSE
A8: Investments | B8: $C$125 | C8: A1:AC1 | D8: 785.67907 | E8: 45867.527 | F8: TRUE | G8: nb26b11'jk5068 | H8: 1996 | I8: 2024 | J8: 0 | K8: Annual | L8: TRUE | M8: FALSE | N8: FALSE
A9: Investments | B9: $C$113 | C9: A1:AC1 | D9: 7317.7961 | E9: 45867.527 | F9: TRUE | G9: nb26b11'jk7166 | H9: 1996 | I9: 2024 | J9: 0 | K9: Annual | L9: TRUE | M9: FALSE | N9: FALSE
A10: Investments | B10: $C$108 | C10: A1:AC1 | D10: 20722.593 | E10: 45867.527 | F10: TRUE | G10: nb26b11'jk2266 | H10: 1996 | I10: 2024 | J10: 0 | K10: Annual | L10: TRUE | M10: FALSE | N10: FALSE
A11: Investments | B11: $C$112 | C11: A1:AC1 | D11: 14658.744 | E11: 45867.527 | F11: TRUE | G11: nb26b11'jk7266 | H11: 1996 | I11: 2024 | J11: 0 | K11: Annual | L11: TRUE | M11: FALSE | N11: FALSE
A12: Investments | B12: $C$124 | C12: A1:AC1 | D12: 2.9084491 | E12: 45867.527 | F12: TRUE | G12: nb26b11'jk4068 | H12: 1996 | I12: 2024 | J12: 0 | K12: Annual | L12: TRUE | M12: FALSE | N12: FALSE
A13: Investments | B13: $C$128 | C13: A1:AC1 | D13: 52.005162 | E13: 45867.527 | F13: TRUE | G13: nb26b11'jk6068 | H13: 1996 | I13: 2024 | J13: 0 | K13: Annual | L13: TRUE | M13: FALSE | N13: FALSE
... A28: Investments | B28: $C$115 | C28: A1:AC1 | D28: 16321.268 | E28: 45867.527 | F28: TRUE | G28: nb26b11'jk7466 | H28: 1996 | I28: 2024 | J28: 0 | K28: Annual | L28: TRUE | M28: FALSE | N28: FALSE

Sheet Charts
A1: Charts 1
A4: Oil price, fixed 2026-prices, USD/barrel | B4: Remark: If necessary you must adjust to the same price year with inflation forecast to the respective rounds
B5: 2023 | C5: 2024 | D5: 2025 | E5: 2026 | F5: 2027 | G5: 2028 | H5: 2029 | I5: 2030 | J5: 2031 | K5: 2032 | L5: 2033 | M5: 2034 | N5: 2035 | O5: 2036 | P5: 2037 | Q5: 2038 | R5: 2039 | S5: 2040 | T5: 2041 | U5: 2042 | V5: 2043 | W5: 2044 | X5: 2045 | Y5: 2046 | Z5: 2047 | AA5: 2048 | AB5: 2049 | AC5: 2050 | AD5: 2051 | AE5: 2052 | AF5: 2053 | AG5: 2054 | AH5: 2055 | AI5: 2056 | AJ5: 2057 | AK5: 2058 | AL5: 2059 | AM5: 2060 | AN5: 2061 | AO5: 2062 | AP5: 2063 | AQ5: 2064 | AR5: 2065 | AS5: 2066 | AT5: 2067 | AU5: 2068 | AV5: 2069 | AW5: 2070 | AX5: 2071 | AY5: 2072 | AZ5: 2073 | BA5: 2074 | BB5: 2075 | BC5: 2076 | BD5: 2077 | BE5: 2078 | BF5: 2079 | BG5: 2080 | BH5: 2081 | BI5: 2082 | BJ5: 2083 | BK5: 2084 | BL5: 2085 | BM5: 2086 | BN5: 2087 | BO5: 2088 | BP5: 2089 | BQ5: 2090
A6: NB26 | B6: =KVARTS!AB31 -> 90.251069 | C6: =KVARTS!AC31 -> 85.047828 | D6: =KVARTS!AD31 -> 71.7493 | E6: =KVARTS!AE31 -> 66.6925 | F6: =KVARTS!AF31 -> 65.269344 | G6: =KVARTS!AG31 -> 64.285812 | H6: =KVARTS!AH31 -> 63.252491 | I6: =KVARTS!AI31 -> 62.052929 | ... BQ6: =KVARTS!CQ31 -> 70.428062
A7: RNB25 | B7: 88.513502 | C7: 83.449414 | D7: 72.094609 | E7: 66.9275 | F7: 65.004897 | G7: 63.80457 | H7: 62.713812 | I7: 61.755096 | J7: 63.217986 | K7: 64.680876 | L7: 66.143766 | M7: 67.606656 | N7: 69.072152 | O7: 69.072152 | P7: 69.072152 | Q7: 69.072152 | R7: 69.072152 | S7: 69.072152 | T7: 69.072152 | U7: 69.072152 | V7: 69.072152 | W7: 69.072152 | X7: 69.072152 | Y7: 69.072152 | Z7: 69.072152 | AA7: 69.072152 | AB7: 69.072152 | AC7: 69.072152 | AD7: 69.072152 | AE7: 69.072152 | AF7: 69.072152 | AG7: 69.072152 | AH7: 69.072152 | AI7: 69.072152 | AJ7: 69.072152 | AK7: 69.072152 | AL7: 69.072152 | AM7: 69.072152 | AN7: 69.072152 | AO7: 69.072152 | AP7: 69.072152 | AQ7: 69.072152 | AR7: 69.072152 | AS7: 69.072152 | AT7: 69.072152 | AU7: 69.072152 | AV7: 69.072152 | AW7: 69.072152 | AX7: 69.072152 | AY7: 69.072152 | AZ7: 69.072152 | BA7: 69.072152 | BB7: 69.072152 | BC7: 69.072152 | BD7: 69.072152 | BE7: 69.072152 | BF7: 69.072152 | BG7: 69.072152 | BH7: 69.072152 | BI7: 69.072152 | BJ7: 69.072152 | BK7: 69.072152 | BL7: 69.072152 | BM7: 69.072152 | BN7: 69.072152 | BO7: 69.072152 | BP7: 69.072152 | BQ7: 69.072152
A9: Difference (Last round) | B9: =B6-B7 -> 1.7375669 | C9: =C6-C7 -> 1.5984142 | D9: =D6-D7 -> -0.34530905 | E9: =E6-E7 -> -0.235 | F9: =F6-F7 -> 0.26444662 | G9: =G6-G7 -> 0.48124226 | H9: =H6-H7 -> 0.5386789 | I9: =I6-I7 -> 0.29783318 | ... BQ9: =BQ6-BQ7 -> 1.3559098
A48: Oil price, fixed 2026-prices, NOK/fat | B48: Remark: If necessary you must adjust to the same price year with inflation forecast to the respective rounds
B49: 2023 | C49: 2024 | D49: 2025 | E49: 2026 | F49: 2027 | G49: 2028 | H49: 2029 | I49: 2030 | J49: 2031 | K49: 2032 | L49: 2033 | M49: 2034 | N49: 2035 | O49: 2036 | P49: 2037 | Q49: 2038 | R49: 2039 | S49: 2040 | T49: 2041 | U49: 2042 | V49: 2043 | W49: 2044 | X49: 2045 | Y49: 2046 | Z49: 2047 | AA49: 2048 | AB49: 2049 | AC49: 2050 | AD49: 2051 | AE49: 2052 | AF49: 2053 | AG49: 2054 | AH49: 2055 | AI49: 2056 | AJ49: 2057 | AK49: 2058 | AL49: 2059 | AM49: 2060 | AN49: 2061 | AO49: 2062 | AP49: 2063 | AQ49: 2064 | AR49: 2065 | AS49: 2066 | AT49: 2067 | AU49: 2068 | AV49: 2069 | AW49: 2070 | AX49: 2071 | AY49: 2072 | AZ49: 2073 | BA49: 2074 | BB49: 2075 | BC49: 2076 | BD49: 2077 | BE49: 2078 | BF49: 2079 | BG49: 2080 | BH49: 2081 | BI49: 2082 | BJ49: 2083 | BK49: 2084 | BL49: 2085 | BM49: 2086 | BN49: 2087 | BO49: 2088 | BP49: 2089 | BQ49: 2090
A50: NB26 | B50: =KVARTS!AB24 -> 953.37084 | C50: =KVARTS!AC24 -> 914.3073 | D50: =KVARTS!AD24 -> 746.45804 | E50: =KVARTS!AE24 -> 674.49527 | F50: =KVARTS!AF24 -> 660.10216 | G50: =KVARTS!AG24 -> 650.15521 | H50: =KVARTS!AH24 -> 639.7047 | I50: =KVARTS!AI24 -> 627.57292 | ... BQ50: =KVARTS!CQ24 -> 712.27491
A51: RNB25 | B51: 941.41394 | C51: 903.26221 | D51: 793.05191 | E51: 731.55542 | F51: 710.54028 | G51: 697.42003 | H51: 685.49742 | I51: 675.01812 | J51: 691.00833 | K51: 706.99855 | L51: 722.98876 | M51: 738.97898 | N51: 754.99768 | O51: 754.99768 | P51: 754.99768 | Q51: 754.99768 | R51: 754.99768 | S51: 754.99768 | T51: 754.99768 | U51: 754.99768 | V51: 754.99768 | W51: 754.99768 | X51: 754.99768 | Y51: 754.99768 | Z51: 754.99768 | AA51: 754.99768 | AB51: 754.99768 | AC51: 754.99768 | AD51: 754.99768 | AE51: 754.99768 | AF51: 754.99768 | AG51: 754.99768 | AH51: 754.99768 | AI51: 754.99768 | AJ51: 754.99768 | AK51: 754.99768 | AL51: 754.99768 | AM51: 754.99768 | AN51: 754.99768 | AO51: 754.99768 | AP51: 754.99768 | AQ51: 754.99768 | AR51: 754.99768 | AS51: 754.99768 | AT51: 754.99768 | AU51: 754.99768 | AV51: 754.99768 | AW51: 754.99768 | AX51: 754.99768 | AY51: 754.99768 | AZ51: 754.99768 | BA51: 754.99768 | BB51: 754.99768 | BC51: 754.99768 | BD51: 754.99768 | BE51: 754.99768 | BF51: 754.99768 | BG51: 754.99768 | BH51: 754.99768 | BI51: 754.99768 | BJ51: 754.99768 | BK51: 754.99768 | BL51: 754.99768 | BM51: 754.99768 | BN51: 754.99768 | BO51: 754.99768 | BP51: 754.99768 | BQ51: 754.99768
A53: Difference (Last round) | B53: =B50-B51 -> 11.9569 | C53: =C50-C51 -> 11.045088 | D53: =D50-D51 -> -46.593864 | E53: =E50-E51 -> -57.06015 | F53: =F50-F51 -> -50.438118 | G53: =G50-G51 -> -47.26482 | H53: =H50-H51 -> -45.792724 | I53: =I50-I51 -> -47.445196 | ... BQ53: =BQ50-BQ51 -> -42.722767
A90: Gas price, Fixed 2026-prices, NOK/Sm3 | B90: Remark: If necessary you must adjust to the same price year with inflation forecast to the respective rounds
B91: 2023 | C91: 2024 | D91: 2025 | E91: 2026 | F91: 2027 | G91: 2028 | H91: 2029 | I91: 2030 | J91: 2031 | K91: 2032 | L91: 2033 | M91: 2034 | N91: 2035 | O91: 2036 | P91: 2037 | Q91: 2038 | R91: 2039 | S91: 2040 | T91: 2041 | U91: 2042 | V91: 2043 | W91: 2044 | X91: 2045 | Y91: 2046 | Z91: 2047 | AA91: 2048 | AB91: 2049 | AC91: 2050 | AD91: 2051 | AE91: 2052 | AF91: 2053 | AG91: 2054 | AH91: 2055 | AI91: 2056 | AJ91: 2057 | AK91: 2058 | AL91: 2059 | AM91: 2060 | AN91: 2061 | AO91: 2062 | AP91: 2063 | AQ91: 2064 | AR91: 2065 | AS91: 2066 | AT91: 2067 | AU91: 2068 | AV91: 2069 | AW91: 2070 | AX91: 2071 | AY91: 2072 | AZ91: 2073 | BA91: 2074 | BB91: 2075 | BC91: 2076 | BD91: 2077 | BE91: 2078 | BF91: 2079 | BG91: 2080 | BH91: 2081 | BI91: 2082 | BJ91: 2083 | BK91: 2084 | BL91: 2085 | BM91: 2086 | BN91: 2087 | BO91: 2088 | BP91: 2089 | BQ91: 2090
A92: NB26 | B92: =KVARTS!AB25 -> 5.9850571 | C92: =KVARTS!AC25 -> 4.727289 | D92: =KVARTS!AD25 -> 5.3241062 | E92: =KVARTS!AE25 -> 3.9871306 | F92: =KVARTS!AF25 -> 3.1820369 | G92: =KVARTS!AG25 -> 3.1820369 | H92: =KVARTS!AH25 -> 3.1820369 | I92: =KVARTS!AI25 -> 2.5294211 | ... BQ92: =KVARTS!CQ25 -> 2.1921649
A93: RNB25 | B93: 5.8698293 | C93: 4.6275677 | D93: 5.5078414 | E93: 4.2099979 | F93: 3.3679983 | G93: 3.3679983 | H93: 3.3679983 | I93: 2.6629158 | J93: 2.6274087 | K93: 2.5919015 | L93: 2.5563944 | M93: 2.5208873 | N93: 2.4853802 | O93: 2.4498731 | P93: 2.4143659 | Q93: 2.3788588 | R93: 2.3433517 | S93: 2.3078604 | T93: 2.3078604 | U93: 2.3078604 | V93: 2.3078604 | W93: 2.3078604 | X93: 2.3078604 | Y93: 2.3078604 | Z93: 2.3078604 | AA93: 2.3078604 | AB93: 2.3078604 | AC93: 2.3078604 | AD93: 2.3078604 | AE93: 2.3078604 | AF93: 2.3078604 | AG93: 2.3078604 | AH93: 2.3078604 | AI93: 2.3078604 | AJ93: 2.3078604 | AK93: 2.3078604 | AL93: 2.3078604 | AM93: 2.3078604 | AN93: 2.3078604 | AO93: 2.3078604 | AP93: 2.3078604 | AQ93: 2.3078604 | AR93: 2.3078604 | AS93: 2.3078604 | AT93: 2.3078604 | AU93: 2.3078604 | AV93: 2.3078604 | AW93: 2.3078604 | AX93: 2.3078604 | AY93: 2.3078604 | AZ93: 2.3078604 | BA93: 2.3078604 | BB93: 2.3078604 | BC93: 2.3078604 | BD93: 2.3078604 | BE93: 2.3078604 | BF93: 2.3078604 | BG93: 2.3078604 | BH93: 2.3078604 | BI93: 2.3078604 | BJ93: 2.3078604 | BK93: 2.3078604 | BL93: 2.3078604 | BM93: 2.3078604 | BN93: 2.3078604 | BO93: 2.3078604 | BP93: 2.3078604 | BQ93: 2.3078604
A95: Difference (Last round) | B95: =B92-B93 -> 0.11522785 | C95: =C92-C93 -> 0.099721347 | D95: =D92-D93 -> -0.18373519 | E95: =E92-E93 -> -0.22286734 | F95: =F92-F93 -> -0.18596143 | G95: =G92-G93 -> -0.18596143 | H95: =H92-H93 -> -0.18596143 | I95: =I92-I93 -> -0.1334947 | ... BQ95: =BQ92-BQ93 -> -0.11569541
A132: Gas price, Fixed 2026-prices, USD/Mmbtu | C132: Remark: If necessary you must adjust to the same price year with inflation forecast to the respective rounds
B133: 2023 | C133: 2024 | D133: 2025 | E133: 2026 | F133: 2027 | G133: 2028 | H133: 2029 | I133: 2030 | J133: 2031 | K133: 2032 | L133: 2033 | M133: 2034 | N133: 2035 | O133: 2036 | P133: 2037 | Q133: 2038 | R133: 2039 | S133: 2040 | T133: 2041 | U133: 2042 | V133: 2043 | W133: 2044 | X133: 2045 | Y133: 2046 | Z133: 2047 | AA133: 2048 | AB133: 2049 | AC133: 2050 | AD133: 2051 | AE133: 2052 | AF133: 2053 | AG133: 2054 | AH133: 2055 | AI133: 2056 | AJ133: 2057 | AK133: 2058 | AL133: 2059 | AM133: 2060 | AN133: 2061 | AO133: 2062 | AP133: 2063 | AQ133: 2064 | AR133: 2065 | AS133: 2066 | AT133: 2067 | AU133: 2068 | AV133: 2069 | AW133: 2070 | AX133: 2071 | AY133: 2072 | AZ133: 2073 | BA133: 2074 | BB133: 2075 | BC133: 2076 | BD133: 2077 | BE133: 2078 | BF133: 2079 | BG133: 2080 | BH133: 2081 | BI133: 2082 | BJ133: 2083 | BK133: 2084 | BL133: 2085 | BM133: 2086 | BN133: 2087 | BO133: 2088 | BP133: 2089 | BQ133: 2090
A134: NB26 | B134: =KVARTS!AB27 -> 14.946296 | C134: =KVARTS!AC27 -> 11.6 | D134: =KVARTS!AD27 -> 13.5 | E134: =KVARTS!AE27 -> 10.4 | F134: =KVARTS!AF27 -> 8.3 | G134: =KVARTS!AG27 -> 8.3 | H134: =KVARTS!AH27 -> 8.3 | I134: =KVARTS!AI27 -> 6.5977221 | ... BQ134: =KVARTS!CQ27 -> 5.7180258
A135: RNB25 | B135: 14.658541 | C135: 11.3553 | D135: 13.299 | E135: 10.23 | F135: 8.184 | G135: 8.184 | H135: 8.184 | I135: 6.4706989 | J135: 6.384419 | K135: 6.2981392 | L135: 6.2118594 | M135: 6.1255796 | N135: 6.0392998 | O135: 5.9530199 | P135: 5.8667401 | Q135: 5.7804603 | R135: 5.6941805 | S135: 5.607939 | T135: 5.607939 | U135: 5.607939 | V135: 5.607939 | W135: 5.607939 | X135: 5.607939 | Y135: 5.607939 | Z135: 5.607939 | AA135: 5.607939 | AB135: 5.607939 | AC135: 5.607939 | AD135: 5.607939 | AE135: 5.607939 | AF135: 5.607939 | AG135: 5.607939 | AH135: 5.607939 | AI135: 5.607939 | AJ135: 5.607939 | AK135: 5.607939 | AL135: 5.607939 | AM135: 5.607939 | AN135: 5.607939 | AO135: 5.607939 | AP135: 5.607939 | AQ135: 5.607939 | AR135: 5.607939 | AS135: 5.607939 | AT135: 5.607939 | AU135: 5.607939 | AV135: 5.607939 | AW135: 5.607939 | AX135: 5.607939 | AY135: 5.607939 | AZ135: 5.607939 | BA135: 5.607939 | BB135: 5.607939 | BC135: 5.607939 | BD135: 5.607939 | BE135: 5.607939 | BF135: 5.607939 | BG135: 5.607939 | BH135: 5.607939 | BI135: 5.607939 | BJ135: 5.607939 | BK135: 5.607939 | BL135: 5.607939 | BM135: 5.607939 | BN135: 5.607939 | BO135: 5.607939 | BP135: 5.607939 | BQ135: 5.607939
A137: Difference (Last round) | B137: =B134-B135 -> 0.28775492 | C137: =C134-C135 -> 0.2447 | D137: =D134-D135 -> 0.201 | E137: =E134-E135 -> 0.17 | F137: =F134-F135 -> 0.116 | G137: =G134-G135 -> 0.116 | H137: =H134-H135 -> 0.116 | I137: =I134-I135 -> 0.12702324 | ... BQ137: =BQ134-BQ135 -> 0.11008681
A174: Oljeproduksjon, Mill. Sm3
B175: 2023 | C175: 2024 | D175: 2025 | E175: 2026 | F175: 2027 | G175: 2028 | H175: 2029 | I175: 2030 | J175: 2031 | K175: 2032 | L175: 2033 | M175: 2034 | N175: 2035 | O175: 2036 | P175: 2037 | Q175: 2038 | R175: 2039 | S175: 2040 | T175: 2041 | U175: 2042 | V175: 2043 | W175: 2044 | X175: 2045 | Y175: 2046 | Z175: 2047 | AA175: 2048 | AB175: 2049 | AC175: 2050 | AD175: 2051 | AE175: 2052 | AF175: 2053 | AG175: 2054 | AH175: 2055 | AI175: 2056 | AJ175: 2057 | AK175: 2058 | AL175: 2059 | AM175: 2060 | AN175: 2061 | AO175: 2062 | AP175: 2063 | AQ175: 2064 | AR175: 2065 | AS175: 2066 | AT175: 2067 | AU175: 2068 | AV175: 2069 | AW175: 2070 | AX175: 2071 | AY175: 2072 | AZ175: 2073 | BA175: 2074 | BB175: 2075 | BC175: 2076 | BD175: 2077 | BE175: 2078 | BF175: 2079 | BG175: 2080 | BH175: 2081 | BI175: 2082 | BJ175: 2083 | BK175: 2084 | BL175: 2085 | BM175: 2086 | BN175: 2087 | BO175: 2088 | BP175: 2089 | BQ175: 2090
A176: NB26 | B176: =Formue!Y30 -> 104.14 | C176: =Formue!Z30 -> 102.88638 | D176: =Formue!AA30 -> 105.18981 | E176: =Formue!AB30 -> 101.04576 | F176: =Formue!AC30 -> 96.575067 | G176: =Formue!AD30 -> 87.047892 | H176: =Formue!AE30 -> 78.845848 | I176: =Formue!AF30 -> 73.793909 | ... BQ176: =Formue!CN30 -> 28.071747
A177: RNB25 | B177: 104.14 | C177: 102.88638 | D177: 102.11998 | E177: 101.04576 | F177: 96.575064 | G177: 88.011194 | H177: 81.293875 | I177: 74.535615 | J177: 71.590373 | K177: 70.337783 | L177: 69.335954 | M177: 69.522144 | N177: 69.113465 | O177: 67.986585 | P177: 66.541979 | Q177: 64.040919 | R177: 61.863724 | S177: 59.860188 | T177: 58.254401 | U177: 56.377547 | V177: 54.637706 | W177: 53.278434 | X177: 51.453299 | Y177: 49.879178 | Z177: 48.095979 | AA177: 46.808533 | AB177: 45.039013 | AC177: 43.377474 | AD177: 42.037654 | AE177: 40.516117 | AF177: 39.141343 | AG177: 37.644951 | AH177: 36.054577 | AI177: 34.609854 | AJ177: 33.132616 | AK177: 31.356611 | AL177: 29.729547 | AM177: 28.071744 | AN177: 28.071744 | AO177: 28.071744 | AP177: 28.071744 | AQ177: 28.071744 | AR177: 28.071744 | AS177: 28.071744 | AT177: 28.071744 | AU177: 28.071744 | AV177: 28.071744 | AW177: 28.071744 | AX177: 28.071744 | AY177: 28.071744 | AZ177: 28.071744 | BA177: 28.071744 | BB177: 28.071744 | BC177: 28.071744 | BD177: 28.071744 | BE177: 28.071744 | BF177: 28.071744 | BG177: 28.071744 | BH177: 28.071744 | BI177: 28.071744 | BJ177: 28.071744 | BK177: 28.071744 | BL177: 28.071744 | BM177: 28.071744 | BN177: 28.071744 | BO177: 28.071744 | BP177: 28.071744 | BQ177: 28.071744
A179: Difference (Last round) | B179: =B176-B177 -> 0 | C179: =C176-C177 -> -1.18278e-07 | D179: =D176-D177 -> 3.0698292 | E179: =E176-E177 -> -1.057982e-06 | F179: =F176-F177 -> 2.9196963e-06 | G179: =G176-G177 -> -0.96330234 | H179: =H176-H177 -> -2.4480273 | I179: =I176-I177 -> -0.74170699 | ... BQ179: =BQ176-BQ177 -> 3.3378601e-06
A220: Gassproduksjon, Mill. Sm3
B221: 2023 | C221: 2024 | D221: 2025 | E221: 2026 | F221: 2027 | G221: 2028 | H221: 2029 | I221: 2030 | J221: 2031 | K221: 2032 | L221: 2033 | M221: 2034 | N221: 2035 | O221: 2036 | P221: 2037 | Q221: 2038 | R221: 2039 | S221: 2040 | T221: 2041 | U221: 2042 | V221: 2043 | W221: 2044 | X221: 2045 | Y221: 2046 | Z221: 2047 | AA221: 2048 | AB221: 2049 | AC221: 2050 | AD221: 2051 | AE221: 2052 | AF221: 2053 | AG221: 2054 | AH221: 2055 | AI221: 2056 | AJ221: 2057 | AK221: 2058 | AL221: 2059 | AM221: 2060 | AN221: 2061 | AO221: 2062 | AP221: 2063 | AQ221: 2064 | AR221: 2065 | AS221: 2066 | AT221: 2067 | AU221: 2068 | AV221: 2069 | AW221: 2070 | AX221: 2071 | AY221: 2072 | AZ221: 2073 | BA221: 2074 | BB221: 2075 | BC221: 2076 | BD221: 2077 | BE221: 2078 | BF221: 2079 | BG221: 2080 | BH221: 2081 | BI221: 2082 | BJ221: 2083 | BK221: 2084 | BL221: 2085 | BM221: 2086 | BN221: 2087 | BO221: 2088 | BP221: 2089 | BQ221: 2090
A222: NB26 | B222: =Formue!Y31 -> 116.02 | C222: =Formue!Z31 -> 124.23875 | D222: =Formue!AA31 -> 118.45207 | E222: =Formue!AB31 -> 120.08612 | F222: =Formue!AC31 -> 120.09464 | G222: =Formue!AD31 -> 116.16609 | H222: =Formue!AE31 -> 110.63627 | I222: =Formue!AF31 -> 104.94158 | ... BQ222: =Formue!CN31 -> 32.602377
A223: RNB25 | B223: 116.02 | C223: 124.23875 | D223: 118.45207 | E223: 120.08612 | F223: 120.09464 | G223: 116.17451 | H223: 110.84279 | I223: 105.10805 | J223: 100.25048 | K223: 93.712644 | L223: 89.882529 | M223: 87.325906 | N223: 84.944702 | O223: 82.731056 | P223: 79.326078 | Q223: 74.342349 | R223: 68.974317 | S223: 65.057322 | T223: 61.493752 | U223: 58.826604 | V223: 56.042452 | W223: 52.927936 | X223: 50.397369 | Y223: 48.438268 | Z223: 46.51669 | AA223: 44.752986 | AB223: 43.317955 | AC223: 41.66783 | AD223: 40.118687 | AE223: 38.369956 | AF223: 36.90352 | AG223: 35.812746 | AH223: 35.209137 | AI223: 34.416167 | AJ223: 33.891616 | AK223: 33.466272 | AL223: 32.995543 | AM223: 32.602375 | AN223: 32.602375 | AO223: 32.602375 | AP223: 32.602375 | AQ223: 32.602375 | AR223: 32.602375 | AS223: 32.602375 | AT223: 32.602375 | AU223: 32.602375 | AV223: 32.602375 | AW223: 32.602375 | AX223: 32.602375 | AY223: 32.602375 | AZ223: 32.602375 | BA223: 32.602375 | BB223: 32.602375 | BC223: 32.602375 | BD223: 32.602375 | BE223: 32.602375 | BF223: 32.602375 | BG223: 32.602375 | BH223: 32.602375 | BI223: 32.602375 | BJ223: 32.602375 | BK223: 32.602375 | BL223: 32.602375 | BM223: 32.602375 | BN223: 32.602375 | BO223: 32.602375 | BP223: 32.602375 | BQ223: 32.602375
A225: Difference (Last round) | B225: =B222-B223 -> 0 | C225: =C222-C223 -> 9.3199048e-10 | D225: =D222-D223 -> -2.0721004e-08 | E225: =E222-E223 -> 0 | F225: =F222-F223 -> 2.4564002e-08 | G225: =G222-G223 -> -0.0084185278 | H225: =H222-H223 -> -0.20651588 | I225: =I222-I223 -> -0.16647177 | ... BQ225: =BQ222-BQ223 -> 2.399087e-06
A258: Total production, Mill. Sm3
B259: 2023 | C259: 2024 | D259: 2025 | E259: 2026 | F259: 2027 | G259: 2028 | H259: 2029 | I259: 2030 | J259: 2031 | K259: 2032 | L259: 2033 | M259: 2034 | N259: 2035 | O259: 2036 | P259: 2037 | Q259: 2038 | R259: 2039 | S259: 2040 | T259: 2041 | U259: 2042 | V259: 2043 | W259: 2044 | X259: 2045 | Y259: 2046 | Z259: 2047 | AA259: 2048 | AB259: 2049 | AC259: 2050 | AD259: 2051 | AE259: 2052 | AF259: 2053 | AG259: 2054 | AH259: 2055 | AI259: 2056 | AJ259: 2057 | AK259: 2058 | AL259: 2059 | AM259: 2060 | AN259: 2061 | AO259: 2062 | AP259: 2063 | AQ259: 2064 | AR259: 2065 | AS259: 2066 | AT259: 2067 | AU259: 2068 | AV259: 2069 | AW259: 2070 | AX259: 2071 | AY259: 2072 | AZ259: 2073 | BA259: 2074 | BB259: 2075 | BC259: 2076 | BD259: 2077 | BE259: 2078 | BF259: 2079 | BG259: 2080 | BH259: 2081 | BI259: 2082 | BJ259: 2083 | BK259: 2084 | BL259: 2085 | BM259: 2086 | BN259: 2087 | BO259: 2088 | BP259: 2089 | BQ259: 2090
A260: NB26 | B260: =Formue!Y34 -> 233.15 | C260: =Formue!Z34 -> 241.21594 | D260: =Formue!AA34 -> 238.1683 | E260: =Formue!AB34 -> 236.41448 | F260: =Formue!AC34 -> 232.08664 | G260: =Formue!AD34 -> 218.5957 | H260: =Formue!AE34 -> 204.60595 | I260: =Formue!AF34 -> 193.19365 | ... BQ260: =Formue!CN34 -> 60.721106
A261: RNB25 | B261: 233.15 | C261: 241.21594 | D261: 235.09847 | E261: 236.41448 | F261: 232.08664 | G261: 219.56742 | H261: 207.2713 | I261: 194.1625 | J261: 184.72425 | K261: 176.03771 | L261: 169.8095 | M261: 166.3155 | N261: 162.32209 | O261: 158.19374 | P261: 152.28294 | Q261: 143.85731 | R261: 135.68329 | S261: 129.30531 | T261: 123.62345 | U261: 118.69145 | V261: 113.81862 | W261: 108.93703 | X261: 104.31182 | Y261: 100.3564 | Z261: 96.522386 | AA261: 93.032913 | AB261: 89.49957 | AC261: 85.996999 | AD261: 82.934551 | AE261: 79.418004 | AF261: 76.468289 | AG261: 73.762389 | AH261: 71.47239 | AI261: 69.165997 | AJ261: 67.10118 | AK261: 64.895405 | AL261: 62.79266 | AM261: 60.7211 | AN261: 60.7211 | AO261: 60.7211 | AP261: 60.7211 | AQ261: 60.7211 | AR261: 60.7211 | AS261: 60.7211 | AT261: 60.7211 | AU261: 60.7211 | AV261: 60.7211 | AW261: 60.7211 | AX261: 60.7211 | AY261: 60.7211 | AZ261: 60.7211 | BA261: 60.7211 | BB261: 60.7211 | BC261: 60.7211 | BD261: 60.7211 | BE261: 60.7211 | BF261: 60.7211 | BG261: 60.7211 | BH261: 60.7211 | BI261: 60.7211 | BJ261: 60.7211 | BK261: 60.7211 | BL261: 60.7211 | BM261: 60.7211 | BN261: 60.7211 | BO261: 60.7211 | BP261: 60.7211 | BQ261: 60.7211
A263: Difference (Last round) | B263: =B260-B261 -> 0 | C263: =C260-C261 -> -1.1967433e-07 | D263: =D260-D261 -> 3.0698292 | E263: =E260-E261 -> -1.1658408e-06 | F263: =F260-F261 -> 2.9984371e-06 | G263: =G260-G261 -> -0.9717209 | H263: =H260-H261 -> -2.6653581 | I263: =I260-I261 -> -0.96884384 | ... BQ263: =BQ260-BQ261 -> 5.7443977e-06
A300: Driftskostnader, Faste | C300: MERK: Husk å justere slik at det brukes samme fastprisår mellom rundene
B303: 2023 | C303: 2024 | D303: 2025 | E303: 2026 | F303: 2027 | G303: 2028 | H303: 2029 | I303: 2030 | J303: 2031 | K303: 2032 | L303: 2033 | M303: 2034 | N303: 2035 | O303: 2036 | P303: 2037 | Q303: 2038 | R303: 2039 | S303: 2040 | T303: 2041 | U303: 2042 | V303: 2043 | W303: 2044 | X303: 2045 | Y303: 2046 | Z303: 2047 | AA303: 2048 | AB303: 2049 | AC303: 2050 | AD303: 2051 | AE303: 2052 | AF303: 2053 | AG303: 2054 | AH303: 2055 | AI303: 2056 | AJ303: 2057 | AK303: 2058 | AL303: 2059 | AM303: 2060 | AN303: 2061 | AO303: 2062 | AP303: 2063 | AQ303: 2064 | AR303: 2065 | AS303: 2066 | AT303: 2067 | AU303: 2068 | AV303: 2069 | AW303: 2070 | AX303: 2071 | AY303: 2072 | AZ303: 2073 | BA303: 2074 | BB303: 2075 | BC303: 2076 | BD303: 2077 | BE303: 2078 | BF303: 2079 | BG303: 2080 | BH303: 2081 | BI303: 2082 | BJ303: 2083 | BK303: 2084 | BL303: 2085 | BM303: 2086 | BN303: 2087 | BO303: 2088 | BP303: 2089 | BQ303: 2090
A304: NB26 | B304: =Formue!Y54 -> 99860.558 | C304: =Formue!Z54 -> 95264.594 | D304: =Formue!AA54 -> 98103.523 | E304: =Formue!AB54 -> 103415.35 | F304: =Formue!AC54 -> 104027.95 | G304: =Formue!AD54 -> 102642.07 | H304: =Formue!AE54 -> 100850.47 | I304: =Formue!AF54 -> 93291.78 | ... BQ304: =Formue!CN54 -> 78135.298
A305: RNB25 | B305: 99860.558 | C305: 95356.63 | D305: 99716.099 | E305: 101512.93 | F305: 100690.39 | G305: 100437.26 | H305: 99559.927 | I305: 94480.78 | J305: 94354.159 | K305: 95197.202 | L305: 94954.627 | M305: 94414.368 | N305: 93300.974 | O305: 89539.903 | P305: 87623.915 | Q305: 85987.708 | R305: 82544.063 | S305: 81288.821 | T305: 80347.38 | U305: 79565.621 | V305: 77935.711 | W305: 76778.036 | X305: 76359.865 | Y305: 73547.473 | Z305: 74126.289 | AA305: 71378.004 | AB305: 69110.584 | AC305: 65456.627 | AD305: 63517.914 | AE305: 61565.759 | AF305: 61076.438 | AG305: 61061.42 | AH305: 58300.091 | AI305: 53153.041 | AJ305: 52367.753 | AK305: 51816.37 | AL305: 49879.628 | AM305: 48857.104 | AN305: 49638.818 | AO305: 50433.039 | AP305: 51239.968 | AQ305: 52059.807 | AR305: 52892.764 | AS305: 53739.048 | AT305: 54598.873 | AU305: 55472.455 | AV305: 56360.014 | AW305: 57261.774 | AX305: 58177.963 | AY305: 59108.81 | AZ305: 60054.551 | BA305: 61015.424 | BB305: 61991.671 | BC305: 62983.538 | BD305: 63991.274 | BE305: 65015.135 | BF305: 66055.377 | BG305: 67112.263 | BH305: 68186.059 | BI305: 69277.036 | BJ305: 70385.468 | BK305: 71511.636 | BL305: 72655.822 | BM305: 73818.315 | BN305: 74999.408 | BO305: 76199.399 | BP305: 77418.589 | BQ305: 78657.287
A307: Difference (Last round) | B307: =B304-B305 -> 0 | C307: =C304-C305 -> -92.035037 | D307: =D304-D305 -> -1612.5755 | E307: =E304-E305 -> 1902.4156 | F307: =F304-F305 -> 3337.5593 | G307: =G304-G305 -> 2204.8111 | H307: =H304-H305 -> 1290.5412 | I307: =I304-I305 -> -1188.9998 | ... BQ307: =BQ304-BQ305 -> -521.98827
A345: Driftskostnader (Faste) / Produksjon
B347: =B303 -> 2023 | C347: =C303 -> 2024 | D347: =D303 -> 2025 | E347: =E303 -> 2026 | F347: =F303 -> 2027 | G347: =G303 -> 2028 | H347: =H303 -> 2029 | I347: =I303 -> 2030 | ... BQ347: =BQ303 -> 2090
A348: NB26 | B348: =Formue!Y111 -> 428.31035 | C348: =Formue!Z111 -> 394.9349 | D348: =Formue!AA111 -> 411.9084 | E348: =Formue!AB111 -> 437.43237 | F348: =Formue!AC111 -> 448.22894 | G348: =Formue!AD111 -> 469.5521 | H348: =Formue!AE111 -> 492.90096 | I348: =Formue!AF111 -> 482.89258 | ... BQ348: =Formue!CN111 -> 1286.7898
A349: RNB25 | B349: 428.31035 | C349: 395.31645 | D349: 424.14609 | E349: 429.38542 | F349: 433.84829 | G349: 457.43243 | H349: 480.33628 | I349: 486.60674 | J349: 510.78383 | K349: 540.77733 | L349: 559.18326 | M349: 567.68233 | N349: 574.78916 | O349: 566.0142 | P349: 575.40205 | Q349: 597.72915 | R349: 608.35836 | S349: 628.65802 | T349: 649.9364 | U349: 670.35683 | V349: 684.73604 | W349: 704.79283 | X349: 732.0346 | Y349: 732.86279 | Z349: 767.96992 | AA349: 767.23389 | AB349: 772.18901 | AC349: 761.15012 | AD349: 765.88 | AE349: 775.21161 | AF349: 798.7159 | AG349: 827.81239 | AH349: 815.70088 | AI349: 768.48515 | AJ349: 780.42969 | AK349: 798.45977 | AL349: 794.35444 | AM349: 804.61494 | AN349: 817.48878 | AO349: 830.5686 | AP349: 843.85769 | AQ349: 857.35942 | AR349: 871.07717 | AS349: 885.0144 | AT349: 899.17463 | AU349: 913.56143 | AV349: 928.17841 | AW349: 943.02926 | AX349: 958.11773 | AY349: 973.44762 | AZ349: 989.02278 | BA349: 1004.8471 | BB349: 1020.9247 | BC349: 1037.2595 | BD349: 1053.8556 | BE349: 1070.7173 | BF349: 1087.8488 | BG349: 1105.2544 | BH349: 1122.9385 | BI349: 1140.9055 | BJ349: 1159.16 | BK349: 1177.7065 | BL349: 1196.5498 | BM349: 1215.6946 | BN349: 1235.1457 | BO349: 1254.9081 | BP349: 1274.9866 | BQ349: 1295.3864
B352: =B347 -> 2023 | C352: =C347 -> 2024 | D352: =D347 -> 2025 | E352: =E347 -> 2026 | F352: =F347 -> 2027 | G352: =G347 -> 2028 | H352: =H347 -> 2029 | I352: =I347 -> 2030 | ... BQ352: =BQ347 -> 2090
A353: NB26 | B353: 100 | C353: =B353*(C348/B348) -> 92.207649 | D353: =C353*(D348/C348) -> 96.170545 | E353: =D353*(E348/D348) -> 102.12977 | F353: =E353*(F348/E348) -> 104.6505 | G353: =F353*(G348/F348) -> 109.62894 | H353: =G353*(H348/G348) -> 115.08033 | I353: =H353*(I348/H348) -> 112.74362 | J353: =I353*(J348/I348) -> 117.09654 | ... BQ353: =BP353*(BQ348/BP348) -> 300.43397
A354: RNB25 | B354: 100 | C354: =B354*(C349/B349) -> 92.296731 | D354: =C354*(D349/C349) -> 99.027748 | E354: =D354*(E349/D349) -> 100.251 | F354: =E354*(F349/E349) -> 101.29297 | G354: =F354*(G349/F349) -> 106.79929 | H354: =G354*(H349/G349) -> 112.14678 | I354: =H354*(I349/H349) -> 113.61078 | J354: =I354*(J349/I349) -> 119.25554 | ... BQ354: =BP354*(BQ349/BP349) -> 302.44107
A393: Petroleum investments, current prices, OED definition
B394: 45291 | C394: 45657 | D394: 46022 | E394: 46387 | F394: 46752 | G394: 47118 | H394: 47483 | I394: 47848 | J394: 48213 | K394: 48579 | L394: 48944 | M394: 49309 | N394: 49674 | O394: 50040 | P394: 50405 | Q394: 50770 | R394: 51135 | S394: 51501 | T394: 51866 | U394: 52231 | V394: 52596 | W394: 52962 | X394: 53327 | Y394: 53692 | Z394: 54057 | AA394: 54423 | AB394: 54788 | AC394: 55153 | AD394: 55518 | AE394: 55884 | AF394: 56249 | AG394: 56614 | AH394: 56979 | AI394: 57345 | AJ394: 57710 | AK394: 58075 | AL394: 58440 | AM394: 58806
A395: NB26 | B395: =Investments!AD21 -> 218509.82 | C395: =Investments!AE21 -> 252419.64 | D395: =Investments!AF21 -> 281357.13 | E395: =Investments!AG21 -> 271550.81 | F395: =Investments!AH21 -> 244022.32 | G395: =Investments!AI21 -> 228312.06 | H395: =Investments!AJ21 -> 231083.21 | I395: =Investments!AK21 -> 229248.04 | ... AM395: =Investments!BO21 -> 179606.24
A396: RNB25 | B396: 218509.82 | C396: 260141.64 | D396: 272940.86 | E396: 248130.45 | F396: 230458.08 | G396: 225731.78 | H396: 232944.78 | I396: 232571.58 | J396: 225138.5 | K396: 218997.61 | L396: 216653.41 | M396: 209949.54 | N396: 203190.94 | O396: 201303.1 | P396: 202522.46 | Q396: 206610.09 | R396: 206854.1 | S396: 206802.87 | T396: 208917.82 | U396: 208928.13 | V396: 209383.56 | W396: 207195.24 | X396: 205691.82 | Y396: 203289.31 | Z396: 201728.11 | AA396: 200297.63 | AB396: 200990.63 | AC396: 197879.34 | AD396: 193316.8 | AE396: 192221.51 | AF396: 192007.29 | AG396: 191865.85 | AH396: 190193.12 | AI396: 188186.73 | AJ396: 185208.08 | AK396: 184144.71 | AL396: 181073.14 | AM396: 179081.42
A398: Difference (Last round) | B398: =B395-B396 -> 0 | C398: =C395-C396 -> -7722 | D398: =D395-D396 -> 8416.265 | E398: =E395-E396 -> 23420.361 | F398: =F395-F396 -> 13564.243 | G398: =G395-G396 -> 2580.2718 | H398: =H395-H396 -> -1861.5629 | I398: =I395-I396 -> -3323.5363 | ... AM398: =AM395-AM396 -> 524.82321
B431: MERK: Husk å justere slik at det brukes samme fastprisår mellom rundene
A433: Investeringsutgifter, faste
B434: 2023 | C434: 2024 | D434: 2025 | E434: 2026 | F434: 2027 | G434: 2028 | H434: 2029 | I434: 2030 | J434: 2031 | K434: 2032 | L434: 2033 | M434: 2034 | N434: 2035 | O434: 2036 | P434: 2037 | Q434: 2038 | R434: 2039 | S434: 2040 | T434: 2041 | U434: 2042 | V434: 2043 | W434: 2044 | X434: 2045 | Y434: 2046 | Z434: 2047 | AA434: 2048 | AB434: 2049 | AC434: 2050 | AD434: 2051 | AE434: 2052 | AF434: 2053 | AG434: 2054 | AH434: 2055 | AI434: 2056 | AJ434: 2057 | AK434: 2058 | AL434: 2059 | AM434: 2060 | AN434: 2061 | AO434: 2062 | AP434: 2063 | AQ434: 2064 | AR434: 2065 | AS434: 2066 | AT434: 2067 | AU434: 2068 | AV434: 2069 | AW434: 2070 | AX434: 2071 | AY434: 2072 | AZ434: 2073 | BA434: 2074 | BB434: 2075 | BC434: 2076 | BD434: 2077 | BE434: 2078 | BF434: 2079 | BG434: 2080 | BH434: 2081 | BI434: 2082 | BJ434: 2083 | BK434: 2084 | BL434: 2085 | BM434: 2086 | BN434: 2087 | BO434: 2088 | BP434: 2089 | BQ434: 2090
A435: NB26 | B435: =Formue!Y57 -> 205379.04 | C435: =Formue!Z57 -> 223509.23 | D435: =Formue!AA57 -> 241035.49 | E435: =Formue!AB57 -> 227798.82 | F435: =Formue!AC57 -> 199558.52 | G435: =Formue!AD57 -> 181079.23 | H435: =Formue!AE57 -> 178136.97 | I435: =Formue!AF57 -> 173113.64 | ... BQ435: =Formue!CN57 -> 83958.521
A436: RNB25 | B436: 205379.04 | C436: 229867.03 | D436: 234172.76 | E436: 208811.31 | F436: 189559.98 | G436: 180069.69 | H436: 180736.25 | I436: 177028.17 | J436: 167995 | K436: 159197.69 | L436: 153949.25 | M436: 146223.18 | N436: 138742.82 | O436: 134329.58 | P436: 132279.41 | Q436: 132030.66 | R436: 129511.41 | S436: 126915.69 | T436: 125557.04 | U436: 123069.68 | V436: 120611.58 | W436: 116860.66 | X436: 113699.29 | Y436: 110269.99 | Z436: 107301.88 | AA436: 104373.89 | AB436: 102362.26 | AC436: 98633.925 | AD436: 94494.331 | AE436: 92050.777 | AF436: 90043.328 | AG436: 88198.916 | AH436: 85658.877 | AI436: 82941.028 | AJ436: 79989.517 | AK436: 78096.754 | AL436: 75211.411 | AM436: 72861.165 | AN436: 73225.47 | AO436: 73591.598 | AP436: 73959.556 | AQ436: 74329.354 | AR436: 74701 | AS436: 75074.505 | AT436: 75449.878 | AU436: 75827.127 | AV436: 76206.263 | AW436: 76587.294 | AX436: 76970.231 | AY436: 77355.082 | AZ436: 77741.857 | BA436: 78130.567 | BB436: 78521.219 | BC436: 78913.825 | BD436: 79308.395 | BE436: 79704.937 | BF436: 80103.461 | BG436: 80503.979 | BH436: 80906.498 | BI436: 81311.031 | BJ436: 81717.586 | BK436: 82126.174 | BL436: 82536.805 | BM436: 82949.489 | BN436: 83364.236 | BO436: 83781.058 | BP436: 84199.963 | BQ436: 84620.963
A438: Difference (Last round) | B438: =B435-B436 -> 0 | C438: =C435-C436 -> -6357.799 | D438: =D435-D436 -> 6862.7266 | E438: =E435-E436 -> 18987.505 | F438: =F435-F436 -> 9998.5421 | G438: =G435-G436 -> 1009.5485 | H438: =H435-H436 -> -2599.2812 | I438: =I435-I436 -> -3914.5232 | ... BQ438: =BQ435-BQ436 -> -662.44143
A475: Investeringsutgifter (Faste) / Produksjon - UTEN INDEKSERING
B477: 2023 | C477: 2024 | D477: 2025 | E477: 2026 | F477: 2027 | G477: 2028 | H477: 2029 | I477: 2030 | J477: 2031 | K477: 2032 | L477: 2033 | M477: 2034 | N477: 2035 | O477: 2036 | P477: 2037 | Q477: 2038 | R477: 2039 | S477: 2040 | T477: 2041 | U477: 2042 | V477: 2043 | W477: 2044 | X477: 2045 | Y477: 2046 | Z477: 2047 | AA477: 2048 | AB477: 2049 | AC477: 2050 | AD477: 2051 | AE477: 2052 | AF477: 2053 | AG477: 2054 | AH477: 2055 | AI477: 2056 | AJ477: 2057 | AK477: 2058 | AL477: 2059 | AM477: 2060 | AN477: 2061 | AO477: 2062 | AP477: 2063 | AQ477: 2064 | AR477: 2065 | AS477: 2066 | AT477: 2067 | AU477: 2068 | AV477: 2069 | AW477: 2070 | AX477: 2071 | AY477: 2072 | AZ477: 2073 | BA477: 2074 | BB477: 2075 | BC477: 2076 | BD477: 2077 | BE477: 2078 | BF477: 2079 | BG477: 2080 | BH477: 2081 | BI477: 2082 | BJ477: 2083 | BK477: 2084 | BL477: 2085 | BM477: 2086 | BN477: 2087 | BO477: 2088 | BP477: 2089 | BQ477: 2090
A478: NB26 | B478: =Formue!Y112 -> 880.88801 | C478: =Formue!Z112 -> 926.59395 | D478: =Formue!AA112 -> 1012.0385 | E478: =Formue!AB112 -> 963.55698 | F478: =Formue!AC112 -> 859.84493 | G478: =Formue!AD112 -> 828.3751 | H478: =Formue!AE112 -> 870.63439 | I478: =Formue!AF112 -> 896.0628 | ... BQ478: =Formue!CN112 -> 1382.6909
A479: RNB25 | B479: 880.88801 | C479: 952.95124 | D479: 996.06244 | E479: 883.2425 | F479: 816.76386 | G479: 820.11113 | H479: 871.97914 | I479: 911.75264 | J479: 909.43666 | K479: 904.33856 | L479: 906.59974 | M479: 879.19155 | N479: 854.73777 | O479: 849.14599 | P479: 868.64236 | Q479: 917.78904 | R479: 954.5126 | S479: 981.51952 | T479: 1015.641 | U479: 1036.8875 | V479: 1059.6823 | W479: 1072.7359 | X479: 1089.9943 | Y479: 1098.7838 | Z479: 1111.6787 | AA479: 1121.9029 | AB479: 1143.7179 | AC479: 1146.9461 | AD479: 1139.3844 | AE479: 1159.0669 | AF479: 1177.5251 | AG479: 1195.7166 | AH479: 1198.4891 | AI479: 1199.159 | AJ479: 1192.0732 | AK479: 1203.425 | AL479: 1197.7739 | AM479: 1199.9316 | AN479: 1205.9312 | AO479: 1211.9609 | AP479: 1218.0207 | AQ479: 1224.1108 | AR479: 1230.2313 | AS479: 1236.3825 | AT479: 1242.5644 | AU479: 1248.7772 | AV479: 1255.0211 | AW479: 1261.2962 | AX479: 1267.6027 | AY479: 1273.9407 | AZ479: 1280.3104 | BA479: 1286.712 | BB479: 1293.1455 | BC479: 1299.6113 | BD479: 1306.1093 | BE479: 1312.6399 | BF479: 1319.2031 | BG479: 1325.7991 | BH479: 1332.4281 | BI479: 1339.0902 | BJ479: 1345.7857 | BK479: 1352.5146 | BL479: 1359.2772 | BM479: 1366.0736 | BN479: 1372.9039 | BO479: 1379.7684 | BP479: 1386.6673 | BQ479: 1393.6006
A481: Forhold | B481: =B478/B479 -> 1 | C481: =C478/C479 -> 0.97234141 | D481: =D478/D479 -> 1.0160392 | E481: =E478/E479 -> 1.0909314 | F481: =F478/F479 -> 1.052746 | G481: =G478/G479 -> 1.0100766 | H481: =H478/H479 -> 0.99845781 | I481: =I478/I479 -> 0.98279156 | ... BQ481: =BQ478/BQ479 -> 0.99217157
A484: Investeringsutgifter (Faste) / Produksjon - MED INDEKSERING
B485: 2023 | C485: 2024 | D485: 2025 | E485: 2026 | F485: 2027 | G485: 2028 | H485: 2029 | I485: 2030 | J485: 2031 | K485: 2032 | L485: 2033 | M485: 2034 | N485: 2035 | O485: 2036 | P485: 2037 | Q485: 2038 | R485: 2039 | S485: 2040 | T485: 2041 | U485: 2042 | V485: 2043 | W485: 2044 | X485: 2045 | Y485: 2046 | Z485: 2047 | AA485: 2048 | AB485: 2049 | AC485: 2050 | AD485: 2051 | AE485: 2052 | AF485: 2053 | AG485: 2054 | AH485: 2055 | AI485: 2056 | AJ485: 2057 | AK485: 2058 | AL485: 2059 | AM485: 2060 | AN485: 2061 | AO485: 2062 | AP485: 2063 | AQ485: 2064 | AR485: 2065 | AS485: 2066 | AT485: 2067 | AU485: 2068 | AV485: 2069 | AW485: 2070 | AX485: 2071 | AY485: 2072 | AZ485: 2073 | BA485: 2074 | BB485: 2075 | BC485: 2076 | BD485: 2077 | BE485: 2078 | BF485: 2079 | BG485: 2080 | BH485: 2081 | BI485: 2082 | BJ485: 2083 | BK485: 2084 | BL485: 2085 | BM485: 2086 | BN485: 2087 | BO485: 2088 | BP485: 2089 | BQ485: 2090
A486: NB26 | B486: 100 | C486: =B486*(C478/B478) -> 105.18862 | D486: =C486*(D478/C478) -> 114.88844 | E486: =D486*(E478/D478) -> 109.38473 | F486: =E486*(F478/E478) -> 97.611151 | G486: =F486*(G478/F478) -> 94.038639 | H486: =G486*(H478/G478) -> 98.83599 | I486: =H486*(I478/H478) -> 101.72267 | J486: =I486*(J478/I478) -> 99.646769 | ... BQ486: =BP486*(BQ478/BP478) -> 156.96557
A487: RNB25 | B487: 100 | C487: =B487*(C479/B479) -> 108.18075 | D487: =C487*(D479/C479) -> 113.07481 | E487: =D487*(E479/D479) -> 100.26729 | F487: =E487*(F479/E479) -> 92.720511 | G487: =F487*(G479/F479) -> 93.100499 | H487: =G487*(H479/G479) -> 98.988649 | I487: =H487*(I479/H479) -> 103.50381 | J487: =I487*(J479/I479) -> 103.24089 | ... BQ487: =BP487*(BQ479/BP479) -> 158.20406
A489: Forhold | B489: =B486/B487 -> 1 | C489: =C486/C487 -> 0.97234141 | D489: =D486/D487 -> 1.0160392 | E489: =E486/E487 -> 1.0909314 | F489: =F486/F487 -> 1.052746 | G489: =G486/G487 -> 1.0100766 | H489: =H486/H487 -> 0.99845781 | I489: =I486/I487 -> 0.98279156 | ... BQ489: =BQ486/BQ487 -> 0.99217157
A534: SNKS, Løpende
B535: 45291 | C535: 45657 | D535: 46022 | E535: 46387 | F535: 46752 | G535: 47118 | H535: 47483 | I535: 47848 | J535: 48213 | K535: 48579 | L535: 48944 | M535: 49309 | N535: 49674 | O535: 50040 | P535: 50405 | Q535: 50770 | R535: 51135 | S535: 51501 | T535: 51866 | U535: 52231 | V535: 52596 | W535: 52962 | X535: 53327 | Y535: 53692 | Z535: 54057 | AA535: 54423 | AB535: 54788 | AC535: 55153 | AD535: 55518 | AE535: 55884 | AF535: 56249 | AG535: 56614 | AH535: 56979 | AI535: 57345 | AJ535: 57710 | AK535: 58075 | AL535: 58440 | AM535: 58806 | AN535: 59171 | AO535: 59536 | AP535: 59901 | AQ535: 60267 | AR535: 60632 | AS535: 60997 | AT535: 61362 | AU535: 61728 | AV535: 62093 | AW535: 62458 | AX535: 62823 | AY535: 63189 | AZ535: 63554 | BA535: 63919 | BB535: 64284 | BC535: 64650 | BD535: 65015 | BE535: 65380 | BF535: 65745 | BG535: 66111 | BH535: 66476 | BI535: 66841 | BJ535: 67206 | BK535: 67572 | BL535: 67937 | BM535: 68302 | BN535: 68667 | BO535: 69033 | BP535: 69398 | BQ535: 69763
A536: NB26 | B536: =SNKS!R99 -> 978064.87 | C536: =SNKS!S99 -> 702159.39 | D536: =SNKS!T99 -> 663615.54 | E536: =SNKS!U99 -> 521305.6 | F536: =SNKS!V99 -> 407654.37 | G536: =SNKS!W99 -> 380031.6 | H536: =SNKS!X99 -> 340095.07 | I536: =SNKS!Y99 -> 279907.86 | ... BQ536: =SNKS!CG99 -> -28371.989
A537: RNB25 | B537: 978064.87 | C537: 702159.39 | D537: 697701 | E537: 594407.2 | F537: 474104.72 | G537: 433036.29 | H537: 387988.54 | I537: 320712.38 | J537: 271695.03 | K537: 267711.73 | L537: 268489.78 | M537: 273230.88 | N537: 283299.43 | O537: 284811.85 | P537: 278630.97 | Q537: 258946.47 | R537: 238012.26 | S537: 224024.54 | T537: 210303.42 | U537: 204233.94 | V537: 190315.16 | W537: 186573.28 | X537: 176806.06 | Y537: 171177.01 | Z537: 163585.74 | AA537: 160329.08 | AB537: 156267.32 | AC537: 149063.21 | AD537: 149897.22 | AE537: 147174.1 | AF537: 139138.09 | AG537: 132339.57 | AH537: 128182.63 | AI537: 129929.59 | AJ537: 130040.17 | AK537: 127430.51 | AL537: 121777.62 | AM537: 118961.21 | AN537: 117055.68 | AO537: 115045.08 | AP537: 112926.87 | AQ537: 110698.51 | AR537: 108357.43 | AS537: 105901.06 | AT537: 103326.81 | AU537: 100632.08 | AV537: 97814.279 | AW537: 94870.807 | AX537: 91799.068 | AY537: 88596.468 | AZ537: 85260.428 | BA537: 81788.378 | BB537: 78177.771 | BC537: 74426.079 | BD537: 70530.805 | BE537: 66489.485 | BF537: 62299.692 | BG537: 57959.048 | BH537: 53465.225 | BI537: 48815.952 | BJ537: 44009.028 | BK537: 39042.321 | BL537: 33913.785 | BM537: 28621.463 | BN537: 23163.496 | BO537: 17538.137 | BP537: 11743.758 | BQ537: 5778.8604
A539: Difference (Last round) | B539: =B536-B537 -> 0 | C539: =C536-C537 -> 0 | D539: =D536-D537 -> -34085.459 | E539: =E536-E537 -> -73101.6 | F539: =F536-F537 -> -66450.347 | G539: =G536-G537 -> -53004.691 | H539: =H536-H537 -> -47893.474 | I539: =I536-I537 -> -40804.52 | ... BQ539: =BQ536-BQ537 -> -34150.849
B583: 2023 | C583: 2024 | D583: 2025 | E583: 2026 | F583: 2027 | G583: 2028 | H583: 2029 | I583: 2030 | J583: 2031 | K583: 2032 | L583: 2033 | M583: 2034 | N583: 2035 | O583: 2036 | P583: 2037 | Q583: 2038 | R583: 2039 | S583: 2040 | T583: 2041 | U583: 2042 | V583: 2043 | W583: 2044 | X583: 2045 | Y583: 2046 | Z583: 2047 | AA583: 2048 | AB583: 2049 | AC583: 2050 | AD583: 2051 | AE583: 2052 | AF583: 2053 | AG583: 2054 | AH583: 2055 | AI583: 2056 | AJ583: 2057 | AK583: 2058 | AL583: 2059 | AM583: 2060 | AN583: 2061 | AO583: 2062 | AP583: 2063 | AQ583: 2064 | AR583: 2065 | AS583: 2066 | AT583: 2067 | AU583: 2068 | AV583: 2069 | AW583: 2070 | AX583: 2071 | AY583: 2072 | AZ583: 2073 | BA583: 2074 | BB583: 2075 | BC583: 2076 | BD583: 2077 | BE583: 2078 | BF583: 2079 | BG583: 2080 | BH583: 2081 | BI583: 2082 | BJ583: 2083 | BK583: 2084 | BL583: 2085 | BM583: 2086 | BN583: 2087 | BO583: 2088 | BP583: 2089 | BQ583: 2090
A584: NB26 | B584: =SNKS!R86 -> 78309 | C584: =SNKS!S86 -> 62578 | D584: =SNKS!T86 -> 37768.1 | E584: =SNKS!U86 -> 25804.6 | F584: =SNKS!V86 -> 13754.374 | G584: =SNKS!W86 -> 13831.601 | H584: =SNKS!X86 -> 13895.068 | I584: =SNKS!Y86 -> 13904.184 | ... BQ584: =SNKS!CG86 -> -8107.1675
A585: RNB25 | B585: 78309 | C585: 62578 | D585: 37800 | E585: 31407.2 | F585: 14704.72 | G585: 14736.292 | H585: 14788.543 | I585: 14853.717 | J585: 15509.692 | K585: 16185.965 | L585: 16883.084 | M585: 17601.614 | N585: 18342.824 | O585: 18709.681 | P585: 19083.874 | Q585: 19465.552 | R585: 19854.863 | S585: 20251.96 | T585: 20656.999 | U585: 21070.139 | V585: 21491.542 | W585: 21921.373 | X585: 22359.8 | Y585: 22806.996 | Z585: 23263.136 | AA585: 23728.399 | AB585: 24202.967 | AC585: 24687.026 | AD585: 25180.767 | AE585: 25684.382 | AF585: 26198.07 | AG585: 26722.031 | AH585: 27256.472 | AI585: 27801.601 | AJ585: 28357.633 | AK585: 28924.786 | AL585: 29503.282 | AM585: 30093.347 | AN585: 29611.31 | AO585: 29102.693 | AP585: 28566.855 | AQ585: 28003.151 | AR585: 27410.934 | AS585: 26789.551 | AT585: 26138.347 | AU585: 25456.668 | AV585: 24743.856 | AW585: 23999.253 | AX585: 23222.202 | AY585: 22412.047 | AZ585: 21568.137 | BA585: 20689.82 | BB585: 19776.453 | BC585: 18827.396 | BD585: 17842.018 | BE585: 16819.694 | BF585: 15759.812 | BG585: 14661.769 | BH585: 13524.976 | BI585: 12348.861 | BJ585: 11132.864 | BK585: 9876.4473 | BL585: 8579.0933 | BM585: 7240.3064 | BN585: 5859.617 | BO585: 4436.5827 | BP585: 2970.7918 | BQ585: 1461.8652
A621: Statens andel av kontantstrømmen
B623: 2023 | C623: 2024 | D623: 2025 | E623: 2026 | F623: 2027 | G623: 2028 | H623: 2029 | I623: 2030 | J623: 2031 | K623: 2032 | L623: 2033 | M623: 2034 | N623: 2035 | O623: 2036 | P623: 2037 | Q623: 2038 | R623: 2039 | S623: 2040 | T623: 2041 | U623: 2042 | V623: 2043 | W623: 2044 | X623: 2045 | Y623: 2046 | Z623: 2047 | AA623: 2048 | AB623: 2049 | AC623: 2050 | AD623: 2051 | AE623: 2052 | AF623: 2053 | AG623: 2054 | AH623: 2055 | AI623: 2056 | AJ623: 2057 | AK623: 2058 | AL623: 2059 | AM623: 2060 | AN623: 2061 | AO623: 2062 | AP623: 2063 | AQ623: 2064 | AR623: 2065 | AS623: 2066 | AT623: 2067 | AU623: 2068 | AV623: 2069 | AW623: 2070 | AX623: 2071 | AY623: 2072 | AZ623: 2073 | BA623: 2074 | BB623: 2075 | BC623: 2076 | BD623: 2077 | BE623: 2078 | BF623: 2079 | BG623: 2080 | BH623: 2081 | BI623: 2082 | BJ623: 2083 | BK623: 2084 | BL623: 2085 | BM623: 2086 | BN623: 2087 | BO623: 2088 | BP623: 2089 | BQ623: 2090
A624: NB26 | B624: =Formue!Y86 -> 1.0737095 | C624: =Formue!Z86 -> 0.90570362 | D624: =Formue!AA86 -> 0.92322991 | E624: =Formue!AB86 -> 0.97096903 | F624: =Formue!AC86 -> 0.90265887 | G624: =Formue!AD86 -> 0.89670673 | H624: =Formue!AE86 -> 0.8987444 | I624: =Formue!AF86 -> 1.0054269 | ... BQ624: =Formue!CN86 -> 0.87124895

Sheet KVARTS
B1: 1997 | C1: 1998 | D1: 1999 | E1: 2000 | F1: 2001 | G1: 2002 | H1: 2003 | I1: 2004 | J1: 2005 | K1: 2006 | L1: 2007 | M1: 2008 | N1: 2009 | O1: 2010 | P1: 2011 | Q1: 2012 | R1: 2013 | S1: 2014 | T1: 2015 | U1: 2016 | V1: 2017 | W1: 2018 | X1: 2019 | Y1: 2020 | Z1: 2021 | AA1: 2022 | AB1: 2023 | AC1: 2024 | AD1: 2025 | AE1: 2026 | AF1: 2027 | AG1: 2028 | AH1: 2029 | AI1: 2030 | AJ1: 2031 | AK1: 2032 | AL1: 2033 | AM1: 2034 | AN1: 2035 | AO1: 2036 | AP1: 2037 | AQ1: 2038 | AR1: 2039 | AS1: 2040 | AT1: 2041 | AU1: 2042 | AV1: 2043 | AW1: 2044 | AX1: 2045 | AY1: 2046 | AZ1: 2047 | BA1: 2048 | BB1: 2049 | BC1: 2050 | BD1: 2051 | BE1: 2052 | BF1: 2053 | BG1: 2054 | BH1: 2055 | BI1: 2056 | BJ1: 2057 | BK1: 2058 | BL1: 2059 | BM1: 2060 | BN1: 2061 | BO1: 2062 | BP1: 2063 | BQ1: 2064 | BR1: 2065 | BS1: 2066 | BT1: 2067 | BU1: 2068 | BV1: 2069 | BW1: 2070 | BX1: 2071 | BY1: 2072 | BZ1: 2073 | CA1: 2074 | CB1: 2075 | CC1: 2076 | CD1: 2077 | CE1: 2078 | CF1: 2079 | CG1: 2080 | CH1: 2081 | CI1: 2082 | CJ1: 2083 | CK1: 2084 | CL1: 2085 | CM1: 2086 | CN1: 2087 | CO1: 2088 | CP1: 2089 | CQ1: 2090
A3: Priser, valutakurs, inflasjon og omregningsfaktorer
A5: Oljepris NOK/fat løpende priser | B5: 135.60234 | C5: 96.551734 | D5: 134.66375 | E5: 251 | F5: 223 | G5: 198 | H5: 201 | I5: 255 | J5: 355 | K5: 423 | L5: 425 | M5: 556 | N5: 391 | O5: 485 | P5: 622 | Q5: 650 | R5: 639 | S5: 627 | T5: 431 | U5: 379 | V5: 452 | W5: 583 | X5: 564 | Y5: 407 | Z5: 609 | AA5: 951 | AB5: 867 | AC5: 856 | AD5: =AD24*AD13 -> 724.01362 | AE5: =AE24*AE13 -> 674.49527 | AF5: =AF24*AF13 -> 673.96431 | AG5: =AG24*AG13 -> 677.74844 | AH5: =AH24*AH13 -> 680.85835 | AI5: =AI24*AI13 -> 681.30503 | AJ5: =AJ24*AJ13 -> 713.68946 | AK5: =AK24*AK13 -> 747.09676 | ... CQ5: =CQ24*CQ13 -> 2537.0869
A6: Gasspris NOK/Sm3, løpende priser | B6: 0.65 | C6: 0.64 | D6: 0.55 | E6: 0.99 | F6: 1.21 | G6: 0.92 | H6: 0.88 | I6: 0.97 | J6: 1.25 | K6: 1.74 | L6: 1.57 | M6: 2.22 | N6: 1.67 | O6: 1.59 | P6: 2 | Q6: 2.21 | R6: 2.31 | S6: 2.05 | T6: 1.92 | U6: 1.4 | V6: 1.65 | W6: 2.2 | X6: 1.57 | Y6: 1.1300308 | Z6: 4.607391 | AA6: 12.04844 | AB6: 5.4428396 | AC6: =AC25*AC13 -> 4.4258199 | AD6: =AD25*AD13 -> 5.1640215 | AE6: =AE25*AE13 -> 3.9871306 | AF6: =AF25*AF13 -> 3.2488597 | AG6: =AG25*AG13 -> 3.3170857 | AH6: =AH25*AH13 -> 3.3867445 | AI6: =AI25*AI13 -> 2.7459874 | AJ6: =AJ25*AJ13 -> 2.7635615 | ... CQ6: =CQ25*CQ13 -> 7.8083799
A7: Gasspris innenlandske leveranser NOK/Sm3, løpende priser | H7: 0.61 | I7: 0.61 | J7: 0.79 | K7: 1.05 | L7: 0.95 | M7: 1.42 | N7: 1.94 | O7: 1.76 | P7: 2.2 | Q7: 1.3 | R7: 1.3 | S7: 0 | T7: 0 | U7: 0 | V7: 0 | W7: 0 | X7: 0 | Y7: 0 | Z7: 0 | AA7: 0 | AB7: 0 | AC7: 0 | AD7: 0 | AE7: 0 | AF7: 0 | AG7: 0 | AH7: 0 | AI7: 0 | AJ7: 0 | AK7: 0 | AL7: 0 | AM7: 0 | AN7: 0 | AO7: 0 | AP7: 0 | AQ7: 0 | AR7: 0 | AS7: 0 | AT7: 0 | AU7: 0 | AV7: 0 | AW7: 0 | AX7: 0 | AY7: 0 | AZ7: 0 | BA7: 0 | BB7: 0 | BC7: 0 | BD7: 0 | BE7: 0 | BF7: 0 | BG7: 0 | BH7: 0 | BI7: 0 | BJ7: 0 | BK7: 0 | BL7: 0 | BM7: 0
A8: NGL- og kondensatpris kr/pr Sm3 løpende priser | B8: 993.63 | C8: 615.23 | D8: 1017.97 | E8: 1717.27 | F8: 1526.37 | G8: 1377.1 | H8: 1093.1689 | I8: 1332.128 | J8: 1847.0464 | K8: 1965.5889 | L8: 1814.6526 | M8: 2521.0891 | N8: 1763.5173 | O8: 2199.1357 | P8: 2796 | Q8: 2896 | R8: ='NGL-pris'!B8 -> 2814.8571 | S8: ='NGL-pris'!C8 -> 2352.3148 | T8: ='NGL-pris'!D8 -> 1629.3665 | U8: ='NGL-pris'!E8 -> 1482.9412 | V8: ='NGL-pris'!F8 -> 1912.6482 | W8: ='NGL-pris'!G8 -> 2249.6673 | X8: ='NGL-pris'!H8 -> 2119.439 | Y8: ='NGL-pris'!I8 -> 1565.0008 | ... BM8: ='NGL-pris'!AW8 -> 5111.4616
A11: Dollarkurs | B11: 7.0525 | C11: 7.55 | D11: 7.83 | E11: 8.8 | F11: 8.9827437 | G11: 7.9774942 | H11: 7.0767603 | I11: 6.7374085 | J11: 6.4424777 | K11: 6.4122903 | L11: 5.8556681 | M11: 5.6433416 | N11: 6.2858001 | O11: 6.0403248 | P11: 5.6 | Q11: 5.82 | R11: 5.88 | S11: 6.3 | T11: 8.07 | U11: 8.4039727 | V11: 8.27 | W11: 8.1400616 | X11: 8.8037 | Y11: 9.4004 | Z11: 8.5952989 | AA11: 9.6161888 | AB11: 10.563541 | AC11: 10.750507 | AD11: 10.403698 | AE11: 10.11351 | AF11: 10.11351 | AG11: 10.11351 | AH11: 10.11351 | AI11: 10.11351 | AJ11: =AI11 -> 10.11351 | AK11: =AJ11 -> 10.11351 | AL11: =AK11 -> 10.11351 | AM11: =AL11 -> 10.11351 | AN11: =AM11 -> 10.11351 | AO11: =AN11 -> 10.11351 | AP11: =AO11 -> 10.11351 | AQ11: =AP11 -> 10.11351 | ... CQ11: =CP11 -> 10.11351
A12: Inflasjonsforutsetning for USD (KPI-vekst i USA) | B12: 2.3376899 | C12: 1.5522791 | D12: 2.1880272 | E12: 3.3768573 | F12: 2.8261711 | G12: 1.5860316 | H12: 2.270095 | I12: 2.6772367 | J12: 3.3927468 | K12: 3.2259441 | L12: 2.8526725 | M12: 3.8391003 | N12: -0.35554627 | O12: 1.6400434 | P12: 3.1568416 | Q12: 2.0693373 | R12: 1.4648327 | S12: 1.622223 | T12: 0.11862714 | U12: 1.2615832 | V12: 2.13011 | W12: 2.4425833 | X12: 1.8122101 | Y12: 1.2335844 | Z12: 4.6978589 | AA12: 8.0027998 | AB12: 4.1163384 | AC12: 2.9495252 | AD12: 3.6 | AE12: 3.1 | AF12: 2.1 | AG12: 2.1 | AH12: 2.1 | AI12: 2 | AJ12: 2 | AK12: 2 | AL12: 2 | AM12: 2 | AN12: 2 | AO12: 2 | AP12: 2 | AQ12: 2 | AR12: 2 | AS12: 2 | AT12: 2 | AU12: 2 | AV12: 2 | AW12: 2 | AX12: 2 | AY12: 2 | AZ12: 2 | BA12: 2 | BB12: 2 | BC12: 2 | BD12: 2 | BE12: 2 | BF12: 2 | BG12: 2 | BH12: 2 | BI12: 2 | BJ12: 2 | BK12: 2 | BL12: 2 | BM12: 2 | BN12: 2 | BO12: 2 | BP12: 2 | BQ12: 2 | BR12: 2 | BS12: 2 | BT12: 2 | BU12: 2 | BV12: 2 | BW12: 2 | BX12: 2 | BY12: 2 | BZ12: 2 | CA12: 2 | CB12: 2 | CC12: 2 | CD12: 2 | CE12: 2 | CF12: 2 | CG12: 2 | CH12: 2 | CI12: 2 | CJ12: 2 | CK12: 2 | CL12: 2 | CM12: 2 | CN12: 2 | CO12: 2 | CP12: 2 | CQ12: 2
A13: Prisindeks | B13: =C13/(1+C12/100) -> 0.47907406 | C13: =D13/(1+D12/100) -> 0.48651062 | D13: =E13/(1+E12/100) -> 0.49715561 | E13: =F13/(1+F12/100) -> 0.51394384 | F13: =G13/(1+G12/100) -> 0.52846878 | G13: =H13/(1+H12/100) -> 0.53685046 | H13: =I13/(1+I12/100) -> 0.54903747 | I13: =J13/(1+J12/100) -> 0.56373651 | ... AD13: =AE13/(1+AE12/100) -> 0.9699321 | AE13: 1 | AF13: =AE13*(1+AF12/100) -> 1.021 | AG13: =AF13*(1+AG12/100) -> 1.042441 | AH13: =AG13*(1+AH12/100) -> 1.0643323 | AI13: =AH13*(1+AI12/100) -> 1.0856189 | AJ13: =AI13*(1+AJ12/100) -> 1.1073313 | AK13: =AJ13*(1+AK12/100) -> 1.1294779 | AL13: =AK13*(1+AL12/100) -> 1.1520675 | AM13: =AL13*(1+AM12/100) -> 1.1751088 | ... CQ13: =CP13*(1+CQ12/100) -> 3.5619491
A14: Inflasjonsforutsetning dr.kost og investeringer | B14: =Investments!D31 -> 4.9 | C14: =Investments!E31 -> 4.2 | D14: =Investments!F31 -> 2.6 | E14: =Investments!G31 -> 2.7 | F14: =Investments!H31 -> 6.5 | G14: =Investments!I31 -> -0.1 | H14: =Investments!J31 -> 2.7 | I14: =Investments!K31 -> 1.7 | ... CQ14: =Investments!CS31 -> 2
A15: Prisindeks driftskostnader og investeringer | B15: =Investments!D32 -> 0.49019996 | C15: =Investments!E32 -> 0.51078836 | D15: =Investments!F32 -> 0.52406886 | E15: =Investments!G32 -> 0.53821872 | F15: =Investments!H32 -> 0.57320293 | G15: =Investments!I32 -> 0.57262973 | H15: =Investments!J32 -> 0.58809073 | I15: =Investments!K32 -> 0.59808828 | ... CQ15: =Investments!CS32 -> 4.5377094
A16: Omregningsfaktor Sm3 o.e.=> fat | B16: 6.28981 | C16: 6.28981 | D16: 6.28981 | E16: 6.28981 | F16: 6.28981 | G16: 6.28981 | H16: 6.28981 | I16: 6.28981 | J16: 6.28981 | K16: 6.28981 | L16: 6.28981 | M16: 6.28981 | N16: 6.28981 | O16: 6.28981 | P16: 6.28981 | Q16: 6.28981 | R16: 6.28981 | S16: 6.28981 | T16: 6.28981 | U16: 6.28981 | V16: 6.28981 | W16: 6.28981 | X16: 6.28981 | Y16: 6.28981 | Z16: 6.28981 | AA16: 6.28981 | AB16: 6.28981 | AC16: 6.28981 | AD16: 6.28981 | AE16: 6.28981 | AF16: 6.28981 | AG16: 6.28981 | AH16: 6.28981 | AI16: 6.28981 | AJ16: 6.28981 | AK16: 6.28981 | AL16: 6.28981 | AM16: 6.28981 | AN16: 6.28981 | AO16: 6.28981 | AP16: 6.28981 | AQ16: 6.28981 | AR16: 6.28981 | AS16: 6.28981 | AT16: 6.28981 | AU16: 6.28981 | AV16: 6.28981 | AW16: 6.28981 | AX16: 6.28981 | AY16: 6.28981 | AZ16: 6.28981 | BA16: 6.28981 | BB16: 6.28981 | BC16: 6.28981 | BD16: 6.28981 | BE16: 6.28981 | BF16: 6.28981 | BG16: 6.28981 | BH16: 6.28981 | BI16: 6.28981 | BJ16: 6.28981 | BK16: 6.28981 | BL16: 6.28981 | BM16: 6.28981 | BN16: 6.28981 | BO16: 6.28981 | BP16: 6.28981 | BQ16: 6.28981 | BR16: 6.28981 | BS16: 6.28981 | BT16: 6.28981 | BU16: 6.28981 | BV16: 6.28981 | BW16: 6.28981 | BX16: 6.28981 | BY16: 6.28981 | BZ16: 6.28981 | CA16: 6.28981 | CB16: 6.28981 | CC16: 6.28981 | CD16: 6.28981 | CE16: 6.28981 | CF16: 6.28981 | CG16: 6.28981 | CH16: 6.28981 | CI16: 6.28981 | CJ16: 6.28981 | CK16: 6.28981 | CL16: 6.28981 | CM16: 6.28981 | CN16: 6.28981 | CO16: 6.28981 | CP16: 6.28981 | CQ16: 6.28981
A17: Omregningsfaktor tonn => sm3 for NGL | B17: 1.9 | C17: 1.9 | D17: 1.9 | E17: 1.9 | F17: 1.9 | G17: 1.9 | H17: 1.9 | I17: 1.9 | J17: 1.9 | K17: 1.9 | L17: 1.9 | M17: 1.9 | N17: 1.9 | O17: 1.9 | P17: 1.9 | Q17: 1.9 | R17: 1.9 | S17: 1.9 | T17: 1.9 | U17: 1.9 | V17: 1.9 | W17: 1.9 | X17: 1.9 | Y17: 1.9 | Z17: 1.9 | AA17: 1.9 | AB17: 1.9 | AC17: 1.9 | AD17: 1.9 | AE17: 1.9 | AF17: 1.9 | AG17: 1.9 | AH17: 1.9 | AI17: 1.9 | AJ17: 1.9 | AK17: 1.9 | AL17: 1.9 | AM17: 1.9 | AN17: 1.9 | AO17: 1.9 | AP17: 1.9 | AQ17: 1.9 | AR17: 1.9 | AS17: 1.9 | AT17: 1.9 | AU17: 1.9 | AV17: 1.9 | AW17: 1.9 | AX17: 1.9 | AY17: 1.9 | AZ17: 1.9 | BA17: 1.9 | BB17: 1.9 | BC17: 1.9 | BD17: 1.9 | BE17: 1.9 | BF17: 1.9 | BG17: 1.9 | BH17: 1.9 | BI17: 1.9 | BJ17: 1.9 | BK17: 1.9 | BL17: 1.9 | BM17: 1.9 | BN17: 1.9 | BO17: 1.9 | BP17: 1.9 | BQ17: 1.9 | BR17: 1.9 | BS17: 1.9 | BT17: 1.9 | BU17: 1.9 | BV17: 1.9 | BW17: 1.9 | BX17: 1.9 | BY17: 1.9 | BZ17: 1.9 | CA17: 1.9 | CB17: 1.9 | CC17: 1.9 | CD17: 1.9 | CE17: 1.9 | CF17: 1.9 | CG17: 1.9 | CH17: 1.9 | CI17: 1.9 | CJ17: 1.9 | CK17: 1.9 | CL17: 1.9 | CM17: 1.9 | CN17: 1.9 | CO17: 1.9 | CP17: 1.9 | CQ17: 1.9
A18: Prisvekst rørtransport | B18: 8.1 | C18: 11.5 | D18: 13.4 | E18: -2.9 | F18: -7.4 | G18: 3.3 | H18: 27.9 | I18: -32.8 | J18: 0 | K18: 0 | L18: 0 | M18: 0 | N18: 0 | O18: 0 | P18: 0 | Q18: 0 | R18: 0 | S18: 0 | T18: 0 | U18: 0 | V18: 0 | W18: 0 | X18: 0 | Y18: 0 | Z18: 0 | AA18: 0 | AB18: 0 | AC18: 0 | AD18: 0 | AE18: 0 | AF18: 0 | AG18: 0 | AH18: 0 | AI18: 0 | AJ18: 0 | AK18: 0 | AL18: 0 | AM18: 0 | AN18: 0 | AO18: 0 | AP18: 0 | AQ18: 0 | AR18: 0 | AS18: 0 | AT18: 0 | AU18: 0 | AV18: 0 | AW18: 0 | AX18: 0 | AY18: 0 | AZ18: 0 | BA18: 0 | BB18: 0 | BC18: 0 | BD18: 0 | BE18: 0 | BF18: 0 | BG18: 0 | BH18: 0 | BI18: 0 | BJ18: 0 | BK18: 0 | BL18: 0 | BM18: 0 | BN18: 0 | BO18: 0 | BP18: 0 | BQ18: 0 | BR18: 0 | BS18: 0 | BT18: 0 | BU18: 0 | BV18: 0 | BW18: 0 | BX18: 0 | BY18: 0 | BZ18: 0 | CA18: 0 | CB18: 0 | CC18: 0 | CD18: 0 | CE18: 0 | CF18: 0 | CG18: 0 | CH18: 0 | CI18: 0 | CJ18: 0 | CK18: 0 | CL18: 0 | CM18: 0 | CN18: 0 | CO18: 0 | CP18: 0 | CQ18: 0
A19: Prisindeks rørtransport | B19: =C19/(1+C18/100) -> 0.99069899 | C19: =D19/(1+D18/100) -> 1.1046294 | D19: =E19/(1+E18/100) -> 1.2526497 | E19: =F19/(1+F18/100) -> 1.2163229 | F19: =G19/(1+G18/100) -> 1.126315 | G19: =H19/(1+H18/100) -> 1.1634834 | H19: =I19/(1+I18/100) -> 1.4880952 | I19: =J19/(1+J18/100) -> 1 | ... Q19: =R19/(1+R18/100) -> 1 | R19: 1 | S19: =R19*(1+S18/100) -> 1 | T19: =S19*(1+T18/100) -> 1 | U19: =T19*(1+U18/100) -> 1 | V19: =U19*(1+V18/100) -> 1 | W19: =V19*(1+W18/100) -> 1 | X19: =W19*(1+X18/100) -> 1 | Y19: =X19*(1+Y18/100) -> 1 | Z19: =Y19*(1+Z18/100) -> 1 | ... CQ19: =CP19*(1+CQ18/100) -> 1
A24: Oljepris (Faste priser) | B24: =B5/B13 -> 283.05089 | C24: =C5/C13 -> 198.45761 | D24: =D5/D13 -> 270.8684 | E24: =E5/E13 -> 488.38021 | F24: =F5/F13 -> 421.97384 | G24: =G5/G13 -> 368.81779 | H24: =H5/H13 -> 366.09523 | I24: =I5/I13 -> 452.33899 | ... AC24: =AC5/AC13 -> 914.3073 | AD24: =AD31*AD11 -> 746.45804 | AE24: =AE31*AE11 -> 674.49527 | AF24: =AF31*AF11 -> 660.10216 | AG24: =AG31*AG11 -> 650.15521 | AH24: =AH31*AH11 -> 639.7047 | AI24: =AI31*AI11 -> 627.57292 | AJ24: =AJ31*AJ11 -> 644.51305 | AK24: =AK31*AK11 -> 661.45318 | ... CQ24: =CQ31*CQ11 -> 712.27491
A25: Gasspris (Faste priser) | B25: =B6/B13 -> 1.356784 | C25: =C6/C13 -> 1.3154903 | D25: =D6/D13 -> 1.1062935 | E25: =E6/E13 -> 1.9262805 | F25: =F6/F13 -> 2.2896339 | G25: =G6/G13 -> 1.7136988 | H25: =H6/H13 -> 1.602805 | I25: =I6/I13 -> 1.720662 | ... AB25: =AB6/AB13 -> 5.9850571 | AC25: 4.727289 | AD25: 5.3241062 | AE25: 3.9871306 | AF25: 3.1820369 | AG25: 3.1820369 | AH25: 3.1820369 | AI25: 2.5294211 | AJ25: 2.4956953 | AK25: 2.4619696 | AL25: 2.4282438 | AM25: 2.3945181 | AN25: 2.3607923 | AO25: 2.3270666 | AP25: 2.2933408 | AQ25: 2.259615 | AR25: 2.2258893 | AS25: 2.1921649 | AT25: 2.1921649 | AU25: 2.1921649 | AV25: 2.1921649 | AW25: 2.1921649 | AX25: 2.1921649 | AY25: 2.1921649 | AZ25: 2.1921649 | BA25: 2.1921649 | BB25: 2.1921649 | BC25: 2.1921649 | BD25: 2.1921649 | BE25: 2.1921649 | BF25: 2.1921649 | BG25: 2.1921649 | BH25: 2.1921649 | BI25: 2.1921649 | BJ25: 2.1921649 | BK25: 2.1921649 | BL25: 2.1921649 | BM25: 2.1921649 | BN25: =BM25 -> 2.1921649 | BO25: =BN25 -> 2.1921649 | BP25: =BO25 -> 2.1921649 | BQ25: =BP25 -> 2.1921649 | BR25: =BQ25 -> 2.1921649 | BS25: =BR25 -> 2.1921649 | BT25: =BS25 -> 2.1921649 | BU25: =BT25 -> 2.1921649 | ... CQ25: =CP25 -> 2.1921649
A26: NGL-pris (Faste priser) ((NOK per Sm3) | B26: =B8/B$13 -> 2074.0635 | C26: =C8/C$13 -> 1264.5767 | D26: =D8/D$13 -> 2047.5883 | E26: =E8/E$13 -> 3341.3573 | F26: =F8/F$13 -> 2888.288 | G26: =G8/G$13 -> 2565.1464 | H26: =H8/H$13 -> 1991.0642 | I26: =I8/I$13 -> 2363.033 | ... CQ26: =CQ8/CQ$13 -> 0
A27: Gasspris (Faste priser) (USD per MMBtu) | B27: =(26.38/B11)*B25 -> 5.0750742 | C27: =(26.38/C11)*C25 -> 4.5963753 | D27: =(26.38/D11)*D25 -> 3.7272058 | E27: =(26.38/E11)*E25 -> 5.7744636 | F27: =(26.38/F11)*F25 -> 6.7240638 | G27: =(26.38/G11)*G25 -> 5.6668641 | H27: =(26.38/H11)*H25 -> 5.9747673 | I27: =(26.38/I11)*I25 -> 6.7371697 | ... CQ27: =(26.38/CQ11)*CQ25 -> 5.7180258
A28: Gasspris (Løpende priser) (USD per MMBtu) | B28: =(26.38/B11)*B6 -> 2.4313364 | C28: =(26.38/C11)*C6 -> 2.2361854 | D28: =(26.38/D11)*D6 -> 1.8530013 | E28: =(26.38/E11)*E6 -> 2.96775 | F28: =(26.38/F11)*F6 -> 3.5534577 | G28: =(26.38/G11)*G6 -> 3.0422586 | H28: =(26.38/H11)*H6 -> 3.2803711 | I28: =(26.38/I11)*I6 -> 3.7979885 | ... CQ28: =(26.38/CQ11)*CQ6 -> 20.367317
A30: Oljepris i USD (løpende priser) | B30: =B5/B11 -> 19.227556 | C30: =C5/C11 -> 12.788309 | D30: =D5/D11 -> 17.198435 | E30: =E5/E11 -> 28.522727 | F30: =F5/F11 -> 24.825377 | G30: =G5/G11 -> 24.819824 | H30: =H5/H11 -> 28.402827 | I30: =I5/I11 -> 37.848381 | ... W30: =W5/W11 -> 71.621079 | X30: =X31*X13 -> 64.063973 | Y30: =Y31*Y13 -> 43.29603 | Z30: =Z31*Z13 -> 70.852685 | AA30: =AA31*AA13 -> 98.895728 | AB30: =AB31*AB13 -> 82.074753 | AC30: =AC31*AC13 -> 79.62415 | AD30: =AD31*AD13 -> 69.59195 | AE30: =AE31*AE13 -> 66.6925 | ... CQ30: =CQ31*CQ13 -> 250.86117
A31: Oljepris i USD (Faste priser) | B31: =B24/B11 -> 40.13483 | C31: =C24/C11 -> 26.285776 | D31: =D24/D11 -> 34.593666 | E31: =E24/E11 -> 55.497751 | F31: =F24/F11 -> 46.976053 | G31: =G24/G11 -> 46.232286 | H31: =H24/H11 -> 51.732038 | I31: =I24/I11 -> 67.138424 | ... AC31: =AC24/AC11 -> 85.047828 | AD31: 71.7493 | AE31: 66.6925 | AF31: 65.269344 | AG31: 64.285812 | AH31: 63.252491 | AI31: 62.052929 | AJ31: 63.727929 | AK31: 65.402929 | AL31: 67.077929 | AM31: 68.752929 | AN31: 70.428062 | AO31: =AN31 -> 70.428062 | AP31: =AO31 -> 70.428062 | AQ31: =AP31 -> 70.428062 | AR31: =AQ31 -> 70.428062 | AS31: =AR31 -> 70.428062 | AT31: =AS31 -> 70.428062 | AU31: =AT31 -> 70.428062 | AV31: =AU31 -> 70.428062 | ... CQ31: =CP31 -> 70.428062
A33: Oljepris NOK/Sm3 o.e. Løpende priser | B33: =B5*B16 -> 852.91293 | C33: =C5*C16 -> 607.29206 | D33: =D5*D16 -> 847.00937 | E33: =E5*E16 -> 1578.7423 | F33: =F5*F16 -> 1402.6276 | G33: =G5*G16 -> 1245.3824 | H33: =H5*H16 -> 1264.2518 | I33: =I5*I16 -> 1603.9016 | ... BM33: =BM5*BM16 -> 8809.834 | BN33: =BM33*(1+$AI$12/100) -> 8986.0307 | BO33: =BN33*(1+$AI$12/100) -> 9165.7513 | BP33: =BO33*(1+$AI$12/100) -> 9349.0663 | BQ33: =BP33*(1+$AI$12/100) -> 9536.0476 | BR33: =BQ33*(1+$AI$12/100) -> 9726.7686 | BS33: =BR33*(1+$AI$12/100) -> 9921.3039 | BT33: =BS33*(1+$AI$12/100) -> 10119.73 | BU33: =BT33*(1+$AI$12/100) -> 10322.125 | ... CQ33: =CP33*(1+$AI$12/100) -> 15957.795
A34: Gasspris NOK/Sm3 o.e.Løpende priser | B34: =B6*1000 -> 650 | C34: =C6*1000 -> 640 | D34: =D6*1000 -> 550 | E34: =E6*1000 -> 990 | F34: =F6*1000 -> 1210 | G34: =G6*1000 -> 920 | H34: =H6*1000 -> 880 | I34: =I6*1000 -> 970 | ... BM34: =BM6*1000 -> 4310.7792 | BN34: =BM34*(1+$AI$12/100) -> 4396.9948 | BO34: =BN34*(1+$AI$12/100) -> 4484.9347 | BP34: =BO34*(1+$AI$12/100) -> 4574.6334 | BQ34: =BP34*(1+$AI$12/100) -> 4666.1261 | BR34: =BQ34*(1+$AI$12/100) -> 4759.4486 | BS34: =BR34*(1+$AI$12/100) -> 4854.6376 | BT34: =BS34*(1+$AI$12/100) -> 4951.7303 | BU34: =BT34*(1+$AI$12/100) -> 5050.7649 | ... CQ34: =CP34*(1+$AI$12/100) -> 7808.3799
A35: Gasspris innenlandske leveranser NOK/Sm3 o.e.Løpende priser | B35: =B7*1000 -> 0 | C35: =C7*1000 -> 0 | D35: =D7*1000 -> 0 | E35: =E7*1000 -> 0 | F35: =F7*1000 -> 0 | G35: =G7*1000 -> 0 | H35: =H7*1000 -> 610 | I35: =I7*1000 -> 610 | ... BM35: =BM7*1000 -> 0 | BN35: =BM35*(1+$AI$12/100) -> 0 | BO35: =BN35*(1+$AI$12/100) -> 0 | BP35: =BO35*(1+$AI$12/100) -> 0 | BQ35: =BP35*(1+$AI$12/100) -> 0 | BR35: =BQ35*(1+$AI$12/100) -> 0 | BS35: =BR35*(1+$AI$12/100) -> 0 | BT35: =BS35*(1+$AI$12/100) -> 0 | BU35: =BT35*(1+$AI$12/100) -> 0 | ... CQ35: =CP35*(1+$AI$12/100) -> 0
A36: NGL-pris kr/Sm3 o.e.Løpende priser | B36: =B8 -> 993.63 | C36: =C8 -> 615.23 | D36: =D8 -> 1017.97 | E36: =E8 -> 1717.27 | F36: =F8 -> 1526.37 | G36: =G8 -> 1377.1 | H36: =H8 -> 1093.1689 | I36: =I8 -> 1332.128 | ... BM36: =BM8 -> 5111.4616 | BN36: =BM36*(1+$AI$12/100) -> 5213.6909 | BO36: =BN36*(1+$AI$12/100) -> 5317.9647 | BP36: =BO36*(1+$AI$12/100) -> 5424.324 | BQ36: =BP36*(1+$AI$12/100) -> 5532.8104 | BR36: =BQ36*(1+$AI$12/100) -> 5643.4667 | BS36: =BR36*(1+$AI$12/100) -> 5756.336 | BT36: =BS36*(1+$AI$12/100) -> 5871.4627 | BU36: =BT36*(1+$AI$12/100) -> 5988.892 | ... CQ36: =CP36*(1+$AI$12/100) -> 9258.7052
A37: Gjennomsnittspris for olje og NGL. Løpende priser | B37: =(B80+B82)/(B62+B64) -> 862.90789 | C37: =(C80+C82)/(C62+C64) -> 607.83709 | D37: =(D80+D82)/(D62+D64) -> 858.80367 | E37: =(E80+E82)/(E62+E64) -> 1587.7764 | F37: =(F80+F82)/(F62+F64) -> 1413.0236 | G37: =(G80+G82)/(G62+G64) -> 1258.4469 | H37: =(H80+H82)/(H62+H64) -> 1243.1599 | I37: =(I80+I82)/(I62+I64) -> 1571.1431 | ... BM37: =(BM80+BM82)/(BM62+BM64) -> 8803.6546 | BN37: =(BN80+BN82)/(Formue!BK30+Formue!BK32) -> 8979.7277 | BO37: =(BO80+BO82)/(Formue!BL30+Formue!BL32) -> 9159.3223 | BP37: =(BP80+BP82)/(Formue!BM30+Formue!BM32) -> 9342.5087 | BQ37: =(BQ80+BQ82)/(Formue!BN30+Formue!BN32) -> 9529.3589 | BR37: =(BR80+BR82)/(Formue!BO30+Formue!BO32) -> 9719.9461 | BS37: =(BS80+BS82)/(Formue!BP30+Formue!BP32) -> 9914.345 | BT37: =(BT80+BT82)/(Formue!BQ30+Formue!BQ32) -> 10112.632 | BU37: =(BU80+BU82)/(Formue!BR30+Formue!BR32) -> 10314.885 | ... CQ37: =(CQ80+CQ82)/(Formue!CN30+Formue!CN32) -> 15946.602
A39: Prisindeks (2013 = 1)
A40: Olje | G40: =G33/$S$33 -> 0.31578947 | H40: =H33/$S$33 -> 0.32057416 | I40: =I33/$S$33 -> 0.40669856 | J40: =J33/$S$33 -> 0.5661882 | K40: =K33/$S$33 -> 0.67464115 | L40: =L33/$S$33 -> 0.67783094 | M40: =M33/$S$33 -> 0.88676236 | N40: =N33/$S$33 -> 0.62360447 | ... CQ40: =CQ33/$S$33 -> 4.0463907
A41: Gass | G41: =G34/$S$34 -> 0.44878049 | H41: =H34/$S$34 -> 0.42926829 | I41: =I34/$S$34 -> 0.47317073 | J41: =J34/$S$34 -> 0.6097561 | K41: =K34/$S$34 -> 0.84878049 | L41: =L34/$S$34 -> 0.76585366 | M41: =M34/$S$34 -> 1.0829268 | N41: =N34/$S$34 -> 0.81463415 | ... CQ41: =CQ34/$S$34 -> 3.8089658
A42: NGL | G42: =G36/$S$36 -> 0.58542334 | H42: =H36/$S$36 -> 0.46472048 | I42: =I36/$S$36 -> 0.56630513 | J42: =J36/$S$36 -> 0.78520375 | K42: =K36/$S$36 -> 0.83559773 | L42: =L36/$S$36 -> 0.7714327 | M42: =M36/$S$36 -> 1.0717482 | N42: =N36/$S$36 -> 0.74969443 | ... CQ42: =CQ36/$S$36 -> 3.9359975
A43: Prisindeks olje og NGL | G43: =G37/$S$37 -> 0.34704412 | H43: =H37/$S$37 -> 0.3428284 | I43: =I37/$S$37 -> 0.4332769 | J43: =J37/$S$37 -> 0.601059 | K43: =K37/$S$37 -> 0.70473579 | L43: =L37/$S$37 -> 0.70558321 | M43: =M37/$S$37 -> 0.92528888 | N43: =N37/$S$37 -> 0.64809201 | ... CQ43: =CQ37/$S$37 -> 4.3976226
A46: Prisvekst
A47: Olje | H47: =(H40/G40-1)*100 -> 1.5151515 | I47: =(I40/H40-1)*100 -> 26.865672 | J47: =(J40/I40-1)*100 -> 39.215686 | K47: =(K40/J40-1)*100 -> 19.15493 | L47: =(L40/K40-1)*100 -> 0.47281324 | M47: =(M40/L40-1)*100 -> 30.823529 | N47: =(N40/M40-1)*100 -> -29.676259 | O47: =(O40/N40-1)*100 -> 24.040921 | ... CQ47: =(CQ40/CP40-1)*100 -> 2
A48: Gass | H48: =(H41/G41-1)*100 -> -4.3478261 | I48: =(I41/H41-1)*100 -> 10.227273 | J48: =(J41/I41-1)*100 -> 28.865979 | K48: =(K41/J41-1)*100 -> 39.2 | L48: =(L41/K41-1)*100 -> -9.7701149 | M48: =(M41/L41-1)*100 -> 41.401274 | N48: =(N41/M41-1)*100 -> -24.774775 | O48: =(O41/N41-1)*100 -> -4.7904192 | ... CQ48: =(CQ41/CP41-1)*100 -> 2
A49: NGL | H49: =(H42/G42-1)*100 -> -20.618047 | I49: =(I42/H42-1)*100 -> 21.859301 | J49: =(J42/I42-1)*100 -> 38.653829 | K49: =(K42/J42-1)*100 -> 6.4179492 | L49: =(L42/K42-1)*100 -> -7.6789376 | M49: =(M42/L42-1)*100 -> 38.929575 | N49: =(N42/M42-1)*100 -> -30.049386 | O49: =(O42/N42-1)*100 -> 24.701682 | ... CQ49: =(CQ42/CP42-1)*100 -> 2
A50: Olje og NGL | H50: =(H43/G43-1)*100 -> -1.2147493 | I50: =(I43/H43-1)*100 -> 26.383024 | J50: =(J43/I43-1)*100 -> 38.723989 | K50: =(K43/J43-1)*100 -> 17.249021 | L50: =(L43/K43-1)*100 -> 0.12024568 | M50: =(M43/L43-1)*100 -> 31.138166 | N50: =(N43/M43-1)*100 -> -29.957873 | O50: =(O43/N43-1)*100 -> 24.048797 | ... CQ50: =(CQ43/CP43-1)*100 -> 2
A53: Andre sektorstørrelser
A54: Vareinnsats utvinningssektor | B54: 11411 | C54: 16782 | D54: 18017 | E54: 20308 | F54: 24757 | G54: 26599 | H54: 25936 | I54: 26721 | J54: 26469 | K54: 30009 | L54: 36294 | M54: 48186 | N54: 47875 | O54: 49795 | P54: 60774 | Q54: 56993 | R54: 58709 | S54: 66905 | T54: 70887 | U54: 63402 | V54: 48616.897 | W54: 53112.032 | X54: 55830.964 | Y54: 53825.904 | Z54: 58224.558 | AA54: 66761.936 | AB54: 70371.718 | AC54: 64118.293 | AD54: 66772.102 | AE54: 74824.551 | AF54: 74025.604 | AG54: 72775.133 | AH54: 72987.97 | AI54: 71646.601 | AJ54: 71125.616 | AK54: 69683.744 | AL54: 73401.787 | AM54: 74009.469 | AN54: 76030.408 | AO54: 75512.978 | AP54: 76146.071 | AQ54: 77813.45 | AR54: 78212.05 | AS54: 77756.284 | AT54: 81056.327 | AU54: 79685.332 | AV54: 79722.825 | AW54: 79973.35 | AX54: 81029.198 | AY54: 80248.271 | AZ54: 81662.766 | BA54: 79797.181 | BB54: 78508.67 | BC54: 78837.881 | BD54: 77699.661 | BE54: 79951.759 | BF54: 81288.863 | BG54: 82344.157 | BH54: 80577.835 | BI54: 76347.104 | BJ54: 77660.912 | BK54: 78288.631 | BL54: 76018.176 | BM54: 73905.234
A55: Vareinnsats rørtransportsektor | B55: 1400 | C55: 1667 | D55: 1697 | E55: 1932 | F55: 1905 | G55: 2050 | H55: 2412 | I55: 2625 | J55: 2506 | K55: 2596 | L55: 2997 | M55: 4283 | N55: 4027 | O55: 4228 | P55: 3899 | Q55: 4701 | R55: 4563 | S55: 4848 | T55: 4334 | U55: 4297 | V55: 3501.3657 | W55: 3802.2125 | X55: 3844.9051 | Y55: 3884.8381 | Z55: 4507.2102 | AA55: 7829.0442 | AB55: 7669.2294 | AC55: 8427.2587 | AD55: 10824.319 | AE55: 10519.109 | AF55: 10328.239 | AG55: 11290.619 | AH55: 10436.901 | AI55: 10252.423 | AJ55: 10470.921 | AK55: 11169.443 | AL55: 11579.099 | AM55: 11683.878 | AN55: 11597.208 | AO55: 11289.162 | AP55: 11437.579 | AQ55: 11952.058 | AR55: 12786.869 | AS55: 12983.134 | AT55: 12638.16 | AU55: 13520.462 | AV55: 13370.464 | AW55: 13252.903 | AX55: 13208.646 | AY55: 13023.224 | AZ55: 13221.623 | BA55: 13360.892 | BB55: 13501.108 | BC55: 10397.85 | BD55: 10516.033 | BE55: 8702.8202 | BF55: 8177.5336 | BG55: 8363.6427 | BH55: 7892.1499 | BI55: 7128.5042 | BJ55: 7248.1512 | BK55: 7377.2375 | BL55: 7489.7073 | BM55: 7610.5072
A56: Vareinnsats petroleumssektor | B56: =SUM(B54:B55) -> 12811 | C56: =SUM(C54:C55) -> 18449 | D56: =SUM(D54:D55) -> 19714 | E56: =SUM(E54:E55) -> 22240 | F56: =SUM(F54:F55) -> 26662 | G56: =SUM(G54:G55) -> 28649 | H56: =SUM(H54:H55) -> 28348 | I56: =SUM(I54:I55) -> 29346 | ... BM56: =SUM(BM54:BM55) -> 81515.741
A57: Vareinnsats (faste kroner) | B57: =B56/B15 -> 26134.233 | C57: =C56/C15 -> 36118.677 | D57: =D56/D15 -> 37617.194 | E57: =E56/E15 -> 41321.491 | F57: =F56/F15 -> 46514.068 | G57: =G56/G15 -> 50030.584 | H57: =H56/H15 -> 48203.446 | I57: =I56/I15 -> 49066.335 | ... BM57: =BM56/BM15 -> 32539.431 | BN57: =BM57*Formue!BK54/Formue!BJ54 -> 33060.062 | BO57: =BN57*Formue!BL54/Formue!BK54 -> 33589.023 | BP57: =BO57*Formue!BM54/Formue!BL54 -> 34126.447 | BQ57: =BP57*Formue!BN54/Formue!BM54 -> 34672.471 | BR57: =BQ57*Formue!BO54/Formue!BN54 -> 35227.23 | BS57: =BR57*Formue!BP54/Formue!BO54 -> 35790.866 | BT57: =BS57*Formue!BQ54/Formue!BP54 -> 36363.52 | BU57: =BT57*Formue!BR54/Formue!BQ54 -> 36945.336 | ... CQ57: =CP57*Formue!CN54/Formue!CM54 -> 52386.719
A61: Produksjon Mill. SM3. o.e. | AA61: Tall tom. 2023 oppdatert 17.01.2025 med Norsk Petroleum
A62: Produksjon av råolje | B62: 175.91 | C62: 168.74 | D62: 168.69 | E62: 181.18 | F62: 180.88 | G62: 173.65 | H62: 165.48 | I62: 162.78 | J62: 148.14 | K62: 136.58 | L62: 128.28 | M62: 122.66 | N62: 114.94 | O62: 104.39 | P62: 97.46 | Q62: 89.2 | R62: 84.94 | S62: 87.7 | T62: 90.85 | U62: 93.9 | V62: 92.28 | W62: 86.27 | X62: 83.21 | Y62: 98.49 | Z62: 102.36 | AA62: 97.81 | AB62: 104.14 | AC62: 102.88638 | AD62: 105.18981 | AE62: 101.04576 | AF62: 96.575067 | AG62: 87.047892 | AH62: 78.845848 | AI62: 73.793909 | AJ62: 71.649847 | AK62: 70.715986 | AL62: 69.386447 | AM62: 69.474901 | AN62: 69.035837 | AO62: 67.882734 | AP62: 66.422217 | AQ62: 63.92065 | AR62: 61.744995 | AS62: 59.765761 | AT62: 58.160948 | AU62: 56.304565 | AV62: 54.58072 | AW62: 53.233861 | AX62: 51.418463 | AY62: 49.851933 | AZ62: 48.074596 | BA62: 46.791757 | BB62: 45.026559 | BC62: 43.367769 | BD62: 42.037652 | BE62: 40.516113 | BF62: 39.141345 | BG62: 37.644953 | BH62: 36.054581 | BI62: 34.609853 | BJ62: 33.132616 | BK62: 31.356615 | BL62: 29.729547 | BM62: 28.071747
A63: Produksjon av naturgass (40 MJ) | B63: 44.36 | C63: 47.06 | D63: 48.7 | E63: 47.43 | F63: 54.15 | G63: 65.53 | H63: 72.93 | I63: 79.1 | J63: 85.67 | K63: 88.23 | L63: 89.51 | M63: 99.46 | N63: 103.68 | O63: 106.53 | P63: 100.3 | Q63: 113.06 | R63: 107.05 | S63: 106.8 | T63: 114.92 | U63: 114.65 | V63: 122.37 | W63: 119.89 | X63: 113.12 | Y63: 110.11 | Z63: 113.08 | AA63: 122.85 | AB63: 116.02 | AC63: 124.23875 | AD63: 118.45207 | AE63: 120.08612 | AF63: 120.09464 | AG63: 116.16609 | AH63: 110.63627 | AI63: 104.94158 | AJ63: 100.13045 | AK63: 93.491734 | AL63: 89.335085 | AM63: 86.735573 | AN63: 84.333942 | AO63: 82.15377 | AP63: 78.84047 | AQ63: 73.883116 | AR63: 68.539687 | AS63: 64.692186 | AT63: 61.229098 | AU63: 58.607326 | AV63: 55.86234 | AW63: 52.787278 | AX63: 50.28289 | AY63: 48.339968 | AZ63: 46.446473 | BA63: 44.699381 | BB63: 43.293509 | BC63: 41.648786 | BD63: 40.11869 | BE63: 38.369959 | BF63: 36.903521 | BG63: 35.812746 | BH63: 35.209139 | BI63: 34.416162 | BJ63: 33.891619 | BK63: 33.466268 | BL63: 32.995546 | BM63: 32.602377
A64: Produksjon av NGL og kondensat | B64: 13.45 | C64: 12.44 | D64: 12.5 | E64: 12.64 | F64: 16.59 | G64: 19.12 | H64: 23.27 | I64: 22.31 | J64: 23.76 | K64: 24.33 | L64: 19.76 | M64: 20.86 | N64: 21.4 | O64: 19.72 | P64: 20.89 | Q64: 22.38 | R64: 21.71 | S64: 21.86 | T64: 22.07 | U64: 22.11 | V64: 22.1 | W64: 21.17 | X64: 19.08 | Y64: 18.25 | Z64: 15.31 | AA64: 12.53 | AB64: 12.99 | AC64: 14.090806 | AD64: 14.526417 | AE64: 15.282594 | AF64: 15.416935 | AG64: 15.381716 | AH64: 15.123827 | AI64: 14.458168 | AJ64: 12.999657 | AK64: 12.101043 | AL64: 10.703649 | AM64: 9.5442072 | AN64: 8.4064846 | AO64: 7.6252251 | AP64: 6.5501176 | AQ64: 5.5222164 | AR64: 4.8854317 | AS64: 4.4192167 | AT64: 3.9106155 | AU64: 3.5138656 | AV64: 3.1591643 | AW64: 2.7467847 | AX64: 2.4737211 | AY64: 2.0487444 | AZ64: 1.9173435 | BA64: 1.4773356 | BB64: 1.1472303 | BC64: 0.95530164 | BD64: 0.78101942 | BE64: 0.53412031 | BF64: 0.42513032 | BG64: 0.30469154 | BH64: 0.20867618 | BI64: 0.13997564 | BJ64: 0.076948321 | BK64: 0.072522703 | BL64: 0.067570853 | BM64: 0.046981571
A65: Samlet produksjon av olje og NGL | B65: =B62+B64 -> 189.36 | C65: =C62+C64 -> 181.18 | D65: =D62+D64 -> 181.19 | E65: =E62+E64 -> 193.82 | F65: =F62+F64 -> 197.47 | G65: =G62+G64 -> 192.77 | H65: =H62+H64 -> 188.75 | I65: =I62+I64 -> 185.09 | ... BM65: =BM62+BM64 -> 28.118729
A66: Samlet produksjon | B66: =B65+B63 -> 233.72 | C66: =C65+C63 -> 228.24 | D66: =D65+D63 -> 229.89 | E66: =E65+E63 -> 241.25 | F66: =F65+F63 -> 251.62 | G66: =G65+G63 -> 258.3 | H66: =H65+H63 -> 261.68 | I66: =I65+I63 -> 264.19 | ... BM66: =BM65+BM63 -> 60.721106
A67: Oljeproduksjon i fat pr. dag | B67: =B16*B62/365 -> 3.0313438 | C67: =C16*C62/365 -> 2.9077878 | D67: =D16*D62/365 -> 2.9069262 | E67: =E16*E62/365 -> 3.1221583 | F67: =F16*F62/365 -> 3.1169886 | G67: =G16*G62/365 -> 2.9923986 | H67: =H16*H62/365 -> 2.8516103 | I67: =I16*I62/365 -> 2.8050829 | ... BM67: =BM16*BM62/365 -> 0.48374234
A68: Olje-/NGL-prod. mill.f/d | B68: =B16*B65/365 -> 3.263119 | C68: =C16*C65/365 -> 3.1221583 | D68: =D16*D65/365 -> 3.1223306 | E68: =E16*E65/365 -> 3.3399753 | F68: =F16*F65/365 -> 3.4028734 | G68: =G16*G65/365 -> 3.3218813 | H68: =H16*H65/365 -> 3.2526072 | I68: =I16*I65/365 -> 3.1895368 | ... BM68: =BM16*BM65/365 -> 0.48455195
A69: Kilde: ODs årsberetning for historiske år og OEDs rapportering | N69: Andel olje | O69: =O62/O66 -> 0.45261013 | P69: =P62/P66 -> 0.44573519 | Q69: =Q62/Q66 -> 0.39707977 | R69: =R62/R66 -> 0.39747309 | S69: =S62/S66 -> 0.40534295 | T69: =T62/T66 -> 0.39874473 | U69: =U62/U66 -> 0.40709269 | V69: =V62/V66 -> 0.38977825 | ... AL69: =AL62/AL66 -> 0.40954034
N70: Andel gass | O70: =O63/O66 -> 0.46188866 | P70: =P63/P66 -> 0.45872399 | Q70: =Q63/Q66 -> 0.50329416 | R70: =R63/R66 -> 0.50093589 | S70: =S63/S66 -> 0.49362174 | T70: =T63/T66 -> 0.50438904 | U70: =U63/U66 -> 0.49705194 | V70: =V63/V66 -> 0.51687434 | ... AL70: =AL63/AL66 -> 0.5272834
A71: Produksjonsvekst pst.
A72: Produksjon av råolje | C72: =(C62/B62-1)*100 -> -4.0759479 | D72: =(D62/C62-1)*100 -> -0.029631386 | E72: =(E62/D62-1)*100 -> 7.4041141 | F72: =(F62/E62-1)*100 -> -0.16558119 | G72: =(G62/F62-1)*100 -> -3.9971252 | H72: =(H62/G62-1)*100 -> -4.7048661 | I72: =(I62/H62-1)*100 -> -1.6316171 | J72: =(J62/I62-1)*100 -> -8.9937339 | ... BM72: =(BM62/BL62-1)*100 -> -5.576271
A73: Produksjon av naturgass | C73: =(C63/B63-1)*100 -> 6.0865645 | D73: =(D63/C63-1)*100 -> 3.4849129 | E73: =(E63/D63-1)*100 -> -2.6078029 | F73: =(F63/E63-1)*100 -> 14.168248 | G73: =(G63/F63-1)*100 -> 21.015697 | H73: =(H63/G63-1)*100 -> 11.292538 | I73: =(I63/H63-1)*100 -> 8.4601673 | J73: =(J63/I63-1)*100 -> 8.3059418 | ... BM73: =(BM63/BL63-1)*100 -> -1.1915821
A74: Produksjon av NGL | C74: =(C64/B64-1)*100 -> -7.5092937 | D74: =(D64/C64-1)*100 -> 0.48231511 | E74: =(E64/D64-1)*100 -> 1.12 | F74: =(F64/E64-1)*100 -> 31.25 | G74: =(G64/F64-1)*100 -> 15.250151 | H74: =(H64/G64-1)*100 -> 21.705021 | I74: =(I64/H64-1)*100 -> -4.1254835 | J74: =(J64/I64-1)*100 -> 6.4993277 | ... BM74: =(BM64/BL64-1)*100 -> -30.470656
A75: Samlet produksjon av olje og NGL | C75: =(C65/B65-1)*100 -> -4.3198141 | D75: =(D65/C65-1)*100 -> 0.005519373 | E75: =(E65/D65-1)*100 -> 6.9705834 | F75: =(F65/E65-1)*100 -> 1.8831906 | G75: =(G65/F65-1)*100 -> -2.3801084 | H75: =(H65/G65-1)*100 -> -2.0853867 | I75: =(I65/H65-1)*100 -> -1.9390728 | J75: =(J65/I65-1)*100 -> -7.1262629 | ... BM75: =(BM65/BL65-1)*100 -> -5.6327239
A76: Samlet produksjon | C76: =(C66/B66-1)*100 -> -2.3446859 | D76: =(D66/C66-1)*100 -> 0.72292324 | E76: =(E66/D66-1)*100 -> 4.9414938 | F76: =(F66/E66-1)*100 -> 4.2984456 | G76: =(G66/F66-1)*100 -> 2.6547969 | H76: =(H66/G66-1)*100 -> 1.3085559 | I76: =(I66/H66-1)*100 -> 0.95918679 | J76: =(J66/I66-1)*100 -> -2.5057724 | ... BM76: =(BM66/BL66-1)*100 -> -3.2990453
A77: Oljeproduksjon i fat pr. dag | C77: =(C67/B67-1)*100 -> -4.0759479 | D77: =(D67/C67-1)*100 -> -0.029631386 | E77: =(E67/D67-1)*100 -> 7.4041141 | F77: =(F67/E67-1)*100 -> -0.16558119 | G77: =(G67/F67-1)*100 -> -3.9971252 | H77: =(H67/G67-1)*100 -> -4.7048661 | I77: =(I67/H67-1)*100 -> -1.6316171 | J77: =(J67/I67-1)*100 -> -8.9937339 | ... BM77: =(BM67/BL67-1)*100 -> -5.576271
A79: Markedsverdi mill. kr | M79: =M81/M83 -> 0.31437505 | N79: =N81/N83 -> 0.35081061 | O79: =O81/O83 -> 0.3188696 | P79: =P81/P83 -> 0.31329188 | Q79: =Q81/Q83 -> 0.3677921 | R79: =R81/R83 -> 0.38056457 | S79: =S81/S83 -> 0.35529228 | T79: =T81/T83 -> 0.43875459 | ... X79: =X81/X83 -> 0.34604674
A80: Olje | B80: =B33*B62 -> 150035.91 | C80: =C33*C62 -> 102474.46 | D80: =D33*D62 -> 142882.01 | E80: =E33*E62 -> 286036.53 | F80: =F33*F62 -> 253707.29 | G80: =G33*G62 -> 216260.65 | H80: =H33*H62 -> 209208.39 | I80: =I33*I62 -> 261083.09 | ... BM80: =BM33*BM62 -> 247307.43 | BN80: =Formue!BK47 -> 252253.58 | BO80: =Formue!BL47 -> 257298.65 | BP80: =Formue!BM47 -> 262444.62 | BQ80: =Formue!BN47 -> 267693.52 | BR80: =Formue!BO47 -> 273047.39 | BS80: =Formue!BP47 -> 278508.33 | BT80: =Formue!BQ47 -> 284078.5 | BU80: =Formue!BR47 -> 289760.07 | ... CQ80: =Formue!CN47 -> 447963.18
A81: Gass | B81: =B34*B63 -> 28834 | C81: =C34*C63 -> 30118.4 | D81: =D34*D63 -> 26785 | E81: =E34*E63 -> 46955.7 | F81: =F34*F63 -> 65521.5 | G81: =G34*G63 -> 60287.6 | H81: =H34*H63 -> 64178.4 | I81: =I34*I63 -> 76727 | ... BM81: =BM34*BM63 -> 140541.65 | BN81: =Formue!BK48 -> 143352.48 | BO81: =Formue!BL48 -> 146219.53 | BP81: =Formue!BM48 -> 149143.92 | BQ81: =Formue!BN48 -> 152126.8 | BR81: =Formue!BO48 -> 155169.34 | BS81: =Formue!BP48 -> 158272.73 | BT81: =Formue!BQ48 -> 161438.18 | BU81: =Formue!BR48 -> 164666.94 | ... CQ81: =Formue!CN48 -> 254571.75
A82: NGL | B82: =B64*B36 -> 13364.323 | C82: =C64*C36 -> 7653.4612 | D82: =D64*D36 -> 12724.625 | E82: =E64*E36 -> 21706.293 | F82: =F64*F36 -> 25322.478 | G82: =G64*G36 -> 26330.152 | H82: =H64*H36 -> 25438.04 | I82: =I64*I36 -> 29719.775 | ... BM82: =BM64*BM36 -> 240.1445 | BN82: =Formue!BK49 -> 244.94739 | BO82: =Formue!BL49 -> 249.84633 | BP82: =Formue!BM49 -> 254.84326 | BQ82: =Formue!BN49 -> 259.94013 | BR82: =Formue!BO49 -> 265.13893 | BS82: =Formue!BP49 -> 270.44171 | BT82: =Formue!BQ49 -> 275.85054 | BU82: =Formue!BR49 -> 281.36755 | ... CQ82: =Formue!CN49 -> 434.98852
A83: Sum | B83: =SUM(B80:B82) -> 192234.24 | C83: =SUM(C80:C82) -> 140246.32 | D83: =SUM(D80:D82) -> 182391.64 | E83: =SUM(E80:E82) -> 354698.52 | F83: =SUM(F80:F82) -> 344551.26 | G83: =SUM(G80:G82) -> 302878.4 | H83: =SUM(H80:H82) -> 298824.83 | I83: =SUM(I80:I82) -> 367529.87 | ... CQ83: =SUM(CQ80:CQ82) -> 702969.91
A85: Markedsverdi mill. 2013-kr
A86: Olje | F86: =(F62*$R$33) -> 726990.83 | G86: =(G62*$R$33) -> 697932.1 | H86: =(H62*$R$33) -> 665095.33 | I86: =(I62*$R$33) -> 654243.52 | J86: =(J62*$R$33) -> 595402.6 | K86: =(K62*$R$33) -> 548940.78 | L86: =(L62*$R$33) -> 515581.51 | M86: =(M62*$R$33) -> 492993.67 | ... BM86: =(BM62*$R$33) -> 112825.65
A87: Gass | F87: =(F63*$R$34) -> 125086.5 | G87: =(G63*$R$34) -> 151374.3 | H87: =(H63*$R$34) -> 168468.3 | I87: =(I63*$R$34) -> 182721 | J87: =(J63*$R$34) -> 197897.7 | K87: =(K63*$R$34) -> 203811.3 | L87: =(L63*$R$34) -> 206768.1 | M87: =(M63*$R$34) -> 229752.6 | ... BM87: =(BM63*$R$34) -> 75311.492
A88: NGL | F88: =(F64*$R36) -> 46698.48 | G88: =(G64*$R36) -> 53820.069 | H88: =(H64*$R36) -> 65501.726 | I88: =(I64*$R36) -> 62799.463 | J88: =(J64*$R36) -> 66881.006 | K88: =(K64*$R36) -> 68485.474 | L88: =(L64*$R36) -> 55621.577 | M88: =(M64*$R36) -> 58717.92 | ... BM88: =(BM64*$R36) -> 132.24641
A89: Sum | F89: =SUM(F86:F87) -> 852077.33 | G89: =SUM(G86:G87) -> 849306.4 | H89: =SUM(H86:H87) -> 833563.63 | I89: =SUM(I86:I87) -> 836964.52 | J89: =SUM(J86:J87) -> 793300.3 | K89: =SUM(K86:K87) -> 752752.08 | L89: =SUM(L86:L87) -> 722349.61 | M89: =SUM(M86:M87) -> 722746.27 | ... BM89: =SUM(BM86:BM87) -> 188137.14
A91: Markedsverdi pst. volumvekst
A92: Olje | G92: =(G86/F86-1)*100 -> -3.9971252 | H92: =(H86/G86-1)*100 -> -4.7048661 | I92: =(I86/H86-1)*100 -> -1.6316171 | J92: =(J86/I86-1)*100 -> -8.9937339 | K92: =(K86/J86-1)*100 -> -7.8034292 | L92: =(L86/K86-1)*100 -> -6.0770245 | M92: =(M86/L86-1)*100 -> -4.3810415 | N92: =(N86/M86-1)*100 -> -6.2938203 | ... BM92: =(BM86/BL86-1)*100 -> -5.576271
A93: Gass | G93: =(G87/F87-1)*100 -> 21.015697 | H93: =(H87/G87-1)*100 -> 11.292538 | I93: =(I87/H87-1)*100 -> 8.4601673 | J93: =(J87/I87-1)*100 -> 8.3059418 | K93: =(K87/J87-1)*100 -> 2.9882106 | L93: =(L87/K87-1)*100 -> 1.4507537 | M93: =(M87/L87-1)*100 -> 11.116076 | N93: =(N87/M87-1)*100 -> 4.2429117 | ... BM93: =(BM87/BL87-1)*100 -> -1.1915821
A94: NGL | G94: =(G88/F88-1)*100 -> 15.250151 | H94: =(H88/G88-1)*100 -> 21.705021 | I94: =(I88/H88-1)*100 -> -4.1254835 | J94: =(J88/I88-1)*100 -> 6.4993277 | K94: =(K88/J88-1)*100 -> 2.3989899 | L94: =(L88/K88-1)*100 -> -18.783395 | M94: =(M88/L88-1)*100 -> 5.5668016 | N94: =(N88/M88-1)*100 -> 2.5886865 | ... BM94: =(BM88/BL88-1)*100 -> -30.470656
A95: Sum | G95: =(G89/F89-1)*100 -> -0.32519742 | H95: =(H89/G89-1)*100 -> -1.8536032 | I95: =(I89/H89-1)*100 -> 0.40799415 | J95: =(J89/I89-1)*100 -> -5.216974 | K95: =(K89/J89-1)*100 -> -5.111333 | L95: =(L89/K89-1)*100 -> -4.0388418 | M95: =(M89/L89-1)*100 -> 0.054912485 | N95: =(N89/M89-1)*100 -> -2.9443162 | ... BM95: =(BM89/BL89-1)*100 -> -3.8686295
A97: Korreksjon for utenlandske rør og terminaler mill. kroner
A98: Råolje (+NGL) | B98: 176 | C98: 350 | D98: 204 | E98: 253 | F98: 265 | G98: 777 | H98: 690 | I98: 778 | J98: 779 | K98: 849 | L98: 1435 | M98: 1474 | N98: 1586 | O98: 1659 | P98: 1111 | Q98: 1011 | R98: 1021 | S98: 1250 | T98: 1568 | U98: 1577 | V98: 1856.4888 | W98: 1838.9909 | X98: 1456.6884 | Y98: 1792.4596 | Z98: 2058.4727 | AA98: 2555.9446 | AB98: 3455.1617 | AC98: 3560.9608 | AD98: 3637.3164 | AE98: 3634.3399 | AF98: 3534.8384 | AG98: 3336.9488 | AH98: 2925.3183 | AI98: 2894.7853 | AJ98: 2923.9194 | AK98: 3508.0545 | AL98: 2861.7243 | AM98: 2635.3021 | AN98: 2545.3204 | AO98: 2402.7368 | AP98: 2493.2653 | AQ98: 2362.4601 | AR98: 2364.8547 | AS98: 2407.8399 | AT98: 2441.8217 | AU98: 2594.9559 | AV98: 2739.3544 | AW98: 2849.8423 | AX98: 2931.8338 | AY98: 2985.7046 | AZ98: 2958.542 | BA98: 2897.3614 | BB98: 1888.7578 | BC98: 1941.3618 | BD98: 1857.5178 | BE98: 1796.9438 | BF98: 1773.3381 | BG98: 1753.841 | BH98: 1667.3447 | BI98: 1641.4201 | BJ98: 1582.4478 | BK98: 1577.3774 | BL98: 1575.5635 | BM98: 1543.1842
A99: Naturgass | B99: 318 | C99: 726 | D99: 611 | E99: 760 | F99: 795 | G99: 333 | H99: 296 | I99: 333 | J99: 334 | K99: 364 | L99: 615 | M99: 632 | N99: 680 | O99: 711 | P99: 1144 | Q99: 1277 | R99: 1286 | S99: 1515 | T99: 1981 | U99: 1921 | V99: 2453.598 | W99: 2540.4938 | X99: 2017.8763 | Y99: 2005.3171 | Z99: 2266.2902 | AA99: 3198.906 | AB99: 3852.9531 | AC99: 4299.9794 | AD99: 4095.907 | AE99: 4319.1696 | AF99: 4395.7014 | AG99: 4453.1843 | AH99: 4104.7984 | AI99: 4116.6451 | AJ99: 4086.1686 | AK99: 4637.9061 | AL99: 3684.4714 | AM99: 3290.0289 | AN99: 3109.3546 | AO99: 2907.8659 | AP99: 2959.4045 | AQ99: 2730.6655 | AR99: 2625.0937 | AS99: 2606.3154 | AT99: 2570.6345 | AU99: 2701.0852 | AV99: 2803.6777 | AW99: 2825.9347 | AX99: 2867.0844 | AY99: 2895.1509 | AZ99: 2858.3462 | BA99: 2767.8009 | BB99: 1816.0605 | BC99: 1864.4114 | BD99: 1772.7246 | BE99: 1701.759 | BF99: 1671.9512 | BG99: 1668.4803 | BH99: 1628.2472 | BI99: 1632.2341 | BJ99: 1618.6986 | BK99: 1683.5024 | BL99: 1748.6502 | BM99: 1792.2459
A100: Samlet | B100: =B98+B99 -> 494 | C100: =C98+C99 -> 1076 | D100: =D98+D99 -> 815 | E100: =E98+E99 -> 1013 | F100: =F98+F99 -> 1060 | G100: =G98+G99 -> 1110 | H100: =H98+H99 -> 986 | I100: =I98+I99 -> 1111 | ... BM100: =BM98+BM99 -> 3335.4301
A101: Kilde: OED (Hva korrigeres det for her?)
A103: Eksport av rørtjenester, mill. kroner
A104: Råolje (+NGL) | B104: 298 | C104: 349 | D104: 356 | E104: 346 | F104: 397 | G104: 387 | H104: 318 | I104: 322 | J104: 361 | K104: 394 | L104: 341 | M104: 382 | N104: 385 | O104: 372 | P104: 317 | Q104: 315 | R104: 329 | S104: 323 | T104: 322 | U104: 367 | V104: 344.97635 | W104: 492.56172 | X104: 627.26876 | Y104: 540.83085 | Z104: 368.678 | AA104: 377.74244 | AB104: 348.76542 | AC104: 374.46841 | AD104: 432.70539 | AE104: 408.52632 | AF104: 406.45702 | AG104: 414.43039 | AH104: 248.31162 | AI104: 185.71937 | AJ104: 170.29871 | AK104: 167.75815 | AL104: 163.24003 | AM104: 162.68428 | AN104: 185.99877 | AO104: 207.38168 | AP104: 255.53944 | AQ104: 262.04316 | AR104: 259.41899 | AS104: 285.20508 | AT104: 266.94654 | AU104: 385.32501 | AV104: 383.67772 | AW104: 377.56395 | AX104: 379.55452 | AY104: 378.04211 | AZ104: 373.74524 | BA104: 364.18166 | BB104: 339.90035 | BC104: 279.05787 | BD104: 268.53431 | BE104: 253.10487 | BF104: 244.58367 | BG104: 237.01135 | BH104: 229.75079 | BI104: 226.8087 | BJ104: 242.34941 | BK104: 248.338 | BL104: 249.1019 | BM104: 252.01968
A105: Naturgass | B105: 2337 | C105: 4065 | D105: 5615 | E105: 4654 | F105: 5325 | G105: 6779 | H105: 6037 | I105: 6114 | J105: 6867 | K105: 7483 | L105: 6479 | M105: 7266 | N105: 7310 | O105: 7060 | P105: 6028 | Q105: 5976 | R105: 6243 | S105: 6141 | T105: 6112 | U105: 6980 | V105: 6554.5507 | W105: 9358.6728 | X105: 11918.106 | Y105: 10275.786 | Z105: 7004.8819 | AA105: 7177.1064 | AB105: 6626.5429 | AC105: 7114.8998 | AD105: 8221.4024 | AE105: 7762.0001 | AF105: 7722.6835 | AG105: 7874.1773 | AH105: 4717.9207 | AI105: 3528.6681 | AJ105: 3235.6755 | AK105: 3187.4048 | AL105: 3101.5605 | AM105: 3091.0014 | AN105: 3533.9766 | AO105: 3940.2519 | AP105: 4855.2494 | AQ105: 4978.8201 | AR105: 4928.9609 | AS105: 5418.8966 | AT105: 5071.9843 | AU105: 7321.1752 | AV105: 7289.8767 | AW105: 7173.715 | AX105: 7211.5358 | AY105: 7182.8002 | AZ105: 7101.1596 | BA105: 6919.4515 | BB105: 6458.1067 | BC105: 5302.0996 | BD105: 5102.1518 | BE105: 4808.9925 | BF105: 4647.0896 | BG105: 4503.2157 | BH105: 4365.2649 | BI105: 4309.3653 | BJ105: 4604.6388 | BK105: 4718.422 | BL105: 4732.936 | BM105: 4788.3739
A106: Samlet | B106: =SUM(B104:B105) -> 2635 | C106: =SUM(C104:C105) -> 4414 | D106: =SUM(D104:D105) -> 5971 | E106: =SUM(E104:E105) -> 5000 | F106: =SUM(F104:F105) -> 5722 | G106: =SUM(G104:G105) -> 7166 | H106: =SUM(H104:H105) -> 6355 | I106: =SUM(I104:I105) -> 6436 | ... BM106: =SUM(BM104:BM105) -> 5040.3936
A107: Kilde: OED
A109: Eksport av rørtjenester. Mill. 2013-kroner
A110: Råolje (+NGL) | B110: =B104/B19 -> 300.79772 | C110: =C104/C19 -> 315.94307 | D110: =D104/D19 -> 284.19757 | E110: =E104/E19 -> 284.46394 | F110: =F104/F19 -> 352.47689 | G110: =G104/G19 -> 332.62186 | H110: =H104/H19 -> 213.696 | I110: =I104/I19 -> 322 | ... BM110: =BM104/BM19 -> 252.01968
A111: Naturgass | B111: =B105/B19 -> 2358.9405 | C111: =C105/C19 -> 3679.9673 | D111: =D105/D19 -> 4482.4981 | E111: =E105/E19 -> 3826.2867 | F111: =F105/F19 -> 4727.8071 | G111: =G105/G19 -> 5826.4692 | H111: =H105/H19 -> 4056.864 | I111: =I105/I19 -> 6114 | ... BM111: =BM105/BM19 -> 4788.3739
A112: Samlet | B112: =SUM(B110:B111) -> 2659.7382 | C112: =SUM(C110:C111) -> 3995.9104 | D112: =SUM(D110:D111) -> 4766.6957 | E112: =SUM(E110:E111) -> 4110.7506 | F112: =SUM(F110:F111) -> 5080.284 | G112: =SUM(G110:G111) -> 6159.091 | H112: =SUM(H110:H111) -> 4270.56 | I112: =SUM(I110:I111) -> 6436 | ... BM112: =SUM(BM110:BM111) -> 5040.3936
A113: Kilde: OED
A115: Volumvekst rørtransport OED | C115: =(C112/B112-1)*100 -> 50.236979 | D115: =(D112/C112-1)*100 -> 19.289354 | E115: =(E112/D112-1)*100 -> -13.761002 | F115: =(F112/E112-1)*100 -> 23.585313 | G115: =(G112/F112-1)*100 -> 21.235171 | H115: =(H112/G112-1)*100 -> -30.662496 | I115: =(I112/H112-1)*100 -> 50.706231 | J115: =(J112/I112-1)*100 -> 12.30578 | ... BM115: =(BM112/BL112-1)*100 -> 1.1713223
A117: Volumvekst rørtransport (hvor kommer disse tallene fra?) | C117: =(C112/B112-1)*100 -> 50.236979 | D117: =(D112/C112-1)*100 -> 19.289354 | E117: =(E112/D112-1)*100 -> -13.761002 | F117: =(F112/E112-1)*100 -> 23.585313 | G117: =(G112/F112-1)*100 -> 21.235171 | H117: =(H112/G112-1)*100 -> -30.662496 | I117: =(I112/H112-1)*100 -> 50.706231 | J117: =(J112/I112-1)*100 -> 12.30578 | ... L117: =(L112/K112-1)*100 -> -13.418814 | M117: 2 | N117: 2 | O117: 2 | P117: 0 | Q117: 0 | R117: 0 | S117: 0 | T117: 0 | U117: 0 | V117: 0 | W117: 0 | X117: 0 | Y117: 0 | Z117: 0 | AA117: 0 | AB117: 0 | AC117: 0 | AD117: 0 | AE117: 0 | AF117: 0 | AG117: 0 | AH117: 0 | AI117: 0 | AJ117: 0 | AK117: 0 | AL117: 0 | AM117: 0 | AN117: 0 | AO117: 0 | AP117: 0 | AQ117: 0 | AR117: 0 | AS117: 0 | AT117: 0 | AU117: 0 | AV117: 0 | AW117: 0 | AX117: 0 | AY117: 0 | AZ117: 0 | BA117: 0 | BB117: 0 | BC117: 0 | BD117: 0 | BE117: 0 | BF117: 0 | BG117: 0 | BH117: 0 | BI117: 0 | BJ117: 0 | BK117: 0 | BL117: 0 | BM117: 0
A120: Produksjonsverdi mill. kr
A121: Olje | B121: =B80-B98-B104 -> 149561.91 | C121: =C80-C98-C104 -> 101775.46 | D121: =D80-D98-D104 -> 142322.01 | E121: =E80-E98-E104 -> 285437.53 | F121: =F80-F98-F104 -> 253045.29 | G121: =G80-G98-G104 -> 215096.65 | H121: =H80-H98-H104 -> 208200.39 | I121: =I80-I98-I104 -> 259983.09 | ... BM121: =BM80-BM98-BM104 -> 245512.23
A122: Gass | B122: =B81-B99-B105 -> 26179 | C122: =C81-C99-C105 -> 25327.4 | D122: =D81-D99-D105 -> 20559 | E122: =E81-E99-E105 -> 41541.7 | F122: =F81-F99-F105 -> 59401.5 | G122: =G81-G99-G105 -> 53175.6 | H122: =H81-H99-H105 -> 57845.4 | I122: =I81-I99-I105 -> 70280 | ... BM122: =BM81-BM99-BM105 -> 133961.03
A123: NGL | B123: =B82 -> 13364.323 | C123: =C82 -> 7653.4612 | D123: =D82 -> 12724.625 | E123: =E82 -> 21706.293 | F123: =F82 -> 25322.478 | G123: =G82 -> 26330.152 | H123: =H82 -> 25438.04 | I123: =I82 -> 29719.775 | ... BM123: =BM82 -> 240.1445
A124: Olje og NGL | B124: =B80+B82-B98-B104 -> 162926.24 | C124: =C80+C82-C98-C104 -> 109428.92 | D124: =D80+D82-D98-D104 -> 155046.64 | E124: =E80+E82-E98-E104 -> 307143.82 | F124: =F80+F82-F98-F104 -> 278367.76 | G124: =G80+G82-G98-G104 -> 241426.8 | H124: =H80+H82-H98-H104 -> 233638.43 | I124: =I80+I82-I98-I104 -> 289702.87 | ... BM124: =BM80+BM82-BM98-BM104 -> 245752.37
A125: Sum | B125: =SUM(B121:B123) -> 189105.24 | C125: =SUM(C121:C123) -> 134756.32 | D125: =SUM(D121:D123) -> 175605.64 | E125: =SUM(E121:E123) -> 348685.52 | F125: =SUM(F121:F123) -> 337769.26 | G125: =SUM(G121:G123) -> 294602.4 | H125: =SUM(H121:H123) -> 291483.83 | I125: =SUM(I121:I123) -> 359982.87 | ... BM125: =SUM(BM121:BM123) -> 379713.4
A127: Produksjonsverdi mill. kr (2013-priser)
A128: Olje | G128: =G121/G40 -> 681139.39 | H128: =H121/H40 -> 649460.92 | I128: =I121/I40 -> 639252.55 | J128: =J121/J40 -> 582207.86 | K128: =K121/K40 -> 536789.57 | L128: =L121/L40 -> 503279.11 | M128: =M121/M40 -> 481642.57 | N128: =N121/N40 -> 450129.47 | ... BM128: =BM121/BM40 -> 109903.23
A129: Gass | G129: =G122/G41 -> 118489.11 | H129: =H122/H41 -> 134753.49 | I129: =I122/I41 -> 148529.9 | J129: =J122/J41 -> 163813.86 | K129: =K122/K41 -> 171626.47 | L129: =L122/L41 -> 174232.63 | M129: =M122/M41 -> 196599.8 | N129: =N122/N41 -> 202735.92 | ... BM129: =BM122/BM41 -> 63705.446
...

Sheet Skiftberegning
A1: INPUT | B1: 2001 | C1: 2002 | D1: 2003 | E1: 2004 | F1: 2005 | G1: 2006 | H1: 2007 | I1: 2008 | J1: 2009 | K1: 2010 | L1: 2011 | M1: 2012 | N1: 2013 | O1: 2014 | P1: 2015 | Q1: 2016 | R1: 2017 | S1: 2018 | T1: 2019 | U1: 2020 | V1: 2021 | W1: 2022 | X1: 2023 | Y1: 2024 | Z1: 2025 | AA1: 2026 | AB1: 2027 | AC1: 2028 | AD1: 2029 | AE1: 2030 | AF1: 2031 | AG1: 2032 | AH1: 2033 | AI1: 2034 | AJ1: 2035 | AK1: 2036 | AL1: 2037 | AM1: 2038 | AN1: 2039 | AO1: 2040 | AP1: 2041 | AQ1: 2042 | AR1: 2043 | AS1: 2044 | AT1: 2045 | AU1: 2046 | AV1: 2047 | AW1: 2048 | AX1: 2049 | AY1: 2050 | AZ1: 2051 | BA1: 2052 | BB1: 2053 | BC1: 2054 | BD1: 2055 | BE1: 2056 | BF1: 2057 | BG1: 2058 | BH1: 2059 | BI1: 2060 | BJ1: 2061 | BK1: 2062 | BL1: 2063 | BM1: 2064 | BN1: 2065 | BO1: 2066 | BP1: 2067 | BQ1: 2068 | BR1: 2069 | BS1: 2070 | BT1: 2071 | BU1: 2072 | BV1: 2073 | BW1: 2074 | BX1: 2075 | BY1: 2076 | BZ1: 2077 | CA1: 2078 | CB1: 2079 | CC1: 2080 | CD1: 2081 | CE1: 2082 | CF1: 2083 | CG1: 2084 | CH1: 2085 | CI1: 2086 | CJ1: 2087 | CK1: 2088 | CL1: 2089 | CM1: 2090
A2: Oljepris i referansebane | B2: =KVARTS!F5 -> 223 | C2: =KVARTS!G5 -> 198 | D2: =KVARTS!H5 -> 201 | E2: =KVARTS!I5 -> 255 | F2: =KVARTS!J5 -> 355 | G2: =KVARTS!K5 -> 423 | H2: =KVARTS!L5 -> 425 | I2: =KVARTS!M5 -> 556 | ... BI2: =KVARTS!BM5 -> 1400.6518 | BJ2: =BI2*(1+Formue!BK43/100) -> 1428.6649 | BK2: =BJ2*(1+Formue!BL43/100) -> 1457.2382 | BL2: =BK2*(1+Formue!BM43/100) -> 1486.3829 | BM2: =BL2*(1+Formue!BN43/100) -> 1516.1106 | BN2: =BM2*(1+Formue!BO43/100) -> 1546.4328 | BO2: =BN2*(1+Formue!BP43/100) -> 1577.3615 | BP2: =BO2*(1+Formue!BQ43/100) -> 1608.9087 | BQ2: =BP2*(1+Formue!BR43/100) -> 1641.0869 | ... CM2: =CL2*(1+Formue!CN43/100) -> 2537.0869
A3: Endring i oljepris | Q3: 0 | R3: 0 | S3: 0 | T3: 0 | U3: 0 | V3: 0
A4: Oljepris i skiftberegning | B4: =B2-B3 -> 223 | C4: =C2-C3 -> 198 | D4: =D2-D3 -> 201 | E4: =E2-E3 -> 255 | F4: =F2-F3 -> 355 | G4: =G2-G3 -> 423 | H4: =H2-H3 -> 425 | I4: =I2-I3 -> 556 | ... CM4: =CM2-CM3 -> 2537.0869
A5: Gasspris i ref. beregning (kroner pr. Sm3) | B5: =KVARTS!F6 -> 1.21 | C5: =KVARTS!G6 -> 0.92 | D5: =KVARTS!H6 -> 0.88 | E5: =KVARTS!I6 -> 0.97 | F5: =KVARTS!J6 -> 1.25 | G5: =KVARTS!K6 -> 1.74 | H5: =KVARTS!L6 -> 1.57 | I5: =KVARTS!M6 -> 2.22 | ... BI5: =KVARTS!BM6 -> 4.3107792 | BJ5: =BI5*(1+Formue!BK43/100) -> 4.3969948 | BK5: =BJ5*(1+Formue!BL43/100) -> 4.4849347 | BL5: =BK5*(1+Formue!BM43/100) -> 4.5746334 | BM5: =BL5*(1+Formue!BN43/100) -> 4.6661261 | BN5: =BM5*(1+Formue!BO43/100) -> 4.7594486 | BO5: =BN5*(1+Formue!BP43/100) -> 4.8546376 | BP5: =BO5*(1+Formue!BQ43/100) -> 4.9517303 | BQ5: =BP5*(1+Formue!BR43/100) -> 5.0507649 | ... CM5: =CL5*(1+Formue!CN43/100) -> 7.8083799
A6: NGL-pris (kroner pr. Sm3 oe) | B6: =KVARTS!F8 -> 1526.37 | C6: =KVARTS!G8 -> 1377.1 | D6: =KVARTS!H8 -> 1093.1689 | E6: =KVARTS!I8 -> 1332.128 | F6: =KVARTS!J8 -> 1847.0464 | G6: =KVARTS!K8 -> 1965.5889 | H6: =KVARTS!L8 -> 1814.6526 | I6: =KVARTS!M8 -> 2521.0891 | ... BI6: =KVARTS!BM8 -> 5111.4616 | BJ6: =BI6*(1+Formue!BK43/100) -> 5213.6909 | BK6: =BJ6*(1+Formue!BL43/100) -> 5317.9647 | BL6: =BK6*(1+Formue!BM43/100) -> 5424.324 | BM6: =BL6*(1+Formue!BN43/100) -> 5532.8104 | BN6: =BM6*(1+Formue!BO43/100) -> 5643.4667 | BO6: =BN6*(1+Formue!BP43/100) -> 5756.336 | BP6: =BO6*(1+Formue!BQ43/100) -> 5871.4627 | BQ6: =BP6*(1+Formue!BR43/100) -> 5988.892 | ... CM6: =CL6*(1+Formue!CN43/100) -> 9258.7052
A7: Marginalskattesats | B7: 0.76 | C7: 0.78 | D7: 0.78 | E7: 0.78 | F7: 0.78 | G7: 0.78 | H7: 0.78 | I7: 0.78 | J7: 0.78 | K7: 0.78 | L7: 0.78 | M7: 0.78 | N7: 0.78 | O7: 0.78 | P7: 0.78 | Q7: 0.78 | R7: 0.78 | S7: 0.78 | T7: 0.78 | U7: 0.78 | V7: 0.78 | W7: 0.78 | X7: 0.78 | Y7: 0.78 | Z7: 0.78 | AA7: 0.78 | AB7: 0.78 | AC7: 0.78 | AD7: 0.78 | AE7: 0.78 | AF7: 0.78 | AG7: 0.78 | AH7: 0.78 | AI7: 0.78 | AJ7: 0.78 | AK7: 0.78 | AL7: 0.78 | AM7: 0.78 | AN7: 0.78 | AO7: 0.78 | AP7: 0.78 | AQ7: 0.78 | AR7: 0.78 | AS7: 0.78 | AT7: 0.78 | AU7: 0.78 | AV7: 0.78 | AW7: 0.78 | AX7: 0.78 | AY7: 0.78 | AZ7: 0.78 | BA7: 0.78 | BB7: 0.78 | BC7: 0.78 | BD7: 0.78 | BE7: 0.78 | BF7: 0.78 | BG7: 0.78 | BH7: 0.78 | BI7: 0.78 | BJ7: 0.78 | BK7: 0.78 | BL7: 0.78 | BM7: 0.78 | BN7: 0.78 | BO7: 0.78 | BP7: 0.78 | BQ7: 0.78 | BR7: 0.78 | BS7: 0.78 | BT7: 0.78 | BU7: 0.78 | BV7: 0.78 | BW7: 0.78 | BX7: 0.78 | BY7: 0.78 | BZ7: 0.78 | CA7: 0.78 | CB7: 0.78 | CC7: 0.78 | CD7: 0.78 | CE7: 0.78 | CF7: 0.78 | CG7: 0.78 | CH7: 0.78 | CI7: 0.78 | CJ7: 0.78 | CK7: 0.78 | CL7: 0.78 | CM7: 0.78
A8: Påløpt produksjonsavgift i referanseberegning | H8: =SNKS!B9 -> 0 | I8: =SNKS!C9 -> 0 | J8: =SNKS!D9 -> 0 | K8: =SNKS!E9 -> 0 | L8: =SNKS!F9 -> 0 | M8: =SNKS!G9 -> 0 | N8: =SNKS!H9 -> 0 | O8: =SNKS!I9 -> 0 | ... BI8: =SNKS!BC9 -> 0 | BJ8: 0 | BK8: 0 | BL8: 0 | BM8: 0 | BN8: 0 | BO8: 0 | BP8: 0 | BQ8: 0 | BR8: 0 | BS8: 0 | BT8: 0 | BU8: 0 | BV8: 0 | BW8: 0 | BX8: 0 | BY8: 0 | BZ8: 0 | CA8: 0 | CB8: 0 | CC8: 0 | CD8: 0 | CE8: 0 | CF8: 0 | CG8: 0 | CH8: 0 | CI8: 0 | CJ8: 0 | CK8: 0 | CL8: 0 | CM8: 0
A9: Råoljeproduksjon i Sm3 oe | B9: =KVARTS!F62 -> 180.88 | C9: =KVARTS!G62 -> 173.65 | D9: =KVARTS!H62 -> 165.48 | E9: =KVARTS!I62 -> 162.78 | F9: =KVARTS!J62 -> 148.14 | G9: =KVARTS!K62 -> 136.58 | H9: =KVARTS!L62 -> 128.28 | I9: =KVARTS!M62 -> 122.66 | ... BI9: =KVARTS!BM62 -> 28.071747 | BJ9: =BI9*(1+Formue!$C$8) -> 28.73893 | BK9: =BJ9*(1+Formue!$C$8) -> 29.42197 | BL9: =BK9*(1+Formue!$C$8) -> 30.121244 | BM9: =BL9*(1+Formue!$C$8) -> 30.837138 | BN9: =BM9*(1+Formue!$C$8) -> 31.570047 | BO9: =BN9*(1+Formue!$C$8) -> 32.320374 | BP9: =BO9*(1+Formue!$C$8) -> 33.088535 | BQ9: =BP9*(1+Formue!$C$8) -> 33.874952 | ... CM9: =CL9*(1+Formue!$C$8) -> 56.794219
A10: Gassproduksjon i Sm3 oe | B10: =KVARTS!F63 -> 54.15 | C10: =KVARTS!G63 -> 65.53 | D10: =KVARTS!H63 -> 72.93 | E10: =KVARTS!I63 -> 79.1 | F10: =KVARTS!J63 -> 85.67 | G10: =KVARTS!K63 -> 88.23 | H10: =KVARTS!L63 -> 89.51 | I10: =KVARTS!M63 -> 99.46 | ... BI10: =KVARTS!BM63 -> 32.602377 | BJ10: =BI10*(1+Formue!$C$9) -> 32.893795 | BK10: =BJ10*(1+Formue!$C$9) -> 33.187818 | BL10: =BK10*(1+Formue!$C$9) -> 33.484469 | BM10: =BL10*(1+Formue!$C$9) -> 33.783771 | BN10: =BM10*(1+Formue!$C$9) -> 34.085749 | BO10: =BN10*(1+Formue!$C$9) -> 34.390426 | BP10: =BO10*(1+Formue!$C$9) -> 34.697826 | BQ10: =BP10*(1+Formue!$C$9) -> 35.007974 | ... CM10: =CL10*(1+Formue!$C$9) -> 42.578532
A11: NGL produksjon Sm3 oe | B11: =KVARTS!F64 -> 16.59 | C11: =KVARTS!G64 -> 19.12 | D11: =KVARTS!H64 -> 23.27 | E11: =KVARTS!I64 -> 22.31 | F11: =KVARTS!J64 -> 23.76 | G11: =KVARTS!K64 -> 24.33 | H11: =KVARTS!L64 -> 19.76 | I11: =KVARTS!M64 -> 20.86 | ... BI11: =KVARTS!BM64 -> 0.046981571 | BJ11: =BI11*(1+Formue!$C$10) -> 0.10282023 | BK11: =BJ11*(1+Formue!$C$10) -> 0.22502442 | BL11: =BK11*(1+Formue!$C$10) -> 0.49247104 | BM11: =BL11*(1+Formue!$C$10) -> 1.0777841 | BN11: =BM11*(1+Formue!$C$10) -> 2.3587549 | BO11: =BN11*(1+Formue!$C$10) -> 5.1621886 | BP11: =BO11*(1+Formue!$C$10) -> 11.297567 | BQ11: =BP11*(1+Formue!$C$10) -> 24.724982 | ... CM11: =CL11*(1+Formue!$C$10) -> 7.5241804e+08
A12: Eksport av råolje (Sm3 o.e.) | B12: =KVARTS!F168 -> 172.94334 | C12: =KVARTS!G168 -> 165.71334 | D12: =KVARTS!H168 -> 157.54334 | E12: =KVARTS!I168 -> 154.84334 | F12: =KVARTS!J168 -> 140.20334 | G12: =KVARTS!K168 -> 121.83889 | H12: =KVARTS!L168 -> 113.69725 | I12: =KVARTS!M168 -> 109.80879 | ... BI12: =KVARTS!BM168 -> 28.071747 | BJ12: =BJ9*($AE$12/$AE$9) -> 22.440071 | BK12: =BK9*($AE$12/$AE$9) -> 22.973406 | BL12: =BL9*($AE$12/$AE$9) -> 23.519417 | BM12: =BM9*($AE$12/$AE$9) -> 24.078404 | BN12: =BN9*($AE$12/$AE$9) -> 24.650677 | BO12: =BO9*($AE$12/$AE$9) -> 25.236552 | BP12: =BP9*($AE$12/$AE$9) -> 25.836351 | BQ12: =BQ9*($AE$12/$AE$9) -> 26.450405 | ... CM12: =CM9*($AE$12/$AE$9) -> 44.346338
A13: Eksport av gass (Sm3.o.e) | B13: =KVARTS!F169 -> 54.15 | C13: =KVARTS!G169 -> 65.53 | D13: =KVARTS!H169 -> 72.93 | E13: =KVARTS!I169 -> 79.1 | F13: =KVARTS!J169 -> 85.67 | G13: =KVARTS!K169 -> 88.23 | H13: =KVARTS!L169 -> 88.51 | I13: =KVARTS!M169 -> 98.46 | ... BI13: =KVARTS!BM169 -> 32.602377 | BJ13: =BJ10*($AE$13/$AE$10) -> 32.392277 | BK13: =BK10*($AE$13/$AE$10) -> 32.681817 | BL13: =BL10*($AE$13/$AE$10) -> 32.973945 | BM13: =BM10*($AE$13/$AE$10) -> 33.268684 | BN13: =BN10*($AE$13/$AE$10) -> 33.566058 | BO13: =BO10*($AE$13/$AE$10) -> 33.86609 | BP13: =BP10*($AE$13/$AE$10) -> 34.168803 | BQ13: =BQ10*($AE$13/$AE$10) -> 34.474222 | ... CM13: =CM10*($AE$13/$AE$10) -> 41.929355
A14: Eksport av NGL (Sm3 o.e.) | B14: =KVARTS!F170 -> 2.68 | C14: =KVARTS!G170 -> 2.72 | D14: =KVARTS!H170 -> 3.32 | E14: =KVARTS!I170 -> 20.08 | F14: =KVARTS!J170 -> 21.53 | G14: =KVARTS!K170 -> 22.1 | H14: =KVARTS!L170 -> 17.53 | I14: =KVARTS!M170 -> 18.63 | ... BI14: =KVARTS!BM170 -> 0.046981571 | BJ14: =BJ11*($AE$14/$AE$11) -> 0.071439394 | BK14: =BK11*($AE$14/$AE$11) -> 0.15634674 | BL14: =BL11*($AE$14/$AE$11) -> 0.34216838 | BM14: =BM11*($AE$14/$AE$11) -> 0.74884327 | BN14: =BN11*($AE$14/$AE$11) -> 1.6388605 | BO14: =BO11*($AE$14/$AE$11) -> 3.5866834 | BP14: =BP11*($AE$14/$AE$11) -> 7.849538 | BQ14: =BQ11*($AE$14/$AE$11) -> 17.178892 | ... CM14: =CM11*($AE$14/$AE$11) -> 5.2277929e+08
A15: Omregning sm3=> fat | B15: =KVARTS!F16 -> 6.28981 | C15: =KVARTS!G16 -> 6.28981 | D15: =KVARTS!H16 -> 6.28981 | E15: =KVARTS!I16 -> 6.28981 | F15: =KVARTS!J16 -> 6.28981 | G15: =KVARTS!K16 -> 6.28981 | H15: =KVARTS!L16 -> 6.28981 | I15: =KVARTS!M16 -> 6.28981 | ... BI15: =KVARTS!BM16 -> 6.28981 | BJ15: =BI15 -> 6.28981 | BK15: =BJ15 -> 6.28981 | BL15: =BK15 -> 6.28981 | BM15: =BL15 -> 6.28981 | BN15: =BM15 -> 6.28981 | BO15: =BN15 -> 6.28981 | BP15: =BO15 -> 6.28981 | BQ15: =BP15 -> 6.28981 | ... CM15: =CL15 -> 6.28981
A16: Omregning Sm3 o.e.=> Sm3 | B16: 1000 | C16: 1000 | D16: 1000 | E16: 1000 | F16: 1000 | G16: 1000 | H16: 1000 | I16: 1000 | J16: 1000 | K16: 1000 | L16: 1000 | M16: 1000 | N16: 1000 | O16: 1000 | P16: 1000 | Q16: 1000 | R16: 1000 | S16: 1000 | T16: 1000 | U16: 1000 | V16: 1000 | W16: 1000 | X16: 1000 | Y16: 1000 | Z16: 1000 | AA16: 1000 | AB16: 1000 | AC16: 1000 | AD16: 1000 | AE16: 1000 | AF16: 1000 | AG16: 1000 | AH16: 1000 | AI16: 1000 | AJ16: 1000 | AK16: 1000 | AL16: 1000 | AM16: 1000 | AN16: 1000 | AO16: 1000 | AP16: 1000 | AQ16: 1000 | AR16: 1000 | AS16: 1000 | AT16: 1000 | AU16: 1000 | AV16: 1000 | AW16: 1000 | AX16: 1000 | AY16: 1000 | AZ16: 1000 | BA16: 1000 | BB16: 1000 | BC16: 1000 | BD16: 1000 | BE16: 1000 | BF16: 1000 | BG16: 1000 | BH16: 1000 | BI16: 1000 | BJ16: 1000 | BK16: 1000 | BL16: 1000 | BM16: 1000 | BN16: 1000 | BO16: 1000 | BP16: 1000 | BQ16: 1000 | BR16: 1000 | BS16: 1000 | BT16: 1000 | BU16: 1000 | BV16: 1000 | BW16: 1000 | BX16: 1000 | BY16: 1000 | BZ16: 1000 | CA16: 1000 | CB16: 1000 | CC16: 1000 | CD16: 1000 | CE16: 1000 | CF16: 1000 | CG16: 1000 | CH16: 1000 | CI16: 1000 | CJ16: 1000 | CK16: 1000 | CL16: 1000 | CM16: 1000
A17: Gassprisgjennomslag | B17: 0.5 | C17: 0.5 | D17: 0.5 | E17: 0.5 | F17: 0.5 | G17: 0.5 | H17: 0.5 | I17: 0.5 | J17: 0.5 | K17: 0.5 | L17: 0.5 | M17: 0.5 | N17: 0.5 | O17: 0.5 | P17: 0.5 | Q17: 0.5 | R17: 0.5 | S17: 0.5 | T17: 0.5 | U17: 0.5 | V17: 0.5 | W17: 0.5 | X17: 0.5 | Y17: 0.5 | Z17: 0.5 | AA17: 0.5 | AB17: 0.5 | AC17: 0.5 | AD17: 0.5 | AE17: 0.5 | AF17: 0.5 | AG17: 0.5 | AH17: 0.5 | AI17: 0.5 | AJ17: 0.5 | AK17: 0.5 | AL17: 0.5 | AM17: 0.5 | AN17: 0.5 | AO17: 0.5 | AP17: 0.5 | AQ17: 0.5 | AR17: 0.5 | AS17: 0.5 | AT17: 0.5 | AU17: 0.5 | AV17: 0.5 | AW17: 0.5 | AX17: 0.5 | AY17: 0.5 | AZ17: 0.5 | BA17: 0.5 | BB17: 0.5 | BC17: 0.5 | BD17: 0.5 | BE17: 0.5 | BF17: 0.5 | BG17: 0.5 | BH17: 0.5 | BI17: 0.5 | BJ17: 0.5 | BK17: 0.5 | BL17: 0.5 | BM17: 0.5 | BN17: 0.5 | BO17: 0.5 | BP17: 0.5 | BQ17: 0.5 | BR17: 0.5 | BS17: 0.5 | BT17: 0.5 | BU17: 0.5 | BV17: 0.5 | BW17: 0.5 | BX17: 0.5 | BY17: 0.5 | BZ17: 0.5 | CA17: 0.5 | CB17: 0.5 | CC17: 0.5 | CD17: 0.5 | CE17: 0.5 | CF17: 0.5 | CG17: 0.5 | CH17: 0.5 | CI17: 0.5 | CJ17: 0.5 | CK17: 0.5 | CL17: 0.5 | CM17: 0.5
A18: SDØEs produksjon i Sm3 o.e.:
A19: Råolje | B19: =Petoro!G87 -> 65 | C19: =Petoro!H87 -> 56 | D19: =Petoro!I87 -> 50.24 | E19: =Petoro!J87 -> 48.98 | F19: =Petoro!K87 -> 42.86 | G19: =Petoro!L87 -> 37.6 | H19: =Petoro!M87 -> 33.6 | I19: =Petoro!N87 -> 30.2 | ... BI19: =Petoro!BN87 -> 3.1099787 | BJ19: =BJ9*($AE$19/$AE$9) -> 4.6911181 | BK19: =BK9*($AE$19/$AE$9) -> 4.8026122 | BL19: =BL9*($AE$19/$AE$9) -> 4.9167562 | BM19: =BM9*($AE$19/$AE$9) -> 5.0336131 | BN19: =BN9*($AE$19/$AE$9) -> 5.1532474 | BO19: =BO9*($AE$19/$AE$9) -> 5.275725 | BP19: =BP9*($AE$19/$AE$9) -> 5.4011135 | BQ19: =BQ9*($AE$19/$AE$9) -> 5.5294821 | ... CM19: =CM9*($AE$19/$AE$9) -> 9.2706439
A20: Gass | B20: =Petoro!G88 -> 22 | C20: =Petoro!H88 -> 22 | D20: =Petoro!I88 -> 24 | E20: =Petoro!J88 -> 24.96 | F20: =Petoro!K88 -> 28.1 | G20: =Petoro!L88 -> 33.8 | H20: =Petoro!M88 -> 32.5 | I20: =Petoro!N88 -> 34.7 | ... BI20: =Petoro!BN88 -> 3.2076143 | BJ20: =BJ10*($AE$20/$AE$10) -> 10.855956 | BK20: =BK10*($AE$20/$AE$10) -> 10.952993 | BL20: =BL10*($AE$20/$AE$10) -> 11.050897 | BM20: =BM10*($AE$20/$AE$10) -> 11.149676 | BN20: =BN10*($AE$20/$AE$10) -> 11.249337 | BO20: =BO10*($AE$20/$AE$10) -> 11.34989 | BP20: =BP10*($AE$20/$AE$10) -> 11.451342 | BQ20: =BQ10*($AE$20/$AE$10) -> 11.5537 | ... CM20: =CM10*($AE$20/$AE$10) -> 14.052215
A21: NGL | B21: =Petoro!G89 -> 3.8 | C21: =Petoro!H89 -> 3.9 | D21: =Petoro!I89 -> 4.39 | E21: =Petoro!J89 -> 4.22 | F21: =Petoro!K89 -> 4.49 | G21: =Petoro!L89 -> 5.4 | H21: =Petoro!M89 -> 4 | I21: =Petoro!N89 -> 4 | ... BI21: =Petoro!BN89 -> 1.9557774e-09 | BJ21: =BJ11*($AE$21/$AE$11) -> 0.014440903 | BK21: =BK11*($AE$21/$AE$11) -> 0.031604244 | BL21: =BL11*($AE$21/$AE$11) -> 0.069166605 | BM21: =BM11*($AE$21/$AE$11) -> 0.15137268 | BN21: =BN11*($AE$21/$AE$11) -> 0.33128256 | BO21: =BO11*($AE$21/$AE$11) -> 0.72501939 | BP21: =BP11*($AE$21/$AE$11) -> 1.5867214 | BQ21: =BQ11*($AE$21/$AE$11) -> 3.4725758 | ... CM21: =CM11*($AE$21/$AE$11) -> 1.0567566e+08
A24: BEREGNING
A25: Pst. vis endring i olje- og NGL pris | B25: =B4/B2-1 -> 0 | C25: =C4/C2-1 -> 0 | D25: =D4/D2-1 -> 0 | E25: =E4/E2-1 -> 0 | F25: =F4/F2-1 -> 0 | G25: =G4/G2-1 -> 0 | H25: =H4/H2-1 -> 0 | I25: =I4/I2-1 -> 0 | ... CM25: =CM4/CM2-1 -> 0
A26: Pst.vis endring i gasspris | B26: =B25*B17 -> 0 | C26: =B25*B17+C25*C17 -> 0 | D26: =C25*C17+D25*D17 -> 0 | E26: =D25*D17+E25*E17 -> 0 | F26: =E25*E17+F25*F17 -> 0 | G26: =F25*F17+G25*G17 -> 0 | H26: =G25*G17+H25*H17 -> 0 | I26: =H25*H17+I25*I17 -> 0 | J26: =I25*I17+J25*J17 -> 0 | ... CM26: =CL25*CL17+CM25*CM17 -> 0
A28: Oljeproduksjon i millioner fat | B28: =B9*$B$15 -> 1137.7008 | C28: =C9*$B$15 -> 1092.2255 | D28: =D9*$B$15 -> 1040.8378 | E28: =E9*$B$15 -> 1023.8553 | F28: =F9*$B$15 -> 931.77245 | G28: =G9*$B$15 -> 859.06225 | H28: =H9*$B$15 -> 806.85683 | I28: =I9*$B$15 -> 771.50809 | ... CM28: =CM9*$B$15 -> 357.22485
A30: Markedsverdi:
A31: Olje | B31: =B2*B28 -> 253707.29 | C31: =C2*C28 -> 216260.65 | D31: =D2*D28 -> 209208.39 | E31: =E2*E28 -> 261083.09 | F31: =F2*F28 -> 330779.22 | G31: =G2*G28 -> 363383.33 | H31: =H2*H28 -> 342914.15 | I31: =I2*I28 -> 428958.5 | ... CM31: =CM2*CM28 -> 906310.5
A32: NGL | B32: =B6*B11 -> 25322.478 | C32: =C6*C11 -> 26330.152 | D32: =D6*D11 -> 25438.04 | E32: =E6*E11 -> 29719.775 | F32: =F6*F11 -> 43885.823 | G32: =G6*G11 -> 47822.778 | H32: =H6*H11 -> 35857.535 | I32: =I6*I11 -> 52589.919 | ... CM32: =CM6*CM11 -> 6.9664168e+12
A33: Olje og NGL | B33: =SUM(B31:B32) -> 279029.76 | C33: =SUM(C31:C32) -> 242590.8 | D33: =SUM(D31:D32) -> 234646.43 | E33: =SUM(E31:E32) -> 290802.87 | F33: =SUM(F31:F32) -> 374665.04 | G33: =SUM(G31:G32) -> 411206.11 | H33: =SUM(H31:H32) -> 378771.69 | I33: =SUM(I31:I32) -> 481548.42 | ... CM33: =SUM(CM31:CM32) -> 6.9664178e+12
A34: Gass | B34: =B5*B10*B16 -> 65521.5 | C34: =C5*C10*C16 -> 60287.6 | D34: =D5*D10*D16 -> 64178.4 | E34: =E5*E10*E16 -> 76727 | F34: =F5*F10*F16 -> 107087.5 | G34: =G5*G10*G16 -> 153520.2 | H34: =H5*H10*H16 -> 140530.7 | I34: =I5*I10*I16 -> 220801.2 | ... CM34: =CM5*CM10*CM16 -> 332469.35
A36: SDØEs andel av produksjon
A37: Olje | B37: =B19/B9 -> 0.35935427 | C37: =C19/C9 -> 0.32248776 | D37: =D19/D9 -> 0.30360164 | E37: =E19/E9 -> 0.30089692 | F37: =F19/F9 -> 0.28932091 | G37: =G19/G9 -> 0.27529653 | H37: =H19/H9 -> 0.26192703 | I37: =I19/I9 -> 0.24620903 | ... CM37: =CM19/CM9 -> 0.16323217
A38: Gass | B38: =B20/B10 -> 0.40627886 | C38: =C20/C10 -> 0.3357241 | D38: =D20/D10 -> 0.32908268 | E38: =E20/E10 -> 0.31554994 | F38: =F20/F10 -> 0.3280028 | G38: =G20/G10 -> 0.38308965 | H38: =H20/H10 -> 0.36308792 | I38: =I20/I10 -> 0.34888397 | ... CM38: =CM20/CM10 -> 0.33003052
